Workbook
Name _ftn1: 'Harms table'!#REF!
Name _ftn2: 'Harms table'!#REF!
Name _ftn3: 'sales tables'!$B$21
Name _ftn4: 'sales tables'!$B$22
Name _ftn5: 'sales tables'!$B$23
Name _ftnref1: 'Harms table'!$I$6
Name _ftnref2: 'Harms table'!$I$23
Name _ftnref4: 'sales tables'!$B$12
Name _ftnref5: 'sales tables'!$B$15

Sheet Config
A1: PSUR Complaint & Sales Surveillance Workbook
A2: Configuration & Instructions
A4: ⚙️ CONFIGURATION
F5: Occurrence Rate Scale (RACT Standard)
B6: Setting | C6: Value | D6: Notes | F6: Occurrence Code | G6: Rate Range | H6: Max Expected Rate
B7: Product / Device Name | C7: Global® Total® for Fertilization | D7: e.g., ALLY UPS Micropipettes | F7: O5 | G7: OHarm > 10% | H7: 1
B8: Surveillance Start Date | C8: 44743 | D8: First day of surveillance (e.g., 01/04/2022) | F8: O4 | G8: 1% < OHarm ≤ 10% | H8: 0.1
B9: Surveillance End Date | C9: 45838 | D9: Last day of surveillance window | F9: O3 | G9: 0.1% < OHarm ≤ 1% | H9: 0.01
B10: Update Frequency | C10: Annual | D10: Enter: Annual or Biennial | F10: O2 | G10: 0.01% < OHarm ≤ 0.1% | H10: 0.001
B11: Historical Data Start Date | D11: Optional – First day of historical period (leave blank if none)
B12: Historical Data End Date | D12: Optional – Last day of historical period (should precede Surveillance Start)
A14: 📋 PSUR COVER PAGE METADATA
B15: Manufacturer Information | C15: Value | D15: Notes
B16: Company Name | C16: CooperSurgical, Inc. | D16: Pre-filled from PSUR template (static)
B17: Company Address | C17: CooperSurgical, Inc., 95 Corporate Drive, Trumbull, CT 06611, United States of America | D17: Pre-filled from PSUR template (static)
B18: Manufacturer SRN | C18: US-MF-000002607 | D18: Pre-filled from PSUR template (static)
B19: Authorized Representative | C19: CooperSurgical Distribution B.V., Celsiusweg 35, 5928 PR Venlo, The Netherlands | D19: Pre-filled from PSUR template (static)
B20: AR SRN | C20: NL-AR-0000000059 | D20: Pre-filled from PSUR template (static)
B21: Notified Body Name | C21: BSI Group The Netherlands B.V. | D21: Pre-filled from PSUR template (static)
B22: Notified Body Number | C22: 2797 | D22: Pre-filled from PSUR template (static)
B23: Certificate Number | C23: N/A - Not Under EU MDR | D23: User input — Certificate number (varies per PSUR cycle)
B25: Device Information | C25: Value | D25: Notes
B26: Basic UDI-DI | C26: N/A - Not Under EU MDR | D26: Basic Unique Device Identification
B27: Device Trade Name | C27: =IF(C7="","",C7) -> Global® Total® for Fertilization | D27: Auto-linked from Product Name above
B28: EMDN Code | C28: N/A - Not Under EU MDR | D28: European Medical Device Nomenclature code
B29: GMDN Code | C29: N/A - Not Under EU MDR | D29: Global Medical Device Nomenclature code
B30: Device Risk Class | C30: Iib | D30: MDR Classification (I, IIa, IIb, III)
B31: Data Collection Period | C31: =IF(OR(C8="",C9=""),"",TEXT(C8,"dd-mmm-yyyy")&" to "&TEXT(C9,"dd-mmm-yyyy")) -> 01-Jul-2022 to 30-Jun-2025 | D31: Auto-calculated from surveillance dates above
B32: PSUR Cadence | C32: =IF(C10="","",C10) -> Annual | D32: Auto-linked from Update Frequency above
B33: ⬆ BLUE cells with YELLOW background = User inputs | GREEN text = Auto-linked from settings above | F33: O1 | G33: OHarm ≤ 0.01% | H33: 0.0001
F35: Auto-calculated in the Harms table columns I & J based on actual complaint rates.
A38: 📖 DATA ENTRY INSTRUCTIONS
B40: OVERVIEW
B41: This workbook automates PSUR (Periodic Safety Update Report) surveillance. You only enter data in TWO sheets — all other tabs auto-calculate.
B43: WORKBOOK STRUCTURE
B44: Sheet | C44: Type | D44: Description
B45: Config (this sheet) | C45: ⚙️ Settings | D45: Surveillance settings, RACT values, and this instruction guide
B46: complaints | C46: ✏️ INPUT | D46: Enter complaint records in columns A–D. Columns E–F auto-populate.
B47: Sales | C47: ✏️ INPUT | D47: Enter sales data in columns A–D (Country, Month, Quantity, Year).
B48: Harms table | C48: 🔒 AUTO | D48: Complaint rates by Medical Device Problem — annual & biennial tables (protected)
B49: Complaint Rate | C49: 🔒 AUTO | D49: Monthly complaint rate trend with control chart (SPC) — includes line chart (protected)
B50: sales tables | C50: 🔒 AUTO | D50: Regional & monthly sales breakdowns with trend chart (protected)
B52: COMPLAINTS SHEET — Data Entry Guide
B53: Enter data in columns A–D (complaint data) and H–I (investigation data). Columns E, F, G are auto-generated formulas — DO NOT edit them.
B54: Column | C54: Format | D54: Details
B55: A — Complaint Number | C55: Text | D55: Required. Unique ID (e.g., 2022-04-0000169). Triggers all data-existence checks.
B56: B — CSI Notification Date | C56: Date | D56: Required. Must be an Excel date value (not text). Drives Complaint Rate chart and Harms table date filtering.
B57: C — Description | C57: Text | D57: Optional. Free-text. Used as fallback for MDP classification if column D is blank (keyword matching).
B58: D — Symptom Code | C58: Text (lowercase) | D58: Recommended. Must match a code from the lookup table (see accepted codes below).
B59: E — Medical Device Problem | C59: 🔒 Auto | D59: Auto-derived from column D (VLOOKUP) or column C (keyword matching). DO NOT EDIT.
B60: F — Harm | C60: 🔒 Auto | D60: Auto-populated: "No Clinical Signs, Symptoms or Conditions" when column E has a value.
B61: G — IMDRF MDP Code | C61: 🔒 Auto | D61: Auto-derived IMDRF Annex A code from column E MDP term via Codes sheet lookup. DO NOT EDIT.
B62: H — Investigation Findings | C62: ✏️ Dropdown | D62: IMDRF Annex C cause category (C01–C13). Select from dropdown. Feeds Section D Table 3.
B63: I — Investigation Conclusion | C63: ✏️ Dropdown | D63: IMDRF Annex D conclusion (D01–D05). Select from dropdown. Feeds Section D Table 4.
B65: Maximum 927 complaint rows (rows 2–928).
B67: ACCEPTED SYMPTOM CODES (Column D)
B68: Symptom Code | C68: Maps To (MDP) | E68: Symptom Code | F68: Maps To (MDP)
B69: alignmentissues | C69: Defective Device | E69: labeling | F69: Device Markings/Labelling Problem
B70: bent | C70: Material Twisted/Bent | E70: laceration | F70: Defective Device
B71: brokenbutton | C71: Break | E71: leak | F71: Fluid/Blood Leak
B72: brokenhandle | C72: Break | E72: lowpressure | F72: Detachment of Device or Device Component
B73: brokenordamagedcomponent | C73: Break | E73: missingcomponent | F73: Component Missing
B74: cannotbeadjusted | C74: Defective Device | E74: other | F74: Appropriate Device Problem Term/Code Not Available
B75: componentseparation | C75: Material Separation | E75: performance | F75: Defective Device
B76: connectionissues | C76: Loose or Intermittent Connection | E76: powerissues | F76: Complete Loss of Power
B77: damagedpackaging | C77: Packaging Problem | E77: pressureissues | F77: Detachment of Device or Device Component
B78: discolorationortarnish | C78: Contamination | E78: productslipping | F78: Detachment of Device or Device Component
B79: doesnotperformproperly | C79: Defective Device | E79: productsticking | F79: Mechanical Jam
... B86: holeortear | C86: Material Frayed | E86: intermittentfunctionality | F86: Difficult or Delayed Activation
B88: SALES SHEET — Data Entry Guide
B89: Enter data in columns A–D. All sales tables and charts auto-calculate from this data.
B90: Column | C90: Format | D90: Details
B91: A — Country | C91: Text (exact match) | D91: Required. Must use exact country names from the accepted list below. Case-sensitive.
B92: B — Month | C92: Text (full name) | D92: Required. Full month name: January, February, March, ... December. NOT abbreviations.
B93: C — Quantity | C93: Number | D93: Required. Units sold. Drives all sales totals, complaint rates, and charts.
B94: D — Calendar year | C94: Number or Text | D94: Required. Must be 2022, 2023, 2024, or 2025. Formulas use exact text matching on these years.
B96: Maximum 78,140 sales rows (rows 2–78,141).
B98: ACCEPTED COUNTRY NAMES (Column A)
B99: Country names are CASE-SENSITIVE. Use exactly as shown below. Any country not listed below will be grouped under "Rest of World".
B101: Region | C101: Accepted Country Names
B102: EEA + Turkey + N. Ireland | C102: Austria, Belgium, Bulgaria, Croatia, Cyprus, Czech Republic, Denmark, Estonia, Finland, France, Germany, Greece, Hungary, Ireland, Italy, Latvia, Lithuania, Luxembourg, Malta, Netherlands, Poland, Portugal, Romania, Slovakia, Slovenia, Spain, Sweden, Iceland, Norway, Turkey, Northern Ireland
B103: Australia | C103: Australia
B104: Brazil | C104: Brazil
B105: Canada | C105: Canada
B106: China | C106: China
B107: Japan | C107: Japan
B108: UK | C108: England, Scotland, Wales, United Kingdom
B109: United States | C109: United States of America
B110: Rest of World | C110: Any other country name — automatically captured as the difference between worldwide total and named regions
B113: ⚠️ IMPORTANT CONSTRAINTS & LIMITS
B115: Constraint | C115: Limit | D115: Impact if Exceeded
B116: Complaint Rate chart time range | C116: Apr 2022 – Dec 2025 (45 months) | D116: Complaints outside this window appear in Harms table but NOT in Complaint Rate chart
B117: Sales year range | C117: 2022, 2023, 2024, 2025 only | D117: Data from other years won't be picked up by regional or monthly tables
B118: Month names | C118: Full English names only | D118: Abbreviations (Jan, Apr) or numbers (1, 4) will NOT match
B119: Max complaint rows | C119: 927 rows (rows 2–928) | D119: Rows beyond 928 will not be included in calculations
B120: Max sales rows | C120: 78,140 rows (rows 2–78,141) | D120: Rows beyond 78,141 will not be included in calculations
B121: Protected sheets | C121: Harms table, Complaint Rate, sales tables, Codes | D121: These sheets are formula-driven and protected. Do not unprotect or edit.

Sheet complaints
A1: Complaint Number | B1: CSI Notification Date | C1: Description | D1: Symptom Code | E1: Medical Device Problem | F1: Harm | G1: IMDRF MDP Code | H1: Investigation Findings | I1: Investigation Conclusion
A2: 2023-03-0000416 | B2: 45006 | C2: The customer is seeing particles in the dish, he was having this particles observed in embryo culture from 11th of this month. He is using on K-system G210 and G185 incubators for culture. He is ruling out different parameters one by one to resolve this issues. Initially he was suspecting the GPS dishes. Yesterday he made droplets of sperm washing from origio all the dishes he is using from different brands and found no artefacts after 24 hr incubation. Today he made droplets with global media and he is finding some artefacts under observation. He thinks it’s the cause of the particles in culture during the course he had done culture swab from all areas and lab equipment including incubator and culture media but no growth reported by infection control. (Photos attached)_x000D_ _x000D_ ANY PATIENT INJURY OR IMPACT TO THE GAMETE OR EMBRYO? No_x000D_ WAS A MEDICAL OR PROCEDURAL INTERVENTION REQUIRED? No | D2: foreignmaterial | E2: {=IF(D2<>"",IFERROR(VLOOKUP(D2,Codes!$K$2:$L$409,2,FALSE),"UNKNOWN - "&D2),IF(C2="","",IFERROR(_xlfn.IFS(ISNUMBER(SEARCH("broken button",C2)),"Break",ISNUMBER(SEARCH("broken handle",C2)),"Break",ISNUMBER(SEARCH("shipping damage",C2)),"Break",ISNUMBER(SEARCH("broken",C2)),"Break",ISNUMBER(SEARCH("crack",C2)),"Break",ISNUMBER(SEARCH("snap",C2)),"Break",ISNUMBER(SEARCH("fracture",C2)),"Break",ISNUMBER(SEARCH("bent",C2)),"Material Twisted/Bent",ISNUMBER(SEARCH("twisted",C2)),"Material Twisted/Bent",ISNUMBER(SEARCH("component separat",C2)),"Material Separation",ISNUMBER(SEARCH("separat",C2)),"Material Separation",ISNUMBER(SEARCH("connection",C2)),"Loose or Intermittent Connection",ISNUMBER(SEARCH("loose",C2)),"Loose or Intermittent Connection",ISNUMBER(SEARCH("damaged packaging",C2)),"Packaging Problem",ISNUMBER(SEARCH("packaging",C2)),"Packaging Problem",ISNUMBER(SEARCH("discoloration",C2)),"Contamination",ISNUMBER(SEARCH("tarnish",C2)),"Contamination",ISNUMBER(SEARCH("stain",C2)),"Contamination",ISNUMBER(SEARCH("foreign material",C2)),"Contamination",ISNUMBER(SEARCH("contamina",C2)),"Contamination",ISNUMBER(SEARCH("overheat",C2)),"Overheating of Device",ISNUMBER(SEARCH("excessive heat",C2)),"Overheating of Device",ISNUMBER(SEARCH("hot",C2)),"Overheating of Device",ISNUMBER(SEARCH("noise",C2)),"Noise, Audible",ISNUMBER(SEARCH("sound",C2)),"Noise, Audible",ISNUMBER(SEARCH("loud",C2)),"Noise, Audible",ISNUMBER(SEARCH("fray",C2)),"Material Frayed",ISNUMBER(SEARCH("hole",C2)),"Material Frayed",ISNUMBER(SEARCH("tear",C2)),"Material Frayed",ISNUMBER(SEARCH("worn",C2)),"Material Frayed",ISNUMBER(SEARCH("intermittent",C2)),"Difficult or Delayed Activation",ISNUMBER(SEARCH("delay",C2)),"Difficult or Delayed Activation",ISNUMBER(SEARCH("label",C2)),"Device Markings/Labelling Problem",ISNUMBER(SEARCH("marking",C2)),"Device Markings/Labelling Problem",ISNUMBER(SEARCH("lacerat",C2)),"Defective Device",ISNUMBER(SEARCH("cut",C2)),"Defective Device",ISNUMBER(SEARCH("leak",C2)),"Fluid/Blood Leak",ISNUMBER(SEARCH("missing",C2)),"Component Missing",ISNUMBER(SEARCH("power",C2)),"Complete Loss of Power",ISNUMBER(SEARCH("will not turn on",C2)),"Complete Loss of Power",ISNUMBER(SEARCH("won't turn on",C2)),"Complete Loss of Power",ISNUMBER(SEARCH("does not turn on",C2)),"Complete Loss of Power",ISNUMBER(SEARCH("electrical",C2)),"Electrical Power Problem",ISNUMBER(SEARCH("pressure",C2)),"Detachment of Device or Device Component",ISNUMBER(SEARCH("slip",C2)),"Detachment of Device or Device Component",ISNUMBER(SEARCH("detach",C2)),"Detachment of Device or Device Component",ISNUMBER(SEARCH("stick",C2)),"Mechanical Jam",ISNUMBER(SEARCH("jam",C2)),"Mechanical Jam",ISNUMBER(SEARCH("rigid",C2)),"Mechanical Jam",ISNUMBER(SEARCH("rust",C2)),"Corroded",ISNUMBER(SEARCH("corrod",C2)),"Corroded",ISNUMBER(SEARCH("corrosion",C2)),"Corroded",ISNUMBER(SEARCH("alignment",C2)),"Defective Device",ISNUMBER(SEARCH("adjust",C2)),"Defective Device",ISNUMBER(SEARCH("perform",C2)),"Defective Device",ISNUMBER(SEARCH("malfunction",C2)),"Defective Device",ISNUMBER(SEARCH("defect",C2)),"Defective Device",ISNUMBER(SEARCH("fail",C2)),"Defective Device",ISNUMBER(SEARCH("not work",C2)),"Defective Device",ISNUMBER(SEARCH("doesn't work",C2)),"Defective Device",TRUE,"UNKNOWN"),"UNKNOWN")))} -> Contamination | F2: =IF(E2="","","No Clinical Signs, Symptoms or Conditions") -> No Clinical Signs, Symptoms or Conditions | G2: =IF(E2="","",IFERROR(VLOOKUP(E2,Codes!$L$2:$N$409,3,FALSE),"—")) -> A1801
A3: 2023-04-0000158 | B3: 45026 | C3: When using the culture media, customer is seeing particles / artefacts in the dish. | D3: particles | E3: {=IF(D3<>"",IFERROR(VLOOKUP(D3,Codes!$K$2:$L$409,2,FALSE),"UNKNOWN - "&D3),IF(C3="","",IFERROR(_xlfn.IFS(ISNUMBER(SEARCH("broken button",C3)),"Break",ISNUMBER(SEARCH("broken handle",C3)),"Break",ISNUMBER(SEARCH("shipping damage",C3)),"Break",ISNUMBER(SEARCH("broken",C3)),"Break",ISNUMBER(SEARCH("crack",C3)),"Break",ISNUMBER(SEARCH("snap",C3)),"Break",ISNUMBER(SEARCH("fracture",C3)),"Break",ISNUMBER(SEARCH("bent",C3)),"Material Twisted/Bent",ISNUMBER(SEARCH("twisted",C3)),"Material Twisted/Bent",ISNUMBER(SEARCH("component separat",C3)),"Material Separation",ISNUMBER(SEARCH("separat",C3)),"Material Separation",ISNUMBER(SEARCH("connection",C3)),"Loose or Intermittent Connection",ISNUMBER(SEARCH("loose",C3)),"Loose or Intermittent Connection",ISNUMBER(SEARCH("damaged packaging",C3)),"Packaging Problem",ISNUMBER(SEARCH("packaging",C3)),"Packaging Problem",ISNUMBER(SEARCH("discoloration",C3)),"Contamination",ISNUMBER(SEARCH("tarnish",C3)),"Contamination",ISNUMBER(SEARCH("stain",C3)),"Contamination",ISNUMBER(SEARCH("foreign material",C3)),"Contamination",ISNUMBER(SEARCH("contamina",C3)),"Contamination",ISNUMBER(SEARCH("overheat",C3)),"Overheating of Device",ISNUMBER(SEARCH("excessive heat",C3)),"Overheating of Device",ISNUMBER(SEARCH("hot",C3)),"Overheating of Device",ISNUMBER(SEARCH("noise",C3)),"Noise, Audible",ISNUMBER(SEARCH("sound",C3)),"Noise, Audible",ISNUMBER(SEARCH("loud",C3)),"Noise, Audible",ISNUMBER(SEARCH("fray",C3)),"Material Frayed",ISNUMBER(SEARCH("hole",C3)),"Material Frayed",ISNUMBER(SEARCH("tear",C3)),"Material Frayed",ISNUMBER(SEARCH("worn",C3)),"Material Frayed",ISNUMBER(SEARCH("intermittent",C3)),"Difficult or Delayed Activation",ISNUMBER(SEARCH("delay",C3)),"Difficult or Delayed Activation",ISNUMBER(SEARCH("label",C3)),"Device Markings/Labelling Problem",ISNUMBER(SEARCH("marking",C3)),"Device Markings/Labelling Problem",ISNUMBER(SEARCH("lacerat",C3)),"Defective Device",ISNUMBER(SEARCH("cut",C3)),"Defective Device",ISNUMBER(SEARCH("leak",C3)),"Fluid/Blood Leak",ISNUMBER(SEARCH("missing",C3)),"Component Missing",ISNUMBER(SEARCH("power",C3)),"Complete Loss of Power",ISNUMBER(SEARCH("will not turn on",C3)),"Complete Loss of Power",ISNUMBER(SEARCH("won't turn on",C3)),"Complete Loss of Power",ISNUMBER(SEARCH("does not turn on",C3)),"Complete Loss of Power",ISNUMBER(SEARCH("electrical",C3)),"Electrical Power Problem",ISNUMBER(SEARCH("pressure",C3)),"Detachment of Device or Device Component",ISNUMBER(SEARCH("slip",C3)),"Detachment of Device or Device Component",ISNUMBER(SEARCH("detach",C3)),"Detachment of Device or Device Component",ISNUMBER(SEARCH("stick",C3)),"Mechanical Jam",ISNUMBER(SEARCH("jam",C3)),"Mechanical Jam",ISNUMBER(SEARCH("rigid",C3)),"Mechanical Jam",ISNUMBER(SEARCH("rust",C3)),"Corroded",ISNUMBER(SEARCH("corrod",C3)),"Corroded",ISNUMBER(SEARCH("corrosion",C3)),"Corroded",ISNUMBER(SEARCH("alignment",C3)),"Defective Device",ISNUMBER(SEARCH("adjust",C3)),"Defective Device",ISNUMBER(SEARCH("perform",C3)),"Defective Device",ISNUMBER(SEARCH("malfunction",C3)),"Defective Device",ISNUMBER(SEARCH("defect",C3)),"Defective Device",ISNUMBER(SEARCH("fail",C3)),"Defective Device",ISNUMBER(SEARCH("not work",C3)),"Defective Device",ISNUMBER(SEARCH("doesn't work",C3)),"Defective Device",TRUE,"UNKNOWN"),"UNKNOWN")))} -> UNKNOWN - particles | F3: =IF(E3="","","No Clinical Signs, Symptoms or Conditions") -> No Clinical Signs, Symptoms or Conditions | G3: =IF(E3="","",IFERROR(VLOOKUP(E3,Codes!$L$2:$N$409,3,FALSE),"—")) -> —
A4: 2023-05-0000145 | B4: 45051 | C4: Product was darker pink than normal | D4: colorph | E4: {=IF(D4<>"",IFERROR(VLOOKUP(D4,Codes!$K$2:$L$409,2,FALSE),"UNKNOWN - "&D4),IF(C4="","",IFERROR(_xlfn.IFS(ISNUMBER(SEARCH("broken button",C4)),"Break",ISNUMBER(SEARCH("broken handle",C4)),"Break",ISNUMBER(SEARCH("shipping damage",C4)),"Break",ISNUMBER(SEARCH("broken",C4)),"Break",ISNUMBER(SEARCH("crack",C4)),"Break",ISNUMBER(SEARCH("snap",C4)),"Break",ISNUMBER(SEARCH("fracture",C4)),"Break",ISNUMBER(SEARCH("bent",C4)),"Material Twisted/Bent",ISNUMBER(SEARCH("twisted",C4)),"Material Twisted/Bent",ISNUMBER(SEARCH("component separat",C4)),"Material Separation",ISNUMBER(SEARCH("separat",C4)),"Material Separation",ISNUMBER(SEARCH("connection",C4)),"Loose or Intermittent Connection",ISNUMBER(SEARCH("loose",C4)),"Loose or Intermittent Connection",ISNUMBER(SEARCH("damaged packaging",C4)),"Packaging Problem",ISNUMBER(SEARCH("packaging",C4)),"Packaging Problem",ISNUMBER(SEARCH("discoloration",C4)),"Contamination",ISNUMBER(SEARCH("tarnish",C4)),"Contamination",ISNUMBER(SEARCH("stain",C4)),"Contamination",ISNUMBER(SEARCH("foreign material",C4)),"Contamination",ISNUMBER(SEARCH("contamina",C4)),"Contamination",ISNUMBER(SEARCH("overheat",C4)),"Overheating of Device",ISNUMBER(SEARCH("excessive heat",C4)),"Overheating of Device",ISNUMBER(SEARCH("hot",C4)),"Overheating of Device",ISNUMBER(SEARCH("noise",C4)),"Noise, Audible",ISNUMBER(SEARCH("sound",C4)),"Noise, Audible",ISNUMBER(SEARCH("loud",C4)),"Noise, Audible",ISNUMBER(SEARCH("fray",C4)),"Material Frayed",ISNUMBER(SEARCH("hole",C4)),"Material Frayed",ISNUMBER(SEARCH("tear",C4)),"Material Frayed",ISNUMBER(SEARCH("worn",C4)),"Material Frayed",ISNUMBER(SEARCH("intermittent",C4)),"Difficult or Delayed Activation",ISNUMBER(SEARCH("delay",C4)),"Difficult or Delayed Activation",ISNUMBER(SEARCH("label",C4)),"Device Markings/Labelling Problem",ISNUMBER(SEARCH("marking",C4)),"Device Markings/Labelling Problem",ISNUMBER(SEARCH("lacerat",C4)),"Defective Device",ISNUMBER(SEARCH("cut",C4)),"Defective Device",ISNUMBER(SEARCH("leak",C4)),"Fluid/Blood Leak",ISNUMBER(SEARCH("missing",C4)),"Component Missing",ISNUMBER(SEARCH("power",C4)),"Complete Loss of Power",ISNUMBER(SEARCH("will not turn on",C4)),"Complete Loss of Power",ISNUMBER(SEARCH("won't turn on",C4)),"Complete Loss of Power",ISNUMBER(SEARCH("does not turn on",C4)),"Complete Loss of Power",ISNUMBER(SEARCH("electrical",C4)),"Electrical Power Problem",ISNUMBER(SEARCH("pressure",C4)),"Detachment of Device or Device Component",ISNUMBER(SEARCH("slip",C4)),"Detachment of Device or Device Component",ISNUMBER(SEARCH("detach",C4)),"Detachment of Device or Device Component",ISNUMBER(SEARCH("stick",C4)),"Mechanical Jam",ISNUMBER(SEARCH("jam",C4)),"Mechanical Jam",ISNUMBER(SEARCH("rigid",C4)),"Mechanical Jam",ISNUMBER(SEARCH("rust",C4)),"Corroded",ISNUMBER(SEARCH("corrod",C4)),"Corroded",ISNUMBER(SEARCH("corrosion",C4)),"Corroded",ISNUMBER(SEARCH("alignment",C4)),"Defective Device",ISNUMBER(SEARCH("adjust",C4)),"Defective Device",ISNUMBER(SEARCH("perform",C4)),"Defective Device",ISNUMBER(SEARCH("malfunction",C4)),"Defective Device",ISNUMBER(SEARCH("defect",C4)),"Defective Device",ISNUMBER(SEARCH("fail",C4)),"Defective Device",ISNUMBER(SEARCH("not work",C4)),"Defective Device",ISNUMBER(SEARCH("doesn't work",C4)),"Defective Device",TRUE,"UNKNOWN"),"UNKNOWN")))} -> UNKNOWN - colorph | F4: =IF(E4="","","No Clinical Signs, Symptoms or Conditions") -> No Clinical Signs, Symptoms or Conditions | G4: =IF(E4="","",IFERROR(VLOOKUP(E4,Codes!$L$2:$N$409,3,FALSE),"—")) -> —
A5: 2023-05-0000540 | B5: 45072 | C5: Product arrived and is a yellow color. just received; did not use. | D5: colorph | E5: {=IF(D5<>"",IFERROR(VLOOKUP(D5,Codes!$K$2:$L$409,2,FALSE),"UNKNOWN - "&D5),IF(C5="","",IFERROR(_xlfn.IFS(ISNUMBER(SEARCH("broken button",C5)),"Break",ISNUMBER(SEARCH("broken handle",C5)),"Break",ISNUMBER(SEARCH("shipping damage",C5)),"Break",ISNUMBER(SEARCH("broken",C5)),"Break",ISNUMBER(SEARCH("crack",C5)),"Break",ISNUMBER(SEARCH("snap",C5)),"Break",ISNUMBER(SEARCH("fracture",C5)),"Break",ISNUMBER(SEARCH("bent",C5)),"Material Twisted/Bent",ISNUMBER(SEARCH("twisted",C5)),"Material Twisted/Bent",ISNUMBER(SEARCH("component separat",C5)),"Material Separation",ISNUMBER(SEARCH("separat",C5)),"Material Separation",ISNUMBER(SEARCH("connection",C5)),"Loose or Intermittent Connection",ISNUMBER(SEARCH("loose",C5)),"Loose or Intermittent Connection",ISNUMBER(SEARCH("damaged packaging",C5)),"Packaging Problem",ISNUMBER(SEARCH("packaging",C5)),"Packaging Problem",ISNUMBER(SEARCH("discoloration",C5)),"Contamination",ISNUMBER(SEARCH("tarnish",C5)),"Contamination",ISNUMBER(SEARCH("stain",C5)),"Contamination",ISNUMBER(SEARCH("foreign material",C5)),"Contamination",ISNUMBER(SEARCH("contamina",C5)),"Contamination",ISNUMBER(SEARCH("overheat",C5)),"Overheating of Device",ISNUMBER(SEARCH("excessive heat",C5)),"Overheating of Device",ISNUMBER(SEARCH("hot",C5)),"Overheating of Device",ISNUMBER(SEARCH("noise",C5)),"Noise, Audible",ISNUMBER(SEARCH("sound",C5)),"Noise, Audible",ISNUMBER(SEARCH("loud",C5)),"Noise, Audible",ISNUMBER(SEARCH("fray",C5)),"Material Frayed",ISNUMBER(SEARCH("hole",C5)),"Material Frayed",ISNUMBER(SEARCH("tear",C5)),"Material Frayed",ISNUMBER(SEARCH("worn",C5)),"Material Frayed",ISNUMBER(SEARCH("intermittent",C5)),"Difficult or Delayed Activation",ISNUMBER(SEARCH("delay",C5)),"Difficult or Delayed Activation",ISNUMBER(SEARCH("label",C5)),"Device Markings/Labelling Problem",ISNUMBER(SEARCH("marking",C5)),"Device Markings/Labelling Problem",ISNUMBER(SEARCH("lacerat",C5)),"Defective Device",ISNUMBER(SEARCH("cut",C5)),"Defective Device",ISNUMBER(SEARCH("leak",C5)),"Fluid/Blood Leak",ISNUMBER(SEARCH("missing",C5)),"Component Missing",ISNUMBER(SEARCH("power",C5)),"Complete Loss of Power",ISNUMBER(SEARCH("will not turn on",C5)),"Complete Loss of Power",ISNUMBER(SEARCH("won't turn on",C5)),"Complete Loss of Power",ISNUMBER(SEARCH("does not turn on",C5)),"Complete Loss of Power",ISNUMBER(SEARCH("electrical",C5)),"Electrical Power Problem",ISNUMBER(SEARCH("pressure",C5)),"Detachment of Device or Device Component",ISNUMBER(SEARCH("slip",C5)),"Detachment of Device or Device Component",ISNUMBER(SEARCH("detach",C5)),"Detachment of Device or Device Component",ISNUMBER(SEARCH("stick",C5)),"Mechanical Jam",ISNUMBER(SEARCH("jam",C5)),"Mechanical Jam",ISNUMBER(SEARCH("rigid",C5)),"Mechanical Jam",ISNUMBER(SEARCH("rust",C5)),"Corroded",ISNUMBER(SEARCH("corrod",C5)),"Corroded",ISNUMBER(SEARCH("corrosion",C5)),"Corroded",ISNUMBER(SEARCH("alignment",C5)),"Defective Device",ISNUMBER(SEARCH("adjust",C5)),"Defective Device",ISNUMBER(SEARCH("perform",C5)),"Defective Device",ISNUMBER(SEARCH("malfunction",C5)),"Defective Device",ISNUMBER(SEARCH("defect",C5)),"Defective Device",ISNUMBER(SEARCH("fail",C5)),"Defective Device",ISNUMBER(SEARCH("not work",C5)),"Defective Device",ISNUMBER(SEARCH("doesn't work",C5)),"Defective Device",TRUE,"UNKNOWN"),"UNKNOWN")))} -> UNKNOWN - colorph | F5: =IF(E5="","","No Clinical Signs, Symptoms or Conditions") -> No Clinical Signs, Symptoms or Conditions | G5: =IF(E5="","",IFERROR(VLOOKUP(E5,Codes!$L$2:$N$409,3,FALSE),"—")) -> —
A6: 2023-05-0000618 | B6: 45076 | C6: Media is all more yellow than previous lots._x000D_ _x000D_ ANY PATIENT INJURY OR IMPACT TO THE GAMETE OR EMBRYO? No_x000D_ WAS A MEDICAL OR PROCEDURAL INTERVENTION REQUIRED? No | D6: colorph | E6: {=IF(D6<>"",IFERROR(VLOOKUP(D6,Codes!$K$2:$L$409,2,FALSE),"UNKNOWN - "&D6),IF(C6="","",IFERROR(_xlfn.IFS(ISNUMBER(SEARCH("broken button",C6)),"Break",ISNUMBER(SEARCH("broken handle",C6)),"Break",ISNUMBER(SEARCH("shipping damage",C6)),"Break",ISNUMBER(SEARCH("broken",C6)),"Break",ISNUMBER(SEARCH("crack",C6)),"Break",ISNUMBER(SEARCH("snap",C6)),"Break",ISNUMBER(SEARCH("fracture",C6)),"Break",ISNUMBER(SEARCH("bent",C6)),"Material Twisted/Bent",ISNUMBER(SEARCH("twisted",C6)),"Material Twisted/Bent",ISNUMBER(SEARCH("component separat",C6)),"Material Separation",ISNUMBER(SEARCH("separat",C6)),"Material Separation",ISNUMBER(SEARCH("connection",C6)),"Loose or Intermittent Connection",ISNUMBER(SEARCH("loose",C6)),"Loose or Intermittent Connection",ISNUMBER(SEARCH("damaged packaging",C6)),"Packaging Problem",ISNUMBER(SEARCH("packaging",C6)),"Packaging Problem",ISNUMBER(SEARCH("discoloration",C6)),"Contamination",ISNUMBER(SEARCH("tarnish",C6)),"Contamination",ISNUMBER(SEARCH("stain",C6)),"Contamination",ISNUMBER(SEARCH("foreign material",C6)),"Contamination",ISNUMBER(SEARCH("contamina",C6)),"Contamination",ISNUMBER(SEARCH("overheat",C6)),"Overheating of Device",ISNUMBER(SEARCH("excessive heat",C6)),"Overheating of Device",ISNUMBER(SEARCH("hot",C6)),"Overheating of Device",ISNUMBER(SEARCH("noise",C6)),"Noise, Audible",ISNUMBER(SEARCH("sound",C6)),"Noise, Audible",ISNUMBER(SEARCH("loud",C6)),"Noise, Audible",ISNUMBER(SEARCH("fray",C6)),"Material Frayed",ISNUMBER(SEARCH("hole",C6)),"Material Frayed",ISNUMBER(SEARCH("tear",C6)),"Material Frayed",ISNUMBER(SEARCH("worn",C6)),"Material Frayed",ISNUMBER(SEARCH("intermittent",C6)),"Difficult or Delayed Activation",ISNUMBER(SEARCH("delay",C6)),"Difficult or Delayed Activation",ISNUMBER(SEARCH("label",C6)),"Device Markings/Labelling Problem",ISNUMBER(SEARCH("marking",C6)),"Device Markings/Labelling Problem",ISNUMBER(SEARCH("lacerat",C6)),"Defective Device",ISNUMBER(SEARCH("cut",C6)),"Defective Device",ISNUMBER(SEARCH("leak",C6)),"Fluid/Blood Leak",ISNUMBER(SEARCH("missing",C6)),"Component Missing",ISNUMBER(SEARCH("power",C6)),"Complete Loss of Power",ISNUMBER(SEARCH("will not turn on",C6)),"Complete Loss of Power",ISNUMBER(SEARCH("won't turn on",C6)),"Complete Loss of Power",ISNUMBER(SEARCH("does not turn on",C6)),"Complete Loss of Power",ISNUMBER(SEARCH("electrical",C6)),"Electrical Power Problem",ISNUMBER(SEARCH("pressure",C6)),"Detachment of Device or Device Component",ISNUMBER(SEARCH("slip",C6)),"Detachment of Device or Device Component",ISNUMBER(SEARCH("detach",C6)),"Detachment of Device or Device Component",ISNUMBER(SEARCH("stick",C6)),"Mechanical Jam",ISNUMBER(SEARCH("jam",C6)),"Mechanical Jam",ISNUMBER(SEARCH("rigid",C6)),"Mechanical Jam",ISNUMBER(SEARCH("rust",C6)),"Corroded",ISNUMBER(SEARCH("corrod",C6)),"Corroded",ISNUMBER(SEARCH("corrosion",C6)),"Corroded",ISNUMBER(SEARCH("alignment",C6)),"Defective Device",ISNUMBER(SEARCH("adjust",C6)),"Defective Device",ISNUMBER(SEARCH("perform",C6)),"Defective Device",ISNUMBER(SEARCH("malfunction",C6)),"Defective Device",ISNUMBER(SEARCH("defect",C6)),"Defective Device",ISNUMBER(SEARCH("fail",C6)),"Defective Device",ISNUMBER(SEARCH("not work",C6)),"Defective Device",ISNUMBER(SEARCH("doesn't work",C6)),"Defective Device",TRUE,"UNKNOWN"),"UNKNOWN")))} -> UNKNOWN - colorph | F6: =IF(E6="","","No Clinical Signs, Symptoms or Conditions") -> No Clinical Signs, Symptoms or Conditions | G6: =IF(E6="","",IFERROR(VLOOKUP(E6,Codes!$L$2:$N$409,3,FALSE),"—")) -> —
A7: 2023-06-0000030 | B7: 45078 | C7: New lot is discolored- more yellow than previous lot. (Photos attached) | D7: colorph | E7: {=IF(D7<>"",IFERROR(VLOOKUP(D7,Codes!$K$2:$L$409,2,FALSE),"UNKNOWN - "&D7),IF(C7="","",IFERROR(_xlfn.IFS(ISNUMBER(SEARCH("broken button",C7)),"Break",ISNUMBER(SEARCH("broken handle",C7)),"Break",ISNUMBER(SEARCH("shipping damage",C7)),"Break",ISNUMBER(SEARCH("broken",C7)),"Break",ISNUMBER(SEARCH("crack",C7)),"Break",ISNUMBER(SEARCH("snap",C7)),"Break",ISNUMBER(SEARCH("fracture",C7)),"Break",ISNUMBER(SEARCH("bent",C7)),"Material Twisted/Bent",ISNUMBER(SEARCH("twisted",C7)),"Material Twisted/Bent",ISNUMBER(SEARCH("component separat",C7)),"Material Separation",ISNUMBER(SEARCH("separat",C7)),"Material Separation",ISNUMBER(SEARCH("connection",C7)),"Loose or Intermittent Connection",ISNUMBER(SEARCH("loose",C7)),"Loose or Intermittent Connection",ISNUMBER(SEARCH("damaged packaging",C7)),"Packaging Problem",ISNUMBER(SEARCH("packaging",C7)),"Packaging Problem",ISNUMBER(SEARCH("discoloration",C7)),"Contamination",ISNUMBER(SEARCH("tarnish",C7)),"Contamination",ISNUMBER(SEARCH("stain",C7)),"Contamination",ISNUMBER(SEARCH("foreign material",C7)),"Contamination",ISNUMBER(SEARCH("contamina",C7)),"Contamination",ISNUMBER(SEARCH("overheat",C7)),"Overheating of Device",ISNUMBER(SEARCH("excessive heat",C7)),"Overheating of Device",ISNUMBER(SEARCH("hot",C7)),"Overheating of Device",ISNUMBER(SEARCH("noise",C7)),"Noise, Audible",ISNUMBER(SEARCH("sound",C7)),"Noise, Audible",ISNUMBER(SEARCH("loud",C7)),"Noise, Audible",ISNUMBER(SEARCH("fray",C7)),"Material Frayed",ISNUMBER(SEARCH("hole",C7)),"Material Frayed",ISNUMBER(SEARCH("tear",C7)),"Material Frayed",ISNUMBER(SEARCH("worn",C7)),"Material Frayed",ISNUMBER(SEARCH("intermittent",C7)),"Difficult or Delayed Activation",ISNUMBER(SEARCH("delay",C7)),"Difficult or Delayed Activation",ISNUMBER(SEARCH("label",C7)),"Device Markings/Labelling Problem",ISNUMBER(SEARCH("marking",C7)),"Device Markings/Labelling Problem",ISNUMBER(SEARCH("lacerat",C7)),"Defective Device",ISNUMBER(SEARCH("cut",C7)),"Defective Device",ISNUMBER(SEARCH("leak",C7)),"Fluid/Blood Leak",ISNUMBER(SEARCH("missing",C7)),"Component Missing",ISNUMBER(SEARCH("power",C7)),"Complete Loss of Power",ISNUMBER(SEARCH("will not turn on",C7)),"Complete Loss of Power",ISNUMBER(SEARCH("won't turn on",C7)),"Complete Loss of Power",ISNUMBER(SEARCH("does not turn on",C7)),"Complete Loss of Power",ISNUMBER(SEARCH("electrical",C7)),"Electrical Power Problem",ISNUMBER(SEARCH("pressure",C7)),"Detachment of Device or Device Component",ISNUMBER(SEARCH("slip",C7)),"Detachment of Device or Device Component",ISNUMBER(SEARCH("detach",C7)),"Detachment of Device or Device Component",ISNUMBER(SEARCH("stick",C7)),"Mechanical Jam",ISNUMBER(SEARCH("jam",C7)),"Mechanical Jam",ISNUMBER(SEARCH("rigid",C7)),"Mechanical Jam",ISNUMBER(SEARCH("rust",C7)),"Corroded",ISNUMBER(SEARCH("corrod",C7)),"Corroded",ISNUMBER(SEARCH("corrosion",C7)),"Corroded",ISNUMBER(SEARCH("alignment",C7)),"Defective Device",ISNUMBER(SEARCH("adjust",C7)),"Defective Device",ISNUMBER(SEARCH("perform",C7)),"Defective Device",ISNUMBER(SEARCH("malfunction",C7)),"Defective Device",ISNUMBER(SEARCH("defect",C7)),"Defective Device",ISNUMBER(SEARCH("fail",C7)),"Defective Device",ISNUMBER(SEARCH("not work",C7)),"Defective Device",ISNUMBER(SEARCH("doesn't work",C7)),"Defective Device",TRUE,"UNKNOWN"),"UNKNOWN")))} -> UNKNOWN - colorph | F7: =IF(E7="","","No Clinical Signs, Symptoms or Conditions") -> No Clinical Signs, Symptoms or Conditions | G7: =IF(E7="","",IFERROR(VLOOKUP(E7,Codes!$L$2:$N$409,3,FALSE),"—")) -> —
A8: 2023-06-0000116 | B8: 45083 | C8: Color of some bottles is yellow. I have attached data logger details. (Photo attached) | D8: colorph | E8: {=IF(D8<>"",IFERROR(VLOOKUP(D8,Codes!$K$2:$L$409,2,FALSE),"UNKNOWN - "&D8),IF(C8="","",IFERROR(_xlfn.IFS(ISNUMBER(SEARCH("broken button",C8)),"Break",ISNUMBER(SEARCH("broken handle",C8)),"Break",ISNUMBER(SEARCH("shipping damage",C8)),"Break",ISNUMBER(SEARCH("broken",C8)),"Break",ISNUMBER(SEARCH("crack",C8)),"Break",ISNUMBER(SEARCH("snap",C8)),"Break",ISNUMBER(SEARCH("fracture",C8)),"Break",ISNUMBER(SEARCH("bent",C8)),"Material Twisted/Bent",ISNUMBER(SEARCH("twisted",C8)),"Material Twisted/Bent",ISNUMBER(SEARCH("component separat",C8)),"Material Separation",ISNUMBER(SEARCH("separat",C8)),"Material Separation",ISNUMBER(SEARCH("connection",C8)),"Loose or Intermittent Connection",ISNUMBER(SEARCH("loose",C8)),"Loose or Intermittent Connection",ISNUMBER(SEARCH("damaged packaging",C8)),"Packaging Problem",ISNUMBER(SEARCH("packaging",C8)),"Packaging Problem",ISNUMBER(SEARCH("discoloration",C8)),"Contamination",ISNUMBER(SEARCH("tarnish",C8)),"Contamination",ISNUMBER(SEARCH("stain",C8)),"Contamination",ISNUMBER(SEARCH("foreign material",C8)),"Contamination",ISNUMBER(SEARCH("contamina",C8)),"Contamination",ISNUMBER(SEARCH("overheat",C8)),"Overheating of Device",ISNUMBER(SEARCH("excessive heat",C8)),"Overheating of Device",ISNUMBER(SEARCH("hot",C8)),"Overheating of Device",ISNUMBER(SEARCH("noise",C8)),"Noise, Audible",ISNUMBER(SEARCH("sound",C8)),"Noise, Audible",ISNUMBER(SEARCH("loud",C8)),"Noise, Audible",ISNUMBER(SEARCH("fray",C8)),"Material Frayed",ISNUMBER(SEARCH("hole",C8)),"Material Frayed",ISNUMBER(SEARCH("tear",C8)),"Material Frayed",ISNUMBER(SEARCH("worn",C8)),"Material Frayed",ISNUMBER(SEARCH("intermittent",C8)),"Difficult or Delayed Activation",ISNUMBER(SEARCH("delay",C8)),"Difficult or Delayed Activation",ISNUMBER(SEARCH("label",C8)),"Device Markings/Labelling Problem",ISNUMBER(SEARCH("marking",C8)),"Device Markings/Labelling Problem",ISNUMBER(SEARCH("lacerat",C8)),"Defective Device",ISNUMBER(SEARCH("cut",C8)),"Defective Device",ISNUMBER(SEARCH("leak",C8)),"Fluid/Blood Leak",ISNUMBER(SEARCH("missing",C8)),"Component Missing",ISNUMBER(SEARCH("power",C8)),"Complete Loss of Power",ISNUMBER(SEARCH("will not turn on",C8)),"Complete Loss of Power",ISNUMBER(SEARCH("won't turn on",C8)),"Complete Loss of Power",ISNUMBER(SEARCH("does not turn on",C8)),"Complete Loss of Power",ISNUMBER(SEARCH("electrical",C8)),"Electrical Power Problem",ISNUMBER(SEARCH("pressure",C8)),"Detachment of Device or Device Component",ISNUMBER(SEARCH("slip",C8)),"Detachment of Device or Device Component",ISNUMBER(SEARCH("detach",C8)),"Detachment of Device or Device Component",ISNUMBER(SEARCH("stick",C8)),"Mechanical Jam",ISNUMBER(SEARCH("jam",C8)),"Mechanical Jam",ISNUMBER(SEARCH("rigid",C8)),"Mechanical Jam",ISNUMBER(SEARCH("rust",C8)),"Corroded",ISNUMBER(SEARCH("corrod",C8)),"Corroded",ISNUMBER(SEARCH("corrosion",C8)),"Corroded",ISNUMBER(SEARCH("alignment",C8)),"Defective Device",ISNUMBER(SEARCH("adjust",C8)),"Defective Device",ISNUMBER(SEARCH("perform",C8)),"Defective Device",ISNUMBER(SEARCH("malfunction",C8)),"Defective Device",ISNUMBER(SEARCH("defect",C8)),"Defective Device",ISNUMBER(SEARCH("fail",C8)),"Defective Device",ISNUMBER(SEARCH("not work",C8)),"Defective Device",ISNUMBER(SEARCH("doesn't work",C8)),"Defective Device",TRUE,"UNKNOWN"),"UNKNOWN")))} -> UNKNOWN - colorph | F8: =IF(E8="","","No Clinical Signs, Symptoms or Conditions") -> No Clinical Signs, Symptoms or Conditions | G8: =IF(E8="","",IFERROR(VLOOKUP(E8,Codes!$L$2:$N$409,3,FALSE),"—")) -> —
A9: 2023-06-0000121 | B9: 45083 | C9: discoloration of media product. will not use. Customer does not trust the media and current LGQC procedures. customer extremely concerned about media QC. does not trust LG media at this time. Very upset with CR manufacturing. (Photo attached)_x000D_ _x000D_ Patient, Gamete, Embryo, or End User Involvement? no | D9: colorph | E9: {=IF(D9<>"",IFERROR(VLOOKUP(D9,Codes!$K$2:$L$409,2,FALSE),"UNKNOWN - "&D9),IF(C9="","",IFERROR(_xlfn.IFS(ISNUMBER(SEARCH("broken button",C9)),"Break",ISNUMBER(SEARCH("broken handle",C9)),"Break",ISNUMBER(SEARCH("shipping damage",C9)),"Break",ISNUMBER(SEARCH("broken",C9)),"Break",ISNUMBER(SEARCH("crack",C9)),"Break",ISNUMBER(SEARCH("snap",C9)),"Break",ISNUMBER(SEARCH("fracture",C9)),"Break",ISNUMBER(SEARCH("bent",C9)),"Material Twisted/Bent",ISNUMBER(SEARCH("twisted",C9)),"Material Twisted/Bent",ISNUMBER(SEARCH("component separat",C9)),"Material Separation",ISNUMBER(SEARCH("separat",C9)),"Material Separation",ISNUMBER(SEARCH("connection",C9)),"Loose or Intermittent Connection",ISNUMBER(SEARCH("loose",C9)),"Loose or Intermittent Connection",ISNUMBER(SEARCH("damaged packaging",C9)),"Packaging Problem",ISNUMBER(SEARCH("packaging",C9)),"Packaging Problem",ISNUMBER(SEARCH("discoloration",C9)),"Contamination",ISNUMBER(SEARCH("tarnish",C9)),"Contamination",ISNUMBER(SEARCH("stain",C9)),"Contamination",ISNUMBER(SEARCH("foreign material",C9)),"Contamination",ISNUMBER(SEARCH("contamina",C9)),"Contamination",ISNUMBER(SEARCH("overheat",C9)),"Overheating of Device",ISNUMBER(SEARCH("excessive heat",C9)),"Overheating of Device",ISNUMBER(SEARCH("hot",C9)),"Overheating of Device",ISNUMBER(SEARCH("noise",C9)),"Noise, Audible",ISNUMBER(SEARCH("sound",C9)),"Noise, Audible",ISNUMBER(SEARCH("loud",C9)),"Noise, Audible",ISNUMBER(SEARCH("fray",C9)),"Material Frayed",ISNUMBER(SEARCH("hole",C9)),"Material Frayed",ISNUMBER(SEARCH("tear",C9)),"Material Frayed",ISNUMBER(SEARCH("worn",C9)),"Material Frayed",ISNUMBER(SEARCH("intermittent",C9)),"Difficult or Delayed Activation",ISNUMBER(SEARCH("delay",C9)),"Difficult or Delayed Activation",ISNUMBER(SEARCH("label",C9)),"Device Markings/Labelling Problem",ISNUMBER(SEARCH("marking",C9)),"Device Markings/Labelling Problem",ISNUMBER(SEARCH("lacerat",C9)),"Defective Device",ISNUMBER(SEARCH("cut",C9)),"Defective Device",ISNUMBER(SEARCH("leak",C9)),"Fluid/Blood Leak",ISNUMBER(SEARCH("missing",C9)),"Component Missing",ISNUMBER(SEARCH("power",C9)),"Complete Loss of Power",ISNUMBER(SEARCH("will not turn on",C9)),"Complete Loss of Power",ISNUMBER(SEARCH("won't turn on",C9)),"Complete Loss of Power",ISNUMBER(SEARCH("does not turn on",C9)),"Complete Loss of Power",ISNUMBER(SEARCH("electrical",C9)),"Electrical Power Problem",ISNUMBER(SEARCH("pressure",C9)),"Detachment of Device or Device Component",ISNUMBER(SEARCH("slip",C9)),"Detachment of Device or Device Component",ISNUMBER(SEARCH("detach",C9)),"Detachment of Device or Device Component",ISNUMBER(SEARCH("stick",C9)),"Mechanical Jam",ISNUMBER(SEARCH("jam",C9)),"Mechanical Jam",ISNUMBER(SEARCH("rigid",C9)),"Mechanical Jam",ISNUMBER(SEARCH("rust",C9)),"Corroded",ISNUMBER(SEARCH("corrod",C9)),"Corroded",ISNUMBER(SEARCH("corrosion",C9)),"Corroded",ISNUMBER(SEARCH("alignment",C9)),"Defective Device",ISNUMBER(SEARCH("adjust",C9)),"Defective Device",ISNUMBER(SEARCH("perform",C9)),"Defective Device",ISNUMBER(SEARCH("malfunction",C9)),"Defective Device",ISNUMBER(SEARCH("defect",C9)),"Defective Device",ISNUMBER(SEARCH("fail",C9)),"Defective Device",ISNUMBER(SEARCH("not work",C9)),"Defective Device",ISNUMBER(SEARCH("doesn't work",C9)),"Defective Device",TRUE,"UNKNOWN"),"UNKNOWN")))} -> UNKNOWN - colorph | F9: =IF(E9="","","No Clinical Signs, Symptoms or Conditions") -> No Clinical Signs, Symptoms or Conditions | G9: =IF(E9="","",IFERROR(VLOOKUP(E9,Codes!$L$2:$N$409,3,FALSE),"—")) -> —
A10: 2023-06-0000281 | B10: 45088 | C10: Discoloration_x000D_ _x000D_ This lab director has had multiple media issues and both of her labs (Stanford being the other), and she is very vocal in the IVF community about the media issues and Cooper not giving her answers. | D10: colorph | E10: {=IF(D10<>"",IFERROR(VLOOKUP(D10,Codes!$K$2:$L$409,2,FALSE),"UNKNOWN - "&D10),IF(C10="","",IFERROR(_xlfn.IFS(ISNUMBER(SEARCH("broken button",C10)),"Break",ISNUMBER(SEARCH("broken handle",C10)),"Break",ISNUMBER(SEARCH("shipping damage",C10)),"Break",ISNUMBER(SEARCH("broken",C10)),"Break",ISNUMBER(SEARCH("crack",C10)),"Break",ISNUMBER(SEARCH("snap",C10)),"Break",ISNUMBER(SEARCH("fracture",C10)),"Break",ISNUMBER(SEARCH("bent",C10)),"Material Twisted/Bent",ISNUMBER(SEARCH("twisted",C10)),"Material Twisted/Bent",ISNUMBER(SEARCH("component separat",C10)),"Material Separation",ISNUMBER(SEARCH("separat",C10)),"Material Separation",ISNUMBER(SEARCH("connection",C10)),"Loose or Intermittent Connection",ISNUMBER(SEARCH("loose",C10)),"Loose or Intermittent Connection",ISNUMBER(SEARCH("damaged packaging",C10)),"Packaging Problem",ISNUMBER(SEARCH("packaging",C10)),"Packaging Problem",ISNUMBER(SEARCH("discoloration",C10)),"Contamination",ISNUMBER(SEARCH("tarnish",C10)),"Contamination",ISNUMBER(SEARCH("stain",C10)),"Contamination",ISNUMBER(SEARCH("foreign material",C10)),"Contamination",ISNUMBER(SEARCH("contamina",C10)),"Contamination",ISNUMBER(SEARCH("overheat",C10)),"Overheating of Device",ISNUMBER(SEARCH("excessive heat",C10)),"Overheating of Device",ISNUMBER(SEARCH("hot",C10)),"Overheating of Device",ISNUMBER(SEARCH("noise",C10)),"Noise, Audible",ISNUMBER(SEARCH("sound",C10)),"Noise, Audible",ISNUMBER(SEARCH("loud",C10)),"Noise, Audible",ISNUMBER(SEARCH("fray",C10)),"Material Frayed",ISNUMBER(SEARCH("hole",C10)),"Material Frayed",ISNUMBER(SEARCH("tear",C10)),"Material Frayed",ISNUMBER(SEARCH("worn",C10)),"Material Frayed",ISNUMBER(SEARCH("intermittent",C10)),"Difficult or Delayed Activation",ISNUMBER(SEARCH("delay",C10)),"Difficult or Delayed Activation",ISNUMBER(SEARCH("label",C10)),"Device Markings/Labelling Problem",ISNUMBER(SEARCH("marking",C10)),"Device Markings/Labelling Problem",ISNUMBER(SEARCH("lacerat",C10)),"Defective Device",ISNUMBER(SEARCH("cut",C10)),"Defective Device",ISNUMBER(SEARCH("leak",C10)),"Fluid/Blood Leak",ISNUMBER(SEARCH("missing",C10)),"Component Missing",ISNUMBER(SEARCH("power",C10)),"Complete Loss of Power",ISNUMBER(SEARCH("will not turn on",C10)),"Complete Loss of Power",ISNUMBER(SEARCH("won't turn on",C10)),"Complete Loss of Power",ISNUMBER(SEARCH("does not turn on",C10)),"Complete Loss of Power",ISNUMBER(SEARCH("electrical",C10)),"Electrical Power Problem",ISNUMBER(SEARCH("pressure",C10)),"Detachment of Device or Device Component",ISNUMBER(SEARCH("slip",C10)),"Detachment of Device or Device Component",ISNUMBER(SEARCH("detach",C10)),"Detachment of Device or Device Component",ISNUMBER(SEARCH("stick",C10)),"Mechanical Jam",ISNUMBER(SEARCH("jam",C10)),"Mechanical Jam",ISNUMBER(SEARCH("rigid",C10)),"Mechanical Jam",ISNUMBER(SEARCH("rust",C10)),"Corroded",ISNUMBER(SEARCH("corrod",C10)),"Corroded",ISNUMBER(SEARCH("corrosion",C10)),"Corroded",ISNUMBER(SEARCH("alignment",C10)),"Defective Device",ISNUMBER(SEARCH("adjust",C10)),"Defective Device",ISNUMBER(SEARCH("perform",C10)),"Defective Device",ISNUMBER(SEARCH("malfunction",C10)),"Defective Device",ISNUMBER(SEARCH("defect",C10)),"Defective Device",ISNUMBER(SEARCH("fail",C10)),"Defective Device",ISNUMBER(SEARCH("not work",C10)),"Defective Device",ISNUMBER(SEARCH("doesn't work",C10)),"Defective Device",TRUE,"UNKNOWN"),"UNKNOWN")))} -> UNKNOWN - colorph | F10: =IF(E10="","","No Clinical Signs, Symptoms or Conditions") -> No Clinical Signs, Symptoms or Conditions | G10: =IF(E10="","",IFERROR(VLOOKUP(E10,Codes!$L$2:$N$409,3,FALSE),"—")) -> —
A11: 2023-06-0000348 | B11: 45091 | C11: The cultured embryos are dark in color and coarse particles, the embryo cyst formation rate is significantly lower than our normal level, the color of the medium and the pH value has changed from the appearance. (Photo attached) | D11: colorph | E11: {=IF(D11<>"",IFERROR(VLOOKUP(D11,Codes!$K$2:$L$409,2,FALSE),"UNKNOWN - "&D11),IF(C11="","",IFERROR(_xlfn.IFS(ISNUMBER(SEARCH("broken button",C11)),"Break",ISNUMBER(SEARCH("broken handle",C11)),"Break",ISNUMBER(SEARCH("shipping damage",C11)),"Break",ISNUMBER(SEARCH("broken",C11)),"Break",ISNUMBER(SEARCH("crack",C11)),"Break",ISNUMBER(SEARCH("snap",C11)),"Break",ISNUMBER(SEARCH("fracture",C11)),"Break",ISNUMBER(SEARCH("bent",C11)),"Material Twisted/Bent",ISNUMBER(SEARCH("twisted",C11)),"Material Twisted/Bent",ISNUMBER(SEARCH("component separat",C11)),"Material Separation",ISNUMBER(SEARCH("separat",C11)),"Material Separation",ISNUMBER(SEARCH("connection",C11)),"Loose or Intermittent Connection",ISNUMBER(SEARCH("loose",C11)),"Loose or Intermittent Connection",ISNUMBER(SEARCH("damaged packaging",C11)),"Packaging Problem",ISNUMBER(SEARCH("packaging",C11)),"Packaging Problem",ISNUMBER(SEARCH("discoloration",C11)),"Contamination",ISNUMBER(SEARCH("tarnish",C11)),"Contamination",ISNUMBER(SEARCH("stain",C11)),"Contamination",ISNUMBER(SEARCH("foreign material",C11)),"Contamination",ISNUMBER(SEARCH("contamina",C11)),"Contamination",ISNUMBER(SEARCH("overheat",C11)),"Overheating of Device",ISNUMBER(SEARCH("excessive heat",C11)),"Overheating of Device",ISNUMBER(SEARCH("hot",C11)),"Overheating of Device",ISNUMBER(SEARCH("noise",C11)),"Noise, Audible",ISNUMBER(SEARCH("sound",C11)),"Noise, Audible",ISNUMBER(SEARCH("loud",C11)),"Noise, Audible",ISNUMBER(SEARCH("fray",C11)),"Material Frayed",ISNUMBER(SEARCH("hole",C11)),"Material Frayed",ISNUMBER(SEARCH("tear",C11)),"Material Frayed",ISNUMBER(SEARCH("worn",C11)),"Material Frayed",ISNUMBER(SEARCH("intermittent",C11)),"Difficult or Delayed Activation",ISNUMBER(SEARCH("delay",C11)),"Difficult or Delayed Activation",ISNUMBER(SEARCH("label",C11)),"Device Markings/Labelling Problem",ISNUMBER(SEARCH("marking",C11)),"Device Markings/Labelling Problem",ISNUMBER(SEARCH("lacerat",C11)),"Defective Device",ISNUMBER(SEARCH("cut",C11)),"Defective Device",ISNUMBER(SEARCH("leak",C11)),"Fluid/Blood Leak",ISNUMBER(SEARCH("missing",C11)),"Component Missing",ISNUMBER(SEARCH("power",C11)),"Complete Loss of Power",ISNUMBER(SEARCH("will not turn on",C11)),"Complete Loss of Power",ISNUMBER(SEARCH("won't turn on",C11)),"Complete Loss of Power",ISNUMBER(SEARCH("does not turn on",C11)),"Complete Loss of Power",ISNUMBER(SEARCH("electrical",C11)),"Electrical Power Problem",ISNUMBER(SEARCH("pressure",C11)),"Detachment of Device or Device Component",ISNUMBER(SEARCH("slip",C11)),"Detachment of Device or Device Component",ISNUMBER(SEARCH("detach",C11)),"Detachment of Device or Device Component",ISNUMBER(SEARCH("stick",C11)),"Mechanical Jam",ISNUMBER(SEARCH("jam",C11)),"Mechanical Jam",ISNUMBER(SEARCH("rigid",C11)),"Mechanical Jam",ISNUMBER(SEARCH("rust",C11)),"Corroded",ISNUMBER(SEARCH("corrod",C11)),"Corroded",ISNUMBER(SEARCH("corrosion",C11)),"Corroded",ISNUMBER(SEARCH("alignment",C11)),"Defective Device",ISNUMBER(SEARCH("adjust",C11)),"Defective Device",ISNUMBER(SEARCH("perform",C11)),"Defective Device",ISNUMBER(SEARCH("malfunction",C11)),"Defective Device",ISNUMBER(SEARCH("defect",C11)),"Defective Device",ISNUMBER(SEARCH("fail",C11)),"Defective Device",ISNUMBER(SEARCH("not work",C11)),"Defective Device",ISNUMBER(SEARCH("doesn't work",C11)),"Defective Device",TRUE,"UNKNOWN"),"UNKNOWN")))} -> UNKNOWN - colorph | F11: =IF(E11="","","No Clinical Signs, Symptoms or Conditions") -> No Clinical Signs, Symptoms or Conditions | G11: =IF(E11="","",IFERROR(VLOOKUP(E11,Codes!$L$2:$N$409,3,FALSE),"—")) -> —
A12: 2023-06-0000391 | B12: 45093 | C12: Product arrived with the color off. It is light pink/peach and with all the media issues lately, customer does not trust to use this. _x000D_ _x000D_ Patient, Gamete, Embryo, or End User Involvement? No | D12: colorph | E12: {=IF(D12<>"",IFERROR(VLOOKUP(D12,Codes!$K$2:$L$409,2,FALSE),"UNKNOWN - "&D12),IF(C12="","",IFERROR(_xlfn.IFS(ISNUMBER(SEARCH("broken button",C12)),"Break",ISNUMBER(SEARCH("broken handle",C12)),"Break",ISNUMBER(SEARCH("shipping damage",C12)),"Break",ISNUMBER(SEARCH("broken",C12)),"Break",ISNUMBER(SEARCH("crack",C12)),"Break",ISNUMBER(SEARCH("snap",C12)),"Break",ISNUMBER(SEARCH("fracture",C12)),"Break",ISNUMBER(SEARCH("bent",C12)),"Material Twisted/Bent",ISNUMBER(SEARCH("twisted",C12)),"Material Twisted/Bent",ISNUMBER(SEARCH("component separat",C12)),"Material Separation",ISNUMBER(SEARCH("separat",C12)),"Material Separation",ISNUMBER(SEARCH("connection",C12)),"Loose or Intermittent Connection",ISNUMBER(SEARCH("loose",C12)),"Loose or Intermittent Connection",ISNUMBER(SEARCH("damaged packaging",C12)),"Packaging Problem",ISNUMBER(SEARCH("packaging",C12)),"Packaging Problem",ISNUMBER(SEARCH("discoloration",C12)),"Contamination",ISNUMBER(SEARCH("tarnish",C12)),"Contamination",ISNUMBER(SEARCH("stain",C12)),"Contamination",ISNUMBER(SEARCH("foreign material",C12)),"Contamination",ISNUMBER(SEARCH("contamina",C12)),"Contamination",ISNUMBER(SEARCH("overheat",C12)),"Overheating of Device",ISNUMBER(SEARCH("excessive heat",C12)),"Overheating of Device",ISNUMBER(SEARCH("hot",C12)),"Overheating of Device",ISNUMBER(SEARCH("noise",C12)),"Noise, Audible",ISNUMBER(SEARCH("sound",C12)),"Noise, Audible",ISNUMBER(SEARCH("loud",C12)),"Noise, Audible",ISNUMBER(SEARCH("fray",C12)),"Material Frayed",ISNUMBER(SEARCH("hole",C12)),"Material Frayed",ISNUMBER(SEARCH("tear",C12)),"Material Frayed",ISNUMBER(SEARCH("worn",C12)),"Material Frayed",ISNUMBER(SEARCH("intermittent",C12)),"Difficult or Delayed Activation",ISNUMBER(SEARCH("delay",C12)),"Difficult or Delayed Activation",ISNUMBER(SEARCH("label",C12)),"Device Markings/Labelling Problem",ISNUMBER(SEARCH("marking",C12)),"Device Markings/Labelling Problem",ISNUMBER(SEARCH("lacerat",C12)),"Defective Device",ISNUMBER(SEARCH("cut",C12)),"Defective Device",ISNUMBER(SEARCH("leak",C12)),"Fluid/Blood Leak",ISNUMBER(SEARCH("missing",C12)),"Component Missing",ISNUMBER(SEARCH("power",C12)),"Complete Loss of Power",ISNUMBER(SEARCH("will not turn on",C12)),"Complete Loss of Power",ISNUMBER(SEARCH("won't turn on",C12)),"Complete Loss of Power",ISNUMBER(SEARCH("does not turn on",C12)),"Complete Loss of Power",ISNUMBER(SEARCH("electrical",C12)),"Electrical Power Problem",ISNUMBER(SEARCH("pressure",C12)),"Detachment of Device or Device Component",ISNUMBER(SEARCH("slip",C12)),"Detachment of Device or Device Component",ISNUMBER(SEARCH("detach",C12)),"Detachment of Device or Device Component",ISNUMBER(SEARCH("stick",C12)),"Mechanical Jam",ISNUMBER(SEARCH("jam",C12)),"Mechanical Jam",ISNUMBER(SEARCH("rigid",C12)),"Mechanical Jam",ISNUMBER(SEARCH("rust",C12)),"Corroded",ISNUMBER(SEARCH("corrod",C12)),"Corroded",ISNUMBER(SEARCH("corrosion",C12)),"Corroded",ISNUMBER(SEARCH("alignment",C12)),"Defective Device",ISNUMBER(SEARCH("adjust",C12)),"Defective Device",ISNUMBER(SEARCH("perform",C12)),"Defective Device",ISNUMBER(SEARCH("malfunction",C12)),"Defective Device",ISNUMBER(SEARCH("defect",C12)),"Defective Device",ISNUMBER(SEARCH("fail",C12)),"Defective Device",ISNUMBER(SEARCH("not work",C12)),"Defective Device",ISNUMBER(SEARCH("doesn't work",C12)),"Defective Device",TRUE,"UNKNOWN"),"UNKNOWN")))} -> UNKNOWN - colorph | F12: =IF(E12="","","No Clinical Signs, Symptoms or Conditions") -> No Clinical Signs, Symptoms or Conditions | G12: =IF(E12="","",IFERROR(VLOOKUP(E12,Codes!$L$2:$N$409,3,FALSE),"—")) -> —
A13: 2023-12-0000241 | B13: 45265 | C13: Customer is reporting lower than normal blast rates. The media was used between 10/7- 10/15. _x000D_ _x000D_ Follow up response:_x000D_ We are not requesting credit, we’re requesting information of if anyone else reported anything related to these lots of medium, or if you find an any problems during your investigation | D13: performance | E13: {=IF(D13<>"",IFERROR(VLOOKUP(D13,Codes!$K$2:$L$409,2,FALSE),"UNKNOWN - "&D13),IF(C13="","",IFERROR(_xlfn.IFS(ISNUMBER(SEARCH("broken button",C13)),"Break",ISNUMBER(SEARCH("broken handle",C13)),"Break",ISNUMBER(SEARCH("shipping damage",C13)),"Break",ISNUMBER(SEARCH("broken",C13)),"Break",ISNUMBER(SEARCH("crack",C13)),"Break",ISNUMBER(SEARCH("snap",C13)),"Break",ISNUMBER(SEARCH("fracture",C13)),"Break",ISNUMBER(SEARCH("bent",C13)),"Material Twisted/Bent",ISNUMBER(SEARCH("twisted",C13)),"Material Twisted/Bent",ISNUMBER(SEARCH("component separat",C13)),"Material Separation",ISNUMBER(SEARCH("separat",C13)),"Material Separation",ISNUMBER(SEARCH("connection",C13)),"Loose or Intermittent Connection",ISNUMBER(SEARCH("loose",C13)),"Loose or Intermittent Connection",ISNUMBER(SEARCH("damaged packaging",C13)),"Packaging Problem",ISNUMBER(SEARCH("packaging",C13)),"Packaging Problem",ISNUMBER(SEARCH("discoloration",C13)),"Contamination",ISNUMBER(SEARCH("tarnish",C13)),"Contamination",ISNUMBER(SEARCH("stain",C13)),"Contamination",ISNUMBER(SEARCH("foreign material",C13)),"Contamination",ISNUMBER(SEARCH("contamina",C13)),"Contamination",ISNUMBER(SEARCH("overheat",C13)),"Overheating of Device",ISNUMBER(SEARCH("excessive heat",C13)),"Overheating of Device",ISNUMBER(SEARCH("hot",C13)),"Overheating of Device",ISNUMBER(SEARCH("noise",C13)),"Noise, Audible",ISNUMBER(SEARCH("sound",C13)),"Noise, Audible",ISNUMBER(SEARCH("loud",C13)),"Noise, Audible",ISNUMBER(SEARCH("fray",C13)),"Material Frayed",ISNUMBER(SEARCH("hole",C13)),"Material Frayed",ISNUMBER(SEARCH("tear",C13)),"Material Frayed",ISNUMBER(SEARCH("worn",C13)),"Material Frayed",ISNUMBER(SEARCH("intermittent",C13)),"Difficult or Delayed Activation",ISNUMBER(SEARCH("delay",C13)),"Difficult or Delayed Activation",ISNUMBER(SEARCH("label",C13)),"Device Markings/Labelling Problem",ISNUMBER(SEARCH("marking",C13)),"Device Markings/Labelling Problem",ISNUMBER(SEARCH("lacerat",C13)),"Defective Device",ISNUMBER(SEARCH("cut",C13)),"Defective Device",ISNUMBER(SEARCH("leak",C13)),"Fluid/Blood Leak",ISNUMBER(SEARCH("missing",C13)),"Component Missing",ISNUMBER(SEARCH("power",C13)),"Complete Loss of Power",ISNUMBER(SEARCH("will not turn on",C13)),"Complete Loss of Power",ISNUMBER(SEARCH("won't turn on",C13)),"Complete Loss of Power",ISNUMBER(SEARCH("does not turn on",C13)),"Complete Loss of Power",ISNUMBER(SEARCH("electrical",C13)),"Electrical Power Problem",ISNUMBER(SEARCH("pressure",C13)),"Detachment of Device or Device Component",ISNUMBER(SEARCH("slip",C13)),"Detachment of Device or Device Component",ISNUMBER(SEARCH("detach",C13)),"Detachment of Device or Device Component",ISNUMBER(SEARCH("stick",C13)),"Mechanical Jam",ISNUMBER(SEARCH("jam",C13)),"Mechanical Jam",ISNUMBER(SEARCH("rigid",C13)),"Mechanical Jam",ISNUMBER(SEARCH("rust",C13)),"Corroded",ISNUMBER(SEARCH("corrod",C13)),"Corroded",ISNUMBER(SEARCH("corrosion",C13)),"Corroded",ISNUMBER(SEARCH("alignment",C13)),"Defective Device",ISNUMBER(SEARCH("adjust",C13)),"Defective Device",ISNUMBER(SEARCH("perform",C13)),"Defective Device",ISNUMBER(SEARCH("malfunction",C13)),"Defective Device",ISNUMBER(SEARCH("defect",C13)),"Defective Device",ISNUMBER(SEARCH("fail",C13)),"Defective Device",ISNUMBER(SEARCH("not work",C13)),"Defective Device",ISNUMBER(SEARCH("doesn't work",C13)),"Defective Device",TRUE,"UNKNOWN"),"UNKNOWN")))} -> Defective Device | F13: =IF(E13="","","No Clinical Signs, Symptoms or Conditions") -> No Clinical Signs, Symptoms or Conditions | G13: =IF(E13="","",IFERROR(VLOOKUP(E13,Codes!$L$2:$N$409,3,FALSE),"—")) -> A0203
... A21: 2025-10-0000274 | B21: 45939 | C21: customer standing order arrived warm, _x000D_ shipped on 10/6 and arrived on 10/8 - customer sayd temp was at 9 degrees and ice pack melted._x000D_ _x000D_ Invoice: SO5500000480485 | D21: arrivedwarm | E21: {=IF(D21<>"",IFERROR(VLOOKUP(D21,Codes!$K$2:$L$409,2,FALSE),"UNKNOWN - "&D21),IF(C21="","",IFERROR(_xlfn.IFS(ISNUMBER(SEARCH("broken button",C21)),"Break",ISNUMBER(SEARCH("broken handle",C21)),"Break",ISNUMBER(SEARCH("shipping damage",C21)),"Break",ISNUMBER(SEARCH("broken",C21)),"Break",ISNUMBER(SEARCH("crack",C21)),"Break",ISNUMBER(SEARCH("snap",C21)),"Break",ISNUMBER(SEARCH("fracture",C21)),"Break",ISNUMBER(SEARCH("bent",C21)),"Material Twisted/Bent",ISNUMBER(SEARCH("twisted",C21)),"Material Twisted/Bent",ISNUMBER(SEARCH("component separat",C21)),"Material Separation",ISNUMBER(SEARCH("separat",C21)),"Material Separation",ISNUMBER(SEARCH("connection",C21)),"Loose or Intermittent Connection",ISNUMBER(SEARCH("loose",C21)),"Loose or Intermittent Connection",ISNUMBER(SEARCH("damaged packaging",C21)),"Packaging Problem",ISNUMBER(SEARCH("packaging",C21)),"Packaging Problem",ISNUMBER(SEARCH("discoloration",C21)),"Contamination",ISNUMBER(SEARCH("tarnish",C21)),"Contamination",ISNUMBER(SEARCH("stain",C21)),"Contamination",ISNUMBER(SEARCH("foreign material",C21)),"Contamination",ISNUMBER(SEARCH("contamina",C21)),"Contamination",ISNUMBER(SEARCH("overheat",C21)),"Overheating of Device",ISNUMBER(SEARCH("excessive heat",C21)),"Overheating of Device",ISNUMBER(SEARCH("hot",C21)),"Overheating of Device",ISNUMBER(SEARCH("noise",C21)),"Noise, Audible",ISNUMBER(SEARCH("sound",C21)),"Noise, Audible",ISNUMBER(SEARCH("loud",C21)),"Noise, Audible",ISNUMBER(SEARCH("fray",C21)),"Material Frayed",ISNUMBER(SEARCH("hole",C21)),"Material Frayed",ISNUMBER(SEARCH("tear",C21)),"Material Frayed",ISNUMBER(SEARCH("worn",C21)),"Material Frayed",ISNUMBER(SEARCH("intermittent",C21)),"Difficult or Delayed Activation",ISNUMBER(SEARCH("delay",C21)),"Difficult or Delayed Activation",ISNUMBER(SEARCH("label",C21)),"Device Markings/Labelling Problem",ISNUMBER(SEARCH("marking",C21)),"Device Markings/Labelling Problem",ISNUMBER(SEARCH("lacerat",C21)),"Defective Device",ISNUMBER(SEARCH("cut",C21)),"Defective Device",ISNUMBER(SEARCH("leak",C21)),"Fluid/Blood Leak",ISNUMBER(SEARCH("missing",C21)),"Component Missing",ISNUMBER(SEARCH("power",C21)),"Complete Loss of Power",ISNUMBER(SEARCH("will not turn on",C21)),"Complete Loss of Power",ISNUMBER(SEARCH("won't turn on",C21)),"Complete Loss of Power",ISNUMBER(SEARCH("does not turn on",C21)),"Complete Loss of Power",ISNUMBER(SEARCH("electrical",C21)),"Electrical Power Problem",ISNUMBER(SEARCH("pressure",C21)),"Detachment of Device or Device Component",ISNUMBER(SEARCH("slip",C21)),"Detachment of Device or Device Component",ISNUMBER(SEARCH("detach",C21)),"Detachment of Device or Device Component",ISNUMBER(SEARCH("stick",C21)),"Mechanical Jam",ISNUMBER(SEARCH("jam",C21)),"Mechanical Jam",ISNUMBER(SEARCH("rigid",C21)),"Mechanical Jam",ISNUMBER(SEARCH("rust",C21)),"Corroded",ISNUMBER(SEARCH("corrod",C21)),"Corroded",ISNUMBER(SEARCH("corrosion",C21)),"Corroded",ISNUMBER(SEARCH("alignment",C21)),"Defective Device",ISNUMBER(SEARCH("adjust",C21)),"Defective Device",ISNUMBER(SEARCH("perform",C21)),"Defective Device",ISNUMBER(SEARCH("malfunction",C21)),"Defective Device",ISNUMBER(SEARCH("defect",C21)),"Defective Device",ISNUMBER(SEARCH("fail",C21)),"Defective Device",ISNUMBER(SEARCH("not work",C21)),"Defective Device",ISNUMBER(SEARCH("doesn't work",C21)),"Defective Device",TRUE,"UNKNOWN"),"UNKNOWN")))} -> UNKNOWN - arrivedwarm | F21: =IF(E21="","","No Clinical Signs, Symptoms or Conditions") -> No Clinical Signs, Symptoms or Conditions | G21: =IF(E21="","",IFERROR(VLOOKUP(E21,Codes!$L$2:$N$409,3,FALSE),"—")) -> —
E22: {=IF(D22<>"",IFERROR(VLOOKUP(D22,Codes!$K$2:$L$409,2,FALSE),"UNKNOWN - "&D22),IF(C22="","",IFERROR(_xlfn.IFS(ISNUMBER(SEARCH("broken button",C22)),"Break",ISNUMBER(SEARCH("broken handle",C22)),"Break",ISNUMBER(SEARCH("shipping damage",C22)),"Break",ISNUMBER(SEARCH("broken",C22)),"Break",ISNUMBER(SEARCH("crack",C22)),"Break",ISNUMBER(SEARCH("snap",C22)),"Break",ISNUMBER(SEARCH("fracture",C22)),"Break",ISNUMBER(SEARCH("bent",C22)),"Material Twisted/Bent",ISNUMBER(SEARCH("twisted",C22)),"Material Twisted/Bent",ISNUMBER(SEARCH("component separat",C22)),"Material Separation",ISNUMBER(SEARCH("separat",C22)),"Material Separation",ISNUMBER(SEARCH("connection",C22)),"Loose or Intermittent Connection",ISNUMBER(SEARCH("loose",C22)),"Loose or Intermittent Connection",ISNUMBER(SEARCH("damaged packaging",C22)),"Packaging Problem",ISNUMBER(SEARCH("packaging",C22)),"Packaging Problem",ISNUMBER(SEARCH("discoloration",C22)),"Contamination",ISNUMBER(SEARCH("tarnish",C22)),"Contamination",ISNUMBER(SEARCH("stain",C22)),"Contamination",ISNUMBER(SEARCH("foreign material",C22)),"Contamination",ISNUMBER(SEARCH("contamina",C22)),"Contamination",ISNUMBER(SEARCH("overheat",C22)),"Overheating of Device",ISNUMBER(SEARCH("excessive heat",C22)),"Overheating of Device",ISNUMBER(SEARCH("hot",C22)),"Overheating of Device",ISNUMBER(SEARCH("noise",C22)),"Noise, Audible",ISNUMBER(SEARCH("sound",C22)),"Noise, Audible",ISNUMBER(SEARCH("loud",C22)),"Noise, Audible",ISNUMBER(SEARCH("fray",C22)),"Material Frayed",ISNUMBER(SEARCH("hole",C22)),"Material Frayed",ISNUMBER(SEARCH("tear",C22)),"Material Frayed",ISNUMBER(SEARCH("worn",C22)),"Material Frayed",ISNUMBER(SEARCH("intermittent",C22)),"Difficult or Delayed Activation",ISNUMBER(SEARCH("delay",C22)),"Difficult or Delayed Activation",ISNUMBER(SEARCH("label",C22)),"Device Markings/Labelling Problem",ISNUMBER(SEARCH("marking",C22)),"Device Markings/Labelling Problem",ISNUMBER(SEARCH("lacerat",C22)),"Defective Device",ISNUMBER(SEARCH("cut",C22)),"Defective Device",ISNUMBER(SEARCH("leak",C22)),"Fluid/Blood Leak",ISNUMBER(SEARCH("missing",C22)),"Component Missing",ISNUMBER(SEARCH("power",C22)),"Complete Loss of Power",ISNUMBER(SEARCH("will not turn on",C22)),"Complete Loss of Power",ISNUMBER(SEARCH("won't turn on",C22)),"Complete Loss of Power",ISNUMBER(SEARCH("does not turn on",C22)),"Complete Loss of Power",ISNUMBER(SEARCH("electrical",C22)),"Electrical Power Problem",ISNUMBER(SEARCH("pressure",C22)),"Detachment of Device or Device Component",ISNUMBER(SEARCH("slip",C22)),"Detachment of Device or Device Component",ISNUMBER(SEARCH("detach",C22)),"Detachment of Device or Device Component",ISNUMBER(SEARCH("stick",C22)),"Mechanical Jam",ISNUMBER(SEARCH("jam",C22)),"Mechanical Jam",ISNUMBER(SEARCH("rigid",C22)),"Mechanical Jam",ISNUMBER(SEARCH("rust",C22)),"Corroded",ISNUMBER(SEARCH("corrod",C22)),"Corroded",ISNUMBER(SEARCH("corrosion",C22)),"Corroded",ISNUMBER(SEARCH("alignment",C22)),"Defective Device",ISNUMBER(SEARCH("adjust",C22)),"Defective Device",ISNUMBER(SEARCH("perform",C22)),"Defective Device",ISNUMBER(SEARCH("malfunction",C22)),"Defective Device",ISNUMBER(SEARCH("defect",C22)),"Defective Device",ISNUMBER(SEARCH("fail",C22)),"Defective Device",ISNUMBER(SEARCH("not work",C22)),"Defective Device",ISNUMBER(SEARCH("doesn't work",C22)),"Defective Device",TRUE,"UNKNOWN"),"UNKNOWN")))} | F22: =IF(E22="","","No Clinical Signs, Symptoms or Conditions") | G22: =IF(E22="","",IFERROR(VLOOKUP(E22,Codes!$L$2:$N$409,3,FALSE),"—"))
E23: {=IF(D23<>"",IFERROR(VLOOKUP(D23,Codes!$K$2:$L$409,2,FALSE),"UNKNOWN - "&D23),IF(C23="","",IFERROR(_xlfn.IFS(ISNUMBER(SEARCH("broken button",C23)),"Break",ISNUMBER(SEARCH("broken handle",C23)),"Break",ISNUMBER(SEARCH("shipping damage",C23)),"Break",ISNUMBER(SEARCH("broken",C23)),"Break",ISNUMBER(SEARCH("crack",C23)),"Break",ISNUMBER(SEARCH("snap",C23)),"Break",ISNUMBER(SEARCH("fracture",C23)),"Break",ISNUMBER(SEARCH("bent",C23)),"Material Twisted/Bent",ISNUMBER(SEARCH("twisted",C23)),"Material Twisted/Bent",ISNUMBER(SEARCH("component separat",C23)),"Material Separation",ISNUMBER(SEARCH("separat",C23)),"Material Separation",ISNUMBER(SEARCH("connection",C23)),"Loose or Intermittent Connection",ISNUMBER(SEARCH("loose",C23)),"Loose or Intermittent Connection",ISNUMBER(SEARCH("damaged packaging",C23)),"Packaging Problem",ISNUMBER(SEARCH("packaging",C23)),"Packaging Problem",ISNUMBER(SEARCH("discoloration",C23)),"Contamination",ISNUMBER(SEARCH("tarnish",C23)),"Contamination",ISNUMBER(SEARCH("stain",C23)),"Contamination",ISNUMBER(SEARCH("foreign material",C23)),"Contamination",ISNUMBER(SEARCH("contamina",C23)),"Contamination",ISNUMBER(SEARCH("overheat",C23)),"Overheating of Device",ISNUMBER(SEARCH("excessive heat",C23)),"Overheating of Device",ISNUMBER(SEARCH("hot",C23)),"Overheating of Device",ISNUMBER(SEARCH("noise",C23)),"Noise, Audible",ISNUMBER(SEARCH("sound",C23)),"Noise, Audible",ISNUMBER(SEARCH("loud",C23)),"Noise, Audible",ISNUMBER(SEARCH("fray",C23)),"Material Frayed",ISNUMBER(SEARCH("hole",C23)),"Material Frayed",ISNUMBER(SEARCH("tear",C23)),"Material Frayed",ISNUMBER(SEARCH("worn",C23)),"Material Frayed",ISNUMBER(SEARCH("intermittent",C23)),"Difficult or Delayed Activation",ISNUMBER(SEARCH("delay",C23)),"Difficult or Delayed Activation",ISNUMBER(SEARCH("label",C23)),"Device Markings/Labelling Problem",ISNUMBER(SEARCH("marking",C23)),"Device Markings/Labelling Problem",ISNUMBER(SEARCH("lacerat",C23)),"Defective Device",ISNUMBER(SEARCH("cut",C23)),"Defective Device",ISNUMBER(SEARCH("leak",C23)),"Fluid/Blood Leak",ISNUMBER(SEARCH("missing",C23)),"Component Missing",ISNUMBER(SEARCH("power",C23)),"Complete Loss of Power",ISNUMBER(SEARCH("will not turn on",C23)),"Complete Loss of Power",ISNUMBER(SEARCH("won't turn on",C23)),"Complete Loss of Power",ISNUMBER(SEARCH("does not turn on",C23)),"Complete Loss of Power",ISNUMBER(SEARCH("electrical",C23)),"Electrical Power Problem",ISNUMBER(SEARCH("pressure",C23)),"Detachment of Device or Device Component",ISNUMBER(SEARCH("slip",C23)),"Detachment of Device or Device Component",ISNUMBER(SEARCH("detach",C23)),"Detachment of Device or Device Component",ISNUMBER(SEARCH("stick",C23)),"Mechanical Jam",ISNUMBER(SEARCH("jam",C23)),"Mechanical Jam",ISNUMBER(SEARCH("rigid",C23)),"Mechanical Jam",ISNUMBER(SEARCH("rust",C23)),"Corroded",ISNUMBER(SEARCH("corrod",C23)),"Corroded",ISNUMBER(SEARCH("corrosion",C23)),"Corroded",ISNUMBER(SEARCH("alignment",C23)),"Defective Device",ISNUMBER(SEARCH("adjust",C23)),"Defective Device",ISNUMBER(SEARCH("perform",C23)),"Defective Device",ISNUMBER(SEARCH("malfunction",C23)),"Defective Device",ISNUMBER(SEARCH("defect",C23)),"Defective Device",ISNUMBER(SEARCH("fail",C23)),"Defective Device",ISNUMBER(SEARCH("not work",C23)),"Defective Device",ISNUMBER(SEARCH("doesn't work",C23)),"Defective Device",TRUE,"UNKNOWN"),"UNKNOWN")))} | F23: =IF(E23="","","No Clinical Signs, Symptoms or Conditions") | G23: =IF(E23="","",IFERROR(VLOOKUP(E23,Codes!$L$2:$N$409,3,FALSE),"—"))
E24: {=IF(D24<>"",IFERROR(VLOOKUP(D24,Codes!$K$2:$L$409,2,FALSE),"UNKNOWN - "&D24),IF(C24="","",IFERROR(_xlfn.IFS(ISNUMBER(SEARCH("broken button",C24)),"Break",ISNUMBER(SEARCH("broken handle",C24)),"Break",ISNUMBER(SEARCH("shipping damage",C24)),"Break",ISNUMBER(SEARCH("broken",C24)),"Break",ISNUMBER(SEARCH("crack",C24)),"Break",ISNUMBER(SEARCH("snap",C24)),"Break",ISNUMBER(SEARCH("fracture",C24)),"Break",ISNUMBER(SEARCH("bent",C24)),"Material Twisted/Bent",ISNUMBER(SEARCH("twisted",C24)),"Material Twisted/Bent",ISNUMBER(SEARCH("component separat",C24)),"Material Separation",ISNUMBER(SEARCH("separat",C24)),"Material Separation",ISNUMBER(SEARCH("connection",C24)),"Loose or Intermittent Connection",ISNUMBER(SEARCH("loose",C24)),"Loose or Intermittent Connection",ISNUMBER(SEARCH("damaged packaging",C24)),"Packaging Problem",ISNUMBER(SEARCH("packaging",C24)),"Packaging Problem",ISNUMBER(SEARCH("discoloration",C24)),"Contamination",ISNUMBER(SEARCH("tarnish",C24)),"Contamination",ISNUMBER(SEARCH("stain",C24)),"Contamination",ISNUMBER(SEARCH("foreign material",C24)),"Contamination",ISNUMBER(SEARCH("contamina",C24)),"Contamination",ISNUMBER(SEARCH("overheat",C24)),"Overheating of Device",ISNUMBER(SEARCH("excessive heat",C24)),"Overheating of Device",ISNUMBER(SEARCH("hot",C24)),"Overheating of Device",ISNUMBER(SEARCH("noise",C24)),"Noise, Audible",ISNUMBER(SEARCH("sound",C24)),"Noise, Audible",ISNUMBER(SEARCH("loud",C24)),"Noise, Audible",ISNUMBER(SEARCH("fray",C24)),"Material Frayed",ISNUMBER(SEARCH("hole",C24)),"Material Frayed",ISNUMBER(SEARCH("tear",C24)),"Material Frayed",ISNUMBER(SEARCH("worn",C24)),"Material Frayed",ISNUMBER(SEARCH("intermittent",C24)),"Difficult or Delayed Activation",ISNUMBER(SEARCH("delay",C24)),"Difficult or Delayed Activation",ISNUMBER(SEARCH("label",C24)),"Device Markings/Labelling Problem",ISNUMBER(SEARCH("marking",C24)),"Device Markings/Labelling Problem",ISNUMBER(SEARCH("lacerat",C24)),"Defective Device",ISNUMBER(SEARCH("cut",C24)),"Defective Device",ISNUMBER(SEARCH("leak",C24)),"Fluid/Blood Leak",ISNUMBER(SEARCH("missing",C24)),"Component Missing",ISNUMBER(SEARCH("power",C24)),"Complete Loss of Power",ISNUMBER(SEARCH("will not turn on",C24)),"Complete Loss of Power",ISNUMBER(SEARCH("won't turn on",C24)),"Complete Loss of Power",ISNUMBER(SEARCH("does not turn on",C24)),"Complete Loss of Power",ISNUMBER(SEARCH("electrical",C24)),"Electrical Power Problem",ISNUMBER(SEARCH("pressure",C24)),"Detachment of Device or Device Component",ISNUMBER(SEARCH("slip",C24)),"Detachment of Device or Device Component",ISNUMBER(SEARCH("detach",C24)),"Detachment of Device or Device Component",ISNUMBER(SEARCH("stick",C24)),"Mechanical Jam",ISNUMBER(SEARCH("jam",C24)),"Mechanical Jam",ISNUMBER(SEARCH("rigid",C24)),"Mechanical Jam",ISNUMBER(SEARCH("rust",C24)),"Corroded",ISNUMBER(SEARCH("corrod",C24)),"Corroded",ISNUMBER(SEARCH("corrosion",C24)),"Corroded",ISNUMBER(SEARCH("alignment",C24)),"Defective Device",ISNUMBER(SEARCH("adjust",C24)),"Defective Device",ISNUMBER(SEARCH("perform",C24)),"Defective Device",ISNUMBER(SEARCH("malfunction",C24)),"Defective Device",ISNUMBER(SEARCH("defect",C24)),"Defective Device",ISNUMBER(SEARCH("fail",C24)),"Defective Device",ISNUMBER(SEARCH("not work",C24)),"Defective Device",ISNUMBER(SEARCH("doesn't work",C24)),"Defective Device",TRUE,"UNKNOWN"),"UNKNOWN")))} | F24: =IF(E24="","","No Clinical Signs, Symptoms or Conditions") | G24: =IF(E24="","",IFERROR(VLOOKUP(E24,Codes!$L$2:$N$409,3,FALSE),"—"))
E25: {=IF(D25<>"",IFERROR(VLOOKUP(D25,Codes!$K$2:$L$409,2,FALSE),"UNKNOWN - "&D25),IF(C25="","",IFERROR(_xlfn.IFS(ISNUMBER(SEARCH("broken button",C25)),"Break",ISNUMBER(SEARCH("broken handle",C25)),"Break",ISNUMBER(SEARCH("shipping damage",C25)),"Break",ISNUMBER(SEARCH("broken",C25)),"Break",ISNUMBER(SEARCH("crack",C25)),"Break",ISNUMBER(SEARCH("snap",C25)),"Break",ISNUMBER(SEARCH("fracture",C25)),"Break",ISNUMBER(SEARCH("bent",C25)),"Material Twisted/Bent",ISNUMBER(SEARCH("twisted",C25)),"Material Twisted/Bent",ISNUMBER(SEARCH("component separat",C25)),"Material Separation",ISNUMBER(SEARCH("separat",C25)),"Material Separation",ISNUMBER(SEARCH("connection",C25)),"Loose or Intermittent Connection",ISNUMBER(SEARCH("loose",C25)),"Loose or Intermittent Connection",ISNUMBER(SEARCH("damaged packaging",C25)),"Packaging Problem",ISNUMBER(SEARCH("packaging",C25)),"Packaging Problem",ISNUMBER(SEARCH("discoloration",C25)),"Contamination",ISNUMBER(SEARCH("tarnish",C25)),"Contamination",ISNUMBER(SEARCH("stain",C25)),"Contamination",ISNUMBER(SEARCH("foreign material",C25)),"Contamination",ISNUMBER(SEARCH("contamina",C25)),"Contamination",ISNUMBER(SEARCH("overheat",C25)),"Overheating of Device",ISNUMBER(SEARCH("excessive heat",C25)),"Overheating of Device",ISNUMBER(SEARCH("hot",C25)),"Overheating of Device",ISNUMBER(SEARCH("noise",C25)),"Noise, Audible",ISNUMBER(SEARCH("sound",C25)),"Noise, Audible",ISNUMBER(SEARCH("loud",C25)),"Noise, Audible",ISNUMBER(SEARCH("fray",C25)),"Material Frayed",ISNUMBER(SEARCH("hole",C25)),"Material Frayed",ISNUMBER(SEARCH("tear",C25)),"Material Frayed",ISNUMBER(SEARCH("worn",C25)),"Material Frayed",ISNUMBER(SEARCH("intermittent",C25)),"Difficult or Delayed Activation",ISNUMBER(SEARCH("delay",C25)),"Difficult or Delayed Activation",ISNUMBER(SEARCH("label",C25)),"Device Markings/Labelling Problem",ISNUMBER(SEARCH("marking",C25)),"Device Markings/Labelling Problem",ISNUMBER(SEARCH("lacerat",C25)),"Defective Device",ISNUMBER(SEARCH("cut",C25)),"Defective Device",ISNUMBER(SEARCH("leak",C25)),"Fluid/Blood Leak",ISNUMBER(SEARCH("missing",C25)),"Component Missing",ISNUMBER(SEARCH("power",C25)),"Complete Loss of Power",ISNUMBER(SEARCH("will not turn on",C25)),"Complete Loss of Power",ISNUMBER(SEARCH("won't turn on",C25)),"Complete Loss of Power",ISNUMBER(SEARCH("does not turn on",C25)),"Complete Loss of Power",ISNUMBER(SEARCH("electrical",C25)),"Electrical Power Problem",ISNUMBER(SEARCH("pressure",C25)),"Detachment of Device or Device Component",ISNUMBER(SEARCH("slip",C25)),"Detachment of Device or Device Component",ISNUMBER(SEARCH("detach",C25)),"Detachment of Device or Device Component",ISNUMBER(SEARCH("stick",C25)),"Mechanical Jam",ISNUMBER(SEARCH("jam",C25)),"Mechanical Jam",ISNUMBER(SEARCH("rigid",C25)),"Mechanical Jam",ISNUMBER(SEARCH("rust",C25)),"Corroded",ISNUMBER(SEARCH("corrod",C25)),"Corroded",ISNUMBER(SEARCH("corrosion",C25)),"Corroded",ISNUMBER(SEARCH("alignment",C25)),"Defective Device",ISNUMBER(SEARCH("adjust",C25)),"Defective Device",ISNUMBER(SEARCH("perform",C25)),"Defective Device",ISNUMBER(SEARCH("malfunction",C25)),"Defective Device",ISNUMBER(SEARCH("defect",C25)),"Defective Device",ISNUMBER(SEARCH("fail",C25)),"Defective Device",ISNUMBER(SEARCH("not work",C25)),"Defective Device",ISNUMBER(SEARCH("doesn't work",C25)),"Defective Device",TRUE,"UNKNOWN"),"UNKNOWN")))} | F25: =IF(E25="","","No Clinical Signs, Symptoms or Conditions") | G25: =IF(E25="","",IFERROR(VLOOKUP(E25,Codes!$L$2:$N$409,3,FALSE),"—"))
E26: {=IF(D26<>"",IFERROR(VLOOKUP(D26,Codes!$K$2:$L$409,2,FALSE),"UNKNOWN - "&D26),IF(C26="","",IFERROR(_xlfn.IFS(ISNUMBER(SEARCH("broken button",C26)),"Break",ISNUMBER(SEARCH("broken handle",C26)),"Break",ISNUMBER(SEARCH("shipping damage",C26)),"Break",ISNUMBER(SEARCH("broken",C26)),"Break",ISNUMBER(SEARCH("crack",C26)),"Break",ISNUMBER(SEARCH("snap",C26)),"Break",ISNUMBER(SEARCH("fracture",C26)),"Break",ISNUMBER(SEARCH("bent",C26)),"Material Twisted/Bent",ISNUMBER(SEARCH("twisted",C26)),"Material Twisted/Bent",ISNUMBER(SEARCH("component separat",C26)),"Material Separation",ISNUMBER(SEARCH("separat",C26)),"Material Separation",ISNUMBER(SEARCH("connection",C26)),"Loose or Intermittent Connection",ISNUMBER(SEARCH("loose",C26)),"Loose or Intermittent Connection",ISNUMBER(SEARCH("damaged packaging",C26)),"Packaging Problem",ISNUMBER(SEARCH("packaging",C26)),"Packaging Problem",ISNUMBER(SEARCH("discoloration",C26)),"Contamination",ISNUMBER(SEARCH("tarnish",C26)),"Contamination",ISNUMBER(SEARCH("stain",C26)),"Contamination",ISNUMBER(SEARCH("foreign material",C26)),"Contamination",ISNUMBER(SEARCH("contamina",C26)),"Contamination",ISNUMBER(SEARCH("overheat",C26)),"Overheating of Device",ISNUMBER(SEARCH("excessive heat",C26)),"Overheating of Device",ISNUMBER(SEARCH("hot",C26)),"Overheating of Device",ISNUMBER(SEARCH("noise",C26)),"Noise, Audible",ISNUMBER(SEARCH("sound",C26)),"Noise, Audible",ISNUMBER(SEARCH("loud",C26)),"Noise, Audible",ISNUMBER(SEARCH("fray",C26)),"Material Frayed",ISNUMBER(SEARCH("hole",C26)),"Material Frayed",ISNUMBER(SEARCH("tear",C26)),"Material Frayed",ISNUMBER(SEARCH("worn",C26)),"Material Frayed",ISNUMBER(SEARCH("intermittent",C26)),"Difficult or Delayed Activation",ISNUMBER(SEARCH("delay",C26)),"Difficult or Delayed Activation",ISNUMBER(SEARCH("label",C26)),"Device Markings/Labelling Problem",ISNUMBER(SEARCH("marking",C26)),"Device Markings/Labelling Problem",ISNUMBER(SEARCH("lacerat",C26)),"Defective Device",ISNUMBER(SEARCH("cut",C26)),"Defective Device",ISNUMBER(SEARCH("leak",C26)),"Fluid/Blood Leak",ISNUMBER(SEARCH("missing",C26)),"Component Missing",ISNUMBER(SEARCH("power",C26)),"Complete Loss of Power",ISNUMBER(SEARCH("will not turn on",C26)),"Complete Loss of Power",ISNUMBER(SEARCH("won't turn on",C26)),"Complete Loss of Power",ISNUMBER(SEARCH("does not turn on",C26)),"Complete Loss of Power",ISNUMBER(SEARCH("electrical",C26)),"Electrical Power Problem",ISNUMBER(SEARCH("pressure",C26)),"Detachment of Device or Device Component",ISNUMBER(SEARCH("slip",C26)),"Detachment of Device or Device Component",ISNUMBER(SEARCH("detach",C26)),"Detachment of Device or Device Component",ISNUMBER(SEARCH("stick",C26)),"Mechanical Jam",ISNUMBER(SEARCH("jam",C26)),"Mechanical Jam",ISNUMBER(SEARCH("rigid",C26)),"Mechanical Jam",ISNUMBER(SEARCH("rust",C26)),"Corroded",ISNUMBER(SEARCH("corrod",C26)),"Corroded",ISNUMBER(SEARCH("corrosion",C26)),"Corroded",ISNUMBER(SEARCH("alignment",C26)),"Defective Device",ISNUMBER(SEARCH("adjust",C26)),"Defective Device",ISNUMBER(SEARCH("perform",C26)),"Defective Device",ISNUMBER(SEARCH("malfunction",C26)),"Defective Device",ISNUMBER(SEARCH("defect",C26)),"Defective Device",ISNUMBER(SEARCH("fail",C26)),"Defective Device",ISNUMBER(SEARCH("not work",C26)),"Defective Device",ISNUMBER(SEARCH("doesn't work",C26)),"Defective Device",TRUE,"UNKNOWN"),"UNKNOWN")))} | F26: =IF(E26="","","No Clinical Signs, Symptoms or Conditions") | G26: =IF(E26="","",IFERROR(VLOOKUP(E26,Codes!$L$2:$N$409,3,FALSE),"—"))
E27: {=IF(D27<>"",IFERROR(VLOOKUP(D27,Codes!$K$2:$L$409,2,FALSE),"UNKNOWN - "&D27),IF(C27="","",IFERROR(_xlfn.IFS(ISNUMBER(SEARCH("broken button",C27)),"Break",ISNUMBER(SEARCH("broken handle",C27)),"Break",ISNUMBER(SEARCH("shipping damage",C27)),"Break",ISNUMBER(SEARCH("broken",C27)),"Break",ISNUMBER(SEARCH("crack",C27)),"Break",ISNUMBER(SEARCH("snap",C27)),"Break",ISNUMBER(SEARCH("fracture",C27)),"Break",ISNUMBER(SEARCH("bent",C27)),"Material Twisted/Bent",ISNUMBER(SEARCH("twisted",C27)),"Material Twisted/Bent",ISNUMBER(SEARCH("component separat",C27)),"Material Separation",ISNUMBER(SEARCH("separat",C27)),"Material Separation",ISNUMBER(SEARCH("connection",C27)),"Loose or Intermittent Connection",ISNUMBER(SEARCH("loose",C27)),"Loose or Intermittent Connection",ISNUMBER(SEARCH("damaged packaging",C27)),"Packaging Problem",ISNUMBER(SEARCH("packaging",C27)),"Packaging Problem",ISNUMBER(SEARCH("discoloration",C27)),"Contamination",ISNUMBER(SEARCH("tarnish",C27)),"Contamination",ISNUMBER(SEARCH("stain",C27)),"Contamination",ISNUMBER(SEARCH("foreign material",C27)),"Contamination",ISNUMBER(SEARCH("contamina",C27)),"Contamination",ISNUMBER(SEARCH("overheat",C27)),"Overheating of Device",ISNUMBER(SEARCH("excessive heat",C27)),"Overheating of Device",ISNUMBER(SEARCH("hot",C27)),"Overheating of Device",ISNUMBER(SEARCH("noise",C27)),"Noise, Audible",ISNUMBER(SEARCH("sound",C27)),"Noise, Audible",ISNUMBER(SEARCH("loud",C27)),"Noise, Audible",ISNUMBER(SEARCH("fray",C27)),"Material Frayed",ISNUMBER(SEARCH("hole",C27)),"Material Frayed",ISNUMBER(SEARCH("tear",C27)),"Material Frayed",ISNUMBER(SEARCH("worn",C27)),"Material Frayed",ISNUMBER(SEARCH("intermittent",C27)),"Difficult or Delayed Activation",ISNUMBER(SEARCH("delay",C27)),"Difficult or Delayed Activation",ISNUMBER(SEARCH("label",C27)),"Device Markings/Labelling Problem",ISNUMBER(SEARCH("marking",C27)),"Device Markings/Labelling Problem",ISNUMBER(SEARCH("lacerat",C27)),"Defective Device",ISNUMBER(SEARCH("cut",C27)),"Defective Device",ISNUMBER(SEARCH("leak",C27)),"Fluid/Blood Leak",ISNUMBER(SEARCH("missing",C27)),"Component Missing",ISNUMBER(SEARCH("power",C27)),"Complete Loss of Power",ISNUMBER(SEARCH("will not turn on",C27)),"Complete Loss of Power",ISNUMBER(SEARCH("won't turn on",C27)),"Complete Loss of Power",ISNUMBER(SEARCH("does not turn on",C27)),"Complete Loss of Power",ISNUMBER(SEARCH("electrical",C27)),"Electrical Power Problem",ISNUMBER(SEARCH("pressure",C27)),"Detachment of Device or Device Component",ISNUMBER(SEARCH("slip",C27)),"Detachment of Device or Device Component",ISNUMBER(SEARCH("detach",C27)),"Detachment of Device or Device Component",ISNUMBER(SEARCH("stick",C27)),"Mechanical Jam",ISNUMBER(SEARCH("jam",C27)),"Mechanical Jam",ISNUMBER(SEARCH("rigid",C27)),"Mechanical Jam",ISNUMBER(SEARCH("rust",C27)),"Corroded",ISNUMBER(SEARCH("corrod",C27)),"Corroded",ISNUMBER(SEARCH("corrosion",C27)),"Corroded",ISNUMBER(SEARCH("alignment",C27)),"Defective Device",ISNUMBER(SEARCH("adjust",C27)),"Defective Device",ISNUMBER(SEARCH("perform",C27)),"Defective Device",ISNUMBER(SEARCH("malfunction",C27)),"Defective Device",ISNUMBER(SEARCH("defect",C27)),"Defective Device",ISNUMBER(SEARCH("fail",C27)),"Defective Device",ISNUMBER(SEARCH("not work",C27)),"Defective Device",ISNUMBER(SEARCH("doesn't work",C27)),"Defective Device",TRUE,"UNKNOWN"),"UNKNOWN")))} | F27: =IF(E27="","","No Clinical Signs, Symptoms or Conditions") | G27: =IF(E27="","",IFERROR(VLOOKUP(E27,Codes!$L$2:$N$409,3,FALSE),"—"))
E28: {=IF(D28<>"",IFERROR(VLOOKUP(D28,Codes!$K$2:$L$409,2,FALSE),"UNKNOWN - "&D28),IF(C28="","",IFERROR(_xlfn.IFS(ISNUMBER(SEARCH("broken button",C28)),"Break",ISNUMBER(SEARCH("broken handle",C28)),"Break",ISNUMBER(SEARCH("shipping damage",C28)),"Break",ISNUMBER(SEARCH("broken",C28)),"Break",ISNUMBER(SEARCH("crack",C28)),"Break",ISNUMBER(SEARCH("snap",C28)),"Break",ISNUMBER(SEARCH("fracture",C28)),"Break",ISNUMBER(SEARCH("bent",C28)),"Material Twisted/Bent",ISNUMBER(SEARCH("twisted",C28)),"Material Twisted/Bent",ISNUMBER(SEARCH("component separat",C28)),"Material Separation",ISNUMBER(SEARCH("separat",C28)),"Material Separation",ISNUMBER(SEARCH("connection",C28)),"Loose or Intermittent Connection",ISNUMBER(SEARCH("loose",C28)),"Loose or Intermittent Connection",ISNUMBER(SEARCH("damaged packaging",C28)),"Packaging Problem",ISNUMBER(SEARCH("packaging",C28)),"Packaging Problem",ISNUMBER(SEARCH("discoloration",C28)),"Contamination",ISNUMBER(SEARCH("tarnish",C28)),"Contamination",ISNUMBER(SEARCH("stain",C28)),"Contamination",ISNUMBER(SEARCH("foreign material",C28)),"Contamination",ISNUMBER(SEARCH("contamina",C28)),"Contamination",ISNUMBER(SEARCH("overheat",C28)),"Overheating of Device",ISNUMBER(SEARCH("excessive heat",C28)),"Overheating of Device",ISNUMBER(SEARCH("hot",C28)),"Overheating of Device",ISNUMBER(SEARCH("noise",C28)),"Noise, Audible",ISNUMBER(SEARCH("sound",C28)),"Noise, Audible",ISNUMBER(SEARCH("loud",C28)),"Noise, Audible",ISNUMBER(SEARCH("fray",C28)),"Material Frayed",ISNUMBER(SEARCH("hole",C28)),"Material Frayed",ISNUMBER(SEARCH("tear",C28)),"Material Frayed",ISNUMBER(SEARCH("worn",C28)),"Material Frayed",ISNUMBER(SEARCH("intermittent",C28)),"Difficult or Delayed Activation",ISNUMBER(SEARCH("delay",C28)),"Difficult or Delayed Activation",ISNUMBER(SEARCH("label",C28)),"Device Markings/Labelling Problem",ISNUMBER(SEARCH("marking",C28)),"Device Markings/Labelling Problem",ISNUMBER(SEARCH("lacerat",C28)),"Defective Device",ISNUMBER(SEARCH("cut",C28)),"Defective Device",ISNUMBER(SEARCH("leak",C28)),"Fluid/Blood Leak",ISNUMBER(SEARCH("missing",C28)),"Component Missing",ISNUMBER(SEARCH("power",C28)),"Complete Loss of Power",ISNUMBER(SEARCH("will not turn on",C28)),"Complete Loss of Power",ISNUMBER(SEARCH("won't turn on",C28)),"Complete Loss of Power",ISNUMBER(SEARCH("does not turn on",C28)),"Complete Loss of Power",ISNUMBER(SEARCH("electrical",C28)),"Electrical Power Problem",ISNUMBER(SEARCH("pressure",C28)),"Detachment of Device or Device Component",ISNUMBER(SEARCH("slip",C28)),"Detachment of Device or Device Component",ISNUMBER(SEARCH("detach",C28)),"Detachment of Device or Device Component",ISNUMBER(SEARCH("stick",C28)),"Mechanical Jam",ISNUMBER(SEARCH("jam",C28)),"Mechanical Jam",ISNUMBER(SEARCH("rigid",C28)),"Mechanical Jam",ISNUMBER(SEARCH("rust",C28)),"Corroded",ISNUMBER(SEARCH("corrod",C28)),"Corroded",ISNUMBER(SEARCH("corrosion",C28)),"Corroded",ISNUMBER(SEARCH("alignment",C28)),"Defective Device",ISNUMBER(SEARCH("adjust",C28)),"Defective Device",ISNUMBER(SEARCH("perform",C28)),"Defective Device",ISNUMBER(SEARCH("malfunction",C28)),"Defective Device",ISNUMBER(SEARCH("defect",C28)),"Defective Device",ISNUMBER(SEARCH("fail",C28)),"Defective Device",ISNUMBER(SEARCH("not work",C28)),"Defective Device",ISNUMBER(SEARCH("doesn't work",C28)),"Defective Device",TRUE,"UNKNOWN"),"UNKNOWN")))} | F28: =IF(E28="","","No Clinical Signs, Symptoms or Conditions") | G28: =IF(E28="","",IFERROR(VLOOKUP(E28,Codes!$L$2:$N$409,3,FALSE),"—"))
E29: {=IF(D29<>"",IFERROR(VLOOKUP(D29,Codes!$K$2:$L$409,2,FALSE),"UNKNOWN - "&D29),IF(C29="","",IFERROR(_xlfn.IFS(ISNUMBER(SEARCH("broken button",C29)),"Break",ISNUMBER(SEARCH("broken handle",C29)),"Break",ISNUMBER(SEARCH("shipping damage",C29)),"Break",ISNUMBER(SEARCH("broken",C29)),"Break",ISNUMBER(SEARCH("crack",C29)),"Break",ISNUMBER(SEARCH("snap",C29)),"Break",ISNUMBER(SEARCH("fracture",C29)),"Break",ISNUMBER(SEARCH("bent",C29)),"Material Twisted/Bent",ISNUMBER(SEARCH("twisted",C29)),"Material Twisted/Bent",ISNUMBER(SEARCH("component separat",C29)),"Material Separation",ISNUMBER(SEARCH("separat",C29)),"Material Separation",ISNUMBER(SEARCH("connection",C29)),"Loose or Intermittent Connection",ISNUMBER(SEARCH("loose",C29)),"Loose or Intermittent Connection",ISNUMBER(SEARCH("damaged packaging",C29)),"Packaging Problem",ISNUMBER(SEARCH("packaging",C29)),"Packaging Problem",ISNUMBER(SEARCH("discoloration",C29)),"Contamination",ISNUMBER(SEARCH("tarnish",C29)),"Contamination",ISNUMBER(SEARCH("stain",C29)),"Contamination",ISNUMBER(SEARCH("foreign material",C29)),"Contamination",ISNUMBER(SEARCH("contamina",C29)),"Contamination",ISNUMBER(SEARCH("overheat",C29)),"Overheating of Device",ISNUMBER(SEARCH("excessive heat",C29)),"Overheating of Device",ISNUMBER(SEARCH("hot",C29)),"Overheating of Device",ISNUMBER(SEARCH("noise",C29)),"Noise, Audible",ISNUMBER(SEARCH("sound",C29)),"Noise, Audible",ISNUMBER(SEARCH("loud",C29)),"Noise, Audible",ISNUMBER(SEARCH("fray",C29)),"Material Frayed",ISNUMBER(SEARCH("hole",C29)),"Material Frayed",ISNUMBER(SEARCH("tear",C29)),"Material Frayed",ISNUMBER(SEARCH("worn",C29)),"Material Frayed",ISNUMBER(SEARCH("intermittent",C29)),"Difficult or Delayed Activation",ISNUMBER(SEARCH("delay",C29)),"Difficult or Delayed Activation",ISNUMBER(SEARCH("label",C29)),"Device Markings/Labelling Problem",ISNUMBER(SEARCH("marking",C29)),"Device Markings/Labelling Problem",ISNUMBER(SEARCH("lacerat",C29)),"Defective Device",ISNUMBER(SEARCH("cut",C29)),"Defective Device",ISNUMBER(SEARCH("leak",C29)),"Fluid/Blood Leak",ISNUMBER(SEARCH("missing",C29)),"Component Missing",ISNUMBER(SEARCH("power",C29)),"Complete Loss of Power",ISNUMBER(SEARCH("will not turn on",C29)),"Complete Loss of Power",ISNUMBER(SEARCH("won't turn on",C29)),"Complete Loss of Power",ISNUMBER(SEARCH("does not turn on",C29)),"Complete Loss of Power",ISNUMBER(SEARCH("electrical",C29)),"Electrical Power Problem",ISNUMBER(SEARCH("pressure",C29)),"Detachment of Device or Device Component",ISNUMBER(SEARCH("slip",C29)),"Detachment of Device or Device Component",ISNUMBER(SEARCH("detach",C29)),"Detachment of Device or Device Component",ISNUMBER(SEARCH("stick",C29)),"Mechanical Jam",ISNUMBER(SEARCH("jam",C29)),"Mechanical Jam",ISNUMBER(SEARCH("rigid",C29)),"Mechanical Jam",ISNUMBER(SEARCH("rust",C29)),"Corroded",ISNUMBER(SEARCH("corrod",C29)),"Corroded",ISNUMBER(SEARCH("corrosion",C29)),"Corroded",ISNUMBER(SEARCH("alignment",C29)),"Defective Device",ISNUMBER(SEARCH("adjust",C29)),"Defective Device",ISNUMBER(SEARCH("perform",C29)),"Defective Device",ISNUMBER(SEARCH("malfunction",C29)),"Defective Device",ISNUMBER(SEARCH("defect",C29)),"Defective Device",ISNUMBER(SEARCH("fail",C29)),"Defective Device",ISNUMBER(SEARCH("not work",C29)),"Defective Device",ISNUMBER(SEARCH("doesn't work",C29)),"Defective Device",TRUE,"UNKNOWN"),"UNKNOWN")))} | F29: =IF(E29="","","No Clinical Signs, Symptoms or Conditions") | G29: =IF(E29="","",IFERROR(VLOOKUP(E29,Codes!$L$2:$N$409,3,FALSE),"—"))
E30: {=IF(D30<>"",IFERROR(VLOOKUP(D30,Codes!$K$2:$L$409,2,FALSE),"UNKNOWN - "&D30),IF(C30="","",IFERROR(_xlfn.IFS(ISNUMBER(SEARCH("broken button",C30)),"Break",ISNUMBER(SEARCH("broken handle",C30)),"Break",ISNUMBER(SEARCH("shipping damage",C30)),"Break",ISNUMBER(SEARCH("broken",C30)),"Break",ISNUMBER(SEARCH("crack",C30)),"Break",ISNUMBER(SEARCH("snap",C30)),"Break",ISNUMBER(SEARCH("fracture",C30)),"Break",ISNUMBER(SEARCH("bent",C30)),"Material Twisted/Bent",ISNUMBER(SEARCH("twisted",C30)),"Material Twisted/Bent",ISNUMBER(SEARCH("component separat",C30)),"Material Separation",ISNUMBER(SEARCH("separat",C30)),"Material Separation",ISNUMBER(SEARCH("connection",C30)),"Loose or Intermittent Connection",ISNUMBER(SEARCH("loose",C30)),"Loose or Intermittent Connection",ISNUMBER(SEARCH("damaged packaging",C30)),"Packaging Problem",ISNUMBER(SEARCH("packaging",C30)),"Packaging Problem",ISNUMBER(SEARCH("discoloration",C30)),"Contamination",ISNUMBER(SEARCH("tarnish",C30)),"Contamination",ISNUMBER(SEARCH("stain",C30)),"Contamination",ISNUMBER(SEARCH("foreign material",C30)),"Contamination",ISNUMBER(SEARCH("contamina",C30)),"Contamination",ISNUMBER(SEARCH("overheat",C30)),"Overheating of Device",ISNUMBER(SEARCH("excessive heat",C30)),"Overheating of Device",ISNUMBER(SEARCH("hot",C30)),"Overheating of Device",ISNUMBER(SEARCH("noise",C30)),"Noise, Audible",ISNUMBER(SEARCH("sound",C30)),"Noise, Audible",ISNUMBER(SEARCH("loud",C30)),"Noise, Audible",ISNUMBER(SEARCH("fray",C30)),"Material Frayed",ISNUMBER(SEARCH("hole",C30)),"Material Frayed",ISNUMBER(SEARCH("tear",C30)),"Material Frayed",ISNUMBER(SEARCH("worn",C30)),"Material Frayed",ISNUMBER(SEARCH("intermittent",C30)),"Difficult or Delayed Activation",ISNUMBER(SEARCH("delay",C30)),"Difficult or Delayed Activation",ISNUMBER(SEARCH("label",C30)),"Device Markings/Labelling Problem",ISNUMBER(SEARCH("marking",C30)),"Device Markings/Labelling Problem",ISNUMBER(SEARCH("lacerat",C30)),"Defective Device",ISNUMBER(SEARCH("cut",C30)),"Defective Device",ISNUMBER(SEARCH("leak",C30)),"Fluid/Blood Leak",ISNUMBER(SEARCH("missing",C30)),"Component Missing",ISNUMBER(SEARCH("power",C30)),"Complete Loss of Power",ISNUMBER(SEARCH("will not turn on",C30)),"Complete Loss of Power",ISNUMBER(SEARCH("won't turn on",C30)),"Complete Loss of Power",ISNUMBER(SEARCH("does not turn on",C30)),"Complete Loss of Power",ISNUMBER(SEARCH("electrical",C30)),"Electrical Power Problem",ISNUMBER(SEARCH("pressure",C30)),"Detachment of Device or Device Component",ISNUMBER(SEARCH("slip",C30)),"Detachment of Device or Device Component",ISNUMBER(SEARCH("detach",C30)),"Detachment of Device or Device Component",ISNUMBER(SEARCH("stick",C30)),"Mechanical Jam",ISNUMBER(SEARCH("jam",C30)),"Mechanical Jam",ISNUMBER(SEARCH("rigid",C30)),"Mechanical Jam",ISNUMBER(SEARCH("rust",C30)),"Corroded",ISNUMBER(SEARCH("corrod",C30)),"Corroded",ISNUMBER(SEARCH("corrosion",C30)),"Corroded",ISNUMBER(SEARCH("alignment",C30)),"Defective Device",ISNUMBER(SEARCH("adjust",C30)),"Defective Device",ISNUMBER(SEARCH("perform",C30)),"Defective Device",ISNUMBER(SEARCH("malfunction",C30)),"Defective Device",ISNUMBER(SEARCH("defect",C30)),"Defective Device",ISNUMBER(SEARCH("fail",C30)),"Defective Device",ISNUMBER(SEARCH("not work",C30)),"Defective Device",ISNUMBER(SEARCH("doesn't work",C30)),"Defective Device",TRUE,"UNKNOWN"),"UNKNOWN")))} | F30: =IF(E30="","","No Clinical Signs, Symptoms or Conditions") | G30: =IF(E30="","",IFERROR(VLOOKUP(E30,Codes!$L$2:$N$409,3,FALSE),"—"))
E31: {=IF(D31<>"",IFERROR(VLOOKUP(D31,Codes!$K$2:$L$409,2,FALSE),"UNKNOWN - "&D31),IF(C31="","",IFERROR(_xlfn.IFS(ISNUMBER(SEARCH("broken button",C31)),"Break",ISNUMBER(SEARCH("broken handle",C31)),"Break",ISNUMBER(SEARCH("shipping damage",C31)),"Break",ISNUMBER(SEARCH("broken",C31)),"Break",ISNUMBER(SEARCH("crack",C31)),"Break",ISNUMBER(SEARCH("snap",C31)),"Break",ISNUMBER(SEARCH("fracture",C31)),"Break",ISNUMBER(SEARCH("bent",C31)),"Material Twisted/Bent",ISNUMBER(SEARCH("twisted",C31)),"Material Twisted/Bent",ISNUMBER(SEARCH("component separat",C31)),"Material Separation",ISNUMBER(SEARCH("separat",C31)),"Material Separation",ISNUMBER(SEARCH("connection",C31)),"Loose or Intermittent Connection",ISNUMBER(SEARCH("loose",C31)),"Loose or Intermittent Connection",ISNUMBER(SEARCH("damaged packaging",C31)),"Packaging Problem",ISNUMBER(SEARCH("packaging",C31)),"Packaging Problem",ISNUMBER(SEARCH("discoloration",C31)),"Contamination",ISNUMBER(SEARCH("tarnish",C31)),"Contamination",ISNUMBER(SEARCH("stain",C31)),"Contamination",ISNUMBER(SEARCH("foreign material",C31)),"Contamination",ISNUMBER(SEARCH("contamina",C31)),"Contamination",ISNUMBER(SEARCH("overheat",C31)),"Overheating of Device",ISNUMBER(SEARCH("excessive heat",C31)),"Overheating of Device",ISNUMBER(SEARCH("hot",C31)),"Overheating of Device",ISNUMBER(SEARCH("noise",C31)),"Noise, Audible",ISNUMBER(SEARCH("sound",C31)),"Noise, Audible",ISNUMBER(SEARCH("loud",C31)),"Noise, Audible",ISNUMBER(SEARCH("fray",C31)),"Material Frayed",ISNUMBER(SEARCH("hole",C31)),"Material Frayed",ISNUMBER(SEARCH("tear",C31)),"Material Frayed",ISNUMBER(SEARCH("worn",C31)),"Material Frayed",ISNUMBER(SEARCH("intermittent",C31)),"Difficult or Delayed Activation",ISNUMBER(SEARCH("delay",C31)),"Difficult or Delayed Activation",ISNUMBER(SEARCH("label",C31)),"Device Markings/Labelling Problem",ISNUMBER(SEARCH("marking",C31)),"Device Markings/Labelling Problem",ISNUMBER(SEARCH("lacerat",C31)),"Defective Device",ISNUMBER(SEARCH("cut",C31)),"Defective Device",ISNUMBER(SEARCH("leak",C31)),"Fluid/Blood Leak",ISNUMBER(SEARCH("missing",C31)),"Component Missing",ISNUMBER(SEARCH("power",C31)),"Complete Loss of Power",ISNUMBER(SEARCH("will not turn on",C31)),"Complete Loss of Power",ISNUMBER(SEARCH("won't turn on",C31)),"Complete Loss of Power",ISNUMBER(SEARCH("does not turn on",C31)),"Complete Loss of Power",ISNUMBER(SEARCH("electrical",C31)),"Electrical Power Problem",ISNUMBER(SEARCH("pressure",C31)),"Detachment of Device or Device Component",ISNUMBER(SEARCH("slip",C31)),"Detachment of Device or Device Component",ISNUMBER(SEARCH("detach",C31)),"Detachment of Device or Device Component",ISNUMBER(SEARCH("stick",C31)),"Mechanical Jam",ISNUMBER(SEARCH("jam",C31)),"Mechanical Jam",ISNUMBER(SEARCH("rigid",C31)),"Mechanical Jam",ISNUMBER(SEARCH("rust",C31)),"Corroded",ISNUMBER(SEARCH("corrod",C31)),"Corroded",ISNUMBER(SEARCH("corrosion",C31)),"Corroded",ISNUMBER(SEARCH("alignment",C31)),"Defective Device",ISNUMBER(SEARCH("adjust",C31)),"Defective Device",ISNUMBER(SEARCH("perform",C31)),"Defective Device",ISNUMBER(SEARCH("malfunction",C31)),"Defective Device",ISNUMBER(SEARCH("defect",C31)),"Defective Device",ISNUMBER(SEARCH("fail",C31)),"Defective Device",ISNUMBER(SEARCH("not work",C31)),"Defective Device",ISNUMBER(SEARCH("doesn't work",C31)),"Defective Device",TRUE,"UNKNOWN"),"UNKNOWN")))} | F31: =IF(E31="","","No Clinical Signs, Symptoms or Conditions") | G31: =IF(E31="","",IFERROR(VLOOKUP(E31,Codes!$L$2:$N$409,3,FALSE),"—"))
E32: {=IF(D32<>"",IFERROR(VLOOKUP(D32,Codes!$K$2:$L$409,2,FALSE),"UNKNOWN - "&D32),IF(C32="","",IFERROR(_xlfn.IFS(ISNUMBER(SEARCH("broken button",C32)),"Break",ISNUMBER(SEARCH("broken handle",C32)),"Break",ISNUMBER(SEARCH("shipping damage",C32)),"Break",ISNUMBER(SEARCH("broken",C32)),"Break",ISNUMBER(SEARCH("crack",C32)),"Break",ISNUMBER(SEARCH("snap",C32)),"Break",ISNUMBER(SEARCH("fracture",C32)),"Break",ISNUMBER(SEARCH("bent",C32)),"Material Twisted/Bent",ISNUMBER(SEARCH("twisted",C32)),"Material Twisted/Bent",ISNUMBER(SEARCH("component separat",C32)),"Material Separation",ISNUMBER(SEARCH("separat",C32)),"Material Separation",ISNUMBER(SEARCH("connection",C32)),"Loose or Intermittent Connection",ISNUMBER(SEARCH("loose",C32)),"Loose or Intermittent Connection",ISNUMBER(SEARCH("damaged packaging",C32)),"Packaging Problem",ISNUMBER(SEARCH("packaging",C32)),"Packaging Problem",ISNUMBER(SEARCH("discoloration",C32)),"Contamination",ISNUMBER(SEARCH("tarnish",C32)),"Contamination",ISNUMBER(SEARCH("stain",C32)),"Contamination",ISNUMBER(SEARCH("foreign material",C32)),"Contamination",ISNUMBER(SEARCH("contamina",C32)),"Contamination",ISNUMBER(SEARCH("overheat",C32)),"Overheating of Device",ISNUMBER(SEARCH("excessive heat",C32)),"Overheating of Device",ISNUMBER(SEARCH("hot",C32)),"Overheating of Device",ISNUMBER(SEARCH("noise",C32)),"Noise, Audible",ISNUMBER(SEARCH("sound",C32)),"Noise, Audible",ISNUMBER(SEARCH("loud",C32)),"Noise, Audible",ISNUMBER(SEARCH("fray",C32)),"Material Frayed",ISNUMBER(SEARCH("hole",C32)),"Material Frayed",ISNUMBER(SEARCH("tear",C32)),"Material Frayed",ISNUMBER(SEARCH("worn",C32)),"Material Frayed",ISNUMBER(SEARCH("intermittent",C32)),"Difficult or Delayed Activation",ISNUMBER(SEARCH("delay",C32)),"Difficult or Delayed Activation",ISNUMBER(SEARCH("label",C32)),"Device Markings/Labelling Problem",ISNUMBER(SEARCH("marking",C32)),"Device Markings/Labelling Problem",ISNUMBER(SEARCH("lacerat",C32)),"Defective Device",ISNUMBER(SEARCH("cut",C32)),"Defective Device",ISNUMBER(SEARCH("leak",C32)),"Fluid/Blood Leak",ISNUMBER(SEARCH("missing",C32)),"Component Missing",ISNUMBER(SEARCH("power",C32)),"Complete Loss of Power",ISNUMBER(SEARCH("will not turn on",C32)),"Complete Loss of Power",ISNUMBER(SEARCH("won't turn on",C32)),"Complete Loss of Power",ISNUMBER(SEARCH("does not turn on",C32)),"Complete Loss of Power",ISNUMBER(SEARCH("electrical",C32)),"Electrical Power Problem",ISNUMBER(SEARCH("pressure",C32)),"Detachment of Device or Device Component",ISNUMBER(SEARCH("slip",C32)),"Detachment of Device or Device Component",ISNUMBER(SEARCH("detach",C32)),"Detachment of Device or Device Component",ISNUMBER(SEARCH("stick",C32)),"Mechanical Jam",ISNUMBER(SEARCH("jam",C32)),"Mechanical Jam",ISNUMBER(SEARCH("rigid",C32)),"Mechanical Jam",ISNUMBER(SEARCH("rust",C32)),"Corroded",ISNUMBER(SEARCH("corrod",C32)),"Corroded",ISNUMBER(SEARCH("corrosion",C32)),"Corroded",ISNUMBER(SEARCH("alignment",C32)),"Defective Device",ISNUMBER(SEARCH("adjust",C32)),"Defective Device",ISNUMBER(SEARCH("perform",C32)),"Defective Device",ISNUMBER(SEARCH("malfunction",C32)),"Defective Device",ISNUMBER(SEARCH("defect",C32)),"Defective Device",ISNUMBER(SEARCH("fail",C32)),"Defective Device",ISNUMBER(SEARCH("not work",C32)),"Defective Device",ISNUMBER(SEARCH("doesn't work",C32)),"Defective Device",TRUE,"UNKNOWN"),"UNKNOWN")))} | F32: =IF(E32="","","No Clinical Signs, Symptoms or Conditions") | G32: =IF(E32="","",IFERROR(VLOOKUP(E32,Codes!$L$2:$N$409,3,FALSE),"—"))
E33: {=IF(D33<>"",IFERROR(VLOOKUP(D33,Codes!$K$2:$L$409,2,FALSE),"UNKNOWN - "&D33),IF(C33="","",IFERROR(_xlfn.IFS(ISNUMBER(SEARCH("broken button",C33)),"Break",ISNUMBER(SEARCH("broken handle",C33)),"Break",ISNUMBER(SEARCH("shipping damage",C33)),"Break",ISNUMBER(SEARCH("broken",C33)),"Break",ISNUMBER(SEARCH("crack",C33)),"Break",ISNUMBER(SEARCH("snap",C33)),"Break",ISNUMBER(SEARCH("fracture",C33)),"Break",ISNUMBER(SEARCH("bent",C33)),"Material Twisted/Bent",ISNUMBER(SEARCH("twisted",C33)),"Material Twisted/Bent",ISNUMBER(SEARCH("component separat",C33)),"Material Separation",ISNUMBER(SEARCH("separat",C33)),"Material Separation",ISNUMBER(SEARCH("connection",C33)),"Loose or Intermittent Connection",ISNUMBER(SEARCH("loose",C33)),"Loose or Intermittent Connection",ISNUMBER(SEARCH("damaged packaging",C33)),"Packaging Problem",ISNUMBER(SEARCH("packaging",C33)),"Packaging Problem",ISNUMBER(SEARCH("discoloration",C33)),"Contamination",ISNUMBER(SEARCH("tarnish",C33)),"Contamination",ISNUMBER(SEARCH("stain",C33)),"Contamination",ISNUMBER(SEARCH("foreign material",C33)),"Contamination",ISNUMBER(SEARCH("contamina",C33)),"Contamination",ISNUMBER(SEARCH("overheat",C33)),"Overheating of Device",ISNUMBER(SEARCH("excessive heat",C33)),"Overheating of Device",ISNUMBER(SEARCH("hot",C33)),"Overheating of Device",ISNUMBER(SEARCH("noise",C33)),"Noise, Audible",ISNUMBER(SEARCH("sound",C33)),"Noise, Audible",ISNUMBER(SEARCH("loud",C33)),"Noise, Audible",ISNUMBER(SEARCH("fray",C33)),"Material Frayed",ISNUMBER(SEARCH("hole",C33)),"Material Frayed",ISNUMBER(SEARCH("tear",C33)),"Material Frayed",ISNUMBER(SEARCH("worn",C33)),"Material Frayed",ISNUMBER(SEARCH("intermittent",C33)),"Difficult or Delayed Activation",ISNUMBER(SEARCH("delay",C33)),"Difficult or Delayed Activation",ISNUMBER(SEARCH("label",C33)),"Device Markings/Labelling Problem",ISNUMBER(SEARCH("marking",C33)),"Device Markings/Labelling Problem",ISNUMBER(SEARCH("lacerat",C33)),"Defective Device",ISNUMBER(SEARCH("cut",C33)),"Defective Device",ISNUMBER(SEARCH("leak",C33)),"Fluid/Blood Leak",ISNUMBER(SEARCH("missing",C33)),"Component Missing",ISNUMBER(SEARCH("power",C33)),"Complete Loss of Power",ISNUMBER(SEARCH("will not turn on",C33)),"Complete Loss of Power",ISNUMBER(SEARCH("won't turn on",C33)),"Complete Loss of Power",ISNUMBER(SEARCH("does not turn on",C33)),"Complete Loss of Power",ISNUMBER(SEARCH("electrical",C33)),"Electrical Power Problem",ISNUMBER(SEARCH("pressure",C33)),"Detachment of Device or Device Component",ISNUMBER(SEARCH("slip",C33)),"Detachment of Device or Device Component",ISNUMBER(SEARCH("detach",C33)),"Detachment of Device or Device Component",ISNUMBER(SEARCH("stick",C33)),"Mechanical Jam",ISNUMBER(SEARCH("jam",C33)),"Mechanical Jam",ISNUMBER(SEARCH("rigid",C33)),"Mechanical Jam",ISNUMBER(SEARCH("rust",C33)),"Corroded",ISNUMBER(SEARCH("corrod",C33)),"Corroded",ISNUMBER(SEARCH("corrosion",C33)),"Corroded",ISNUMBER(SEARCH("alignment",C33)),"Defective Device",ISNUMBER(SEARCH("adjust",C33)),"Defective Device",ISNUMBER(SEARCH("perform",C33)),"Defective Device",ISNUMBER(SEARCH("malfunction",C33)),"Defective Device",ISNUMBER(SEARCH("defect",C33)),"Defective Device",ISNUMBER(SEARCH("fail",C33)),"Defective Device",ISNUMBER(SEARCH("not work",C33)),"Defective Device",ISNUMBER(SEARCH("doesn't work",C33)),"Defective Device",TRUE,"UNKNOWN"),"UNKNOWN")))} | F33: =IF(E33="","","No Clinical Signs, Symptoms or Conditions") | G33: =IF(E33="","",IFERROR(VLOOKUP(E33,Codes!$L$2:$N$409,3,FALSE),"—"))
... E928: {=IF(D928<>"",IFERROR(VLOOKUP(D928,Codes!$K$2:$L$409,2,FALSE),"UNKNOWN - "&D928),IF(C928="","",IFERROR(_xlfn.IFS(ISNUMBER(SEARCH("broken button",C928)),"Break",ISNUMBER(SEARCH("broken handle",C928)),"Break",ISNUMBER(SEARCH("shipping damage",C928)),"Break",ISNUMBER(SEARCH("broken",C928)),"Break",ISNUMBER(SEARCH("crack",C928)),"Break",ISNUMBER(SEARCH("snap",C928)),"Break",ISNUMBER(SEARCH("fracture",C928)),"Break",ISNUMBER(SEARCH("bent",C928)),"Material Twisted/Bent",ISNUMBER(SEARCH("twisted",C928)),"Material Twisted/Bent",ISNUMBER(SEARCH("component separat",C928)),"Material Separation",ISNUMBER(SEARCH("separat",C928)),"Material Separation",ISNUMBER(SEARCH("connection",C928)),"Loose or Intermittent Connection",ISNUMBER(SEARCH("loose",C928)),"Loose or Intermittent Connection",ISNUMBER(SEARCH("damaged packaging",C928)),"Packaging Problem",ISNUMBER(SEARCH("packaging",C928)),"Packaging Problem",ISNUMBER(SEARCH("discoloration",C928)),"Contamination",ISNUMBER(SEARCH("tarnish",C928)),"Contamination",ISNUMBER(SEARCH("stain",C928)),"Contamination",ISNUMBER(SEARCH("foreign material",C928)),"Contamination",ISNUMBER(SEARCH("contamina",C928)),"Contamination",ISNUMBER(SEARCH("overheat",C928)),"Overheating of Device",ISNUMBER(SEARCH("excessive heat",C928)),"Overheating of Device",ISNUMBER(SEARCH("hot",C928)),"Overheating of Device",ISNUMBER(SEARCH("noise",C928)),"Noise, Audible",ISNUMBER(SEARCH("sound",C928)),"Noise, Audible",ISNUMBER(SEARCH("loud",C928)),"Noise, Audible",ISNUMBER(SEARCH("fray",C928)),"Material Frayed",ISNUMBER(SEARCH("hole",C928)),"Material Frayed",ISNUMBER(SEARCH("tear",C928)),"Material Frayed",ISNUMBER(SEARCH("worn",C928)),"Material Frayed",ISNUMBER(SEARCH("intermittent",C928)),"Difficult or Delayed Activation",ISNUMBER(SEARCH("delay",C928)),"Difficult or Delayed Activation",ISNUMBER(SEARCH("label",C928)),"Device Markings/Labelling Problem",ISNUMBER(SEARCH("marking",C928)),"Device Markings/Labelling Problem",ISNUMBER(SEARCH("lacerat",C928)),"Defective Device",ISNUMBER(SEARCH("cut",C928)),"Defective Device",ISNUMBER(SEARCH("leak",C928)),"Fluid/Blood Leak",ISNUMBER(SEARCH("missing",C928)),"Component Missing",ISNUMBER(SEARCH("power",C928)),"Complete Loss of Power",ISNUMBER(SEARCH("will not turn on",C928)),"Complete Loss of Power",ISNUMBER(SEARCH("won't turn on",C928)),"Complete Loss of Power",ISNUMBER(SEARCH("does not turn on",C928)),"Complete Loss of Power",ISNUMBER(SEARCH("electrical",C928)),"Electrical Power Problem",ISNUMBER(SEARCH("pressure",C928)),"Detachment of Device or Device Component",ISNUMBER(SEARCH("slip",C928)),"Detachment of Device or Device Component",ISNUMBER(SEARCH("detach",C928)),"Detachment of Device or Device Component",ISNUMBER(SEARCH("stick",C928)),"Mechanical Jam",ISNUMBER(SEARCH("jam",C928)),"Mechanical Jam",ISNUMBER(SEARCH("rigid",C928)),"Mechanical Jam",ISNUMBER(SEARCH("rust",C928)),"Corroded",ISNUMBER(SEARCH("corrod",C928)),"Corroded",ISNUMBER(SEARCH("corrosion",C928)),"Corroded",ISNUMBER(SEARCH("alignment",C928)),"Defective Device",ISNUMBER(SEARCH("adjust",C928)),"Defective Device",ISNUMBER(SEARCH("perform",C928)),"Defective Device",ISNUMBER(SEARCH("malfunction",C928)),"Defective Device",ISNUMBER(SEARCH("defect",C928)),"Defective Device",ISNUMBER(SEARCH("fail",C928)),"Defective Device",ISNUMBER(SEARCH("not work",C928)),"Defective Device",ISNUMBER(SEARCH("doesn't work",C928)),"Defective Device",TRUE,"UNKNOWN"),"UNKNOWN")))} | F928: =IF(E928="","","No Clinical Signs, Symptoms or Conditions") | G928: =IF(E928="","",IFERROR(VLOOKUP(E928,Codes!$L$2:$N$409,3,FALSE),"—"))

Sheet Sales
A1: Country | B1: Month | C1: Quantity | D1: Calendar year
A2: Argentina | B2: April | C2: 48 | D2: 2024
A3: Argentina | B3: April | C3: 10 | D3: 2024
A4: Argentina | B4: April | C4: 25 | D4: 2025
A5: Argentina | B5: April | C5: 2 | D5: 2025
A6: Argentina | B6: August | C6: 24 | D6: 2024
A7: Argentina | B7: August | C7: 3 | D7: 2024
A8: Argentina | B8: December | C8: 23 | D8: 2024
A9: Argentina | B9: December | C9: 2 | D9: 2024
A10: Argentina | B10: February | C10: 25 | D10: 2025
A11: Argentina | B11: February | C11: 1 | D11: 2025
A12: Argentina | B12: January | C12: 24 | D12: 2025
A13: Argentina | B13: January | C13: 1 | D13: 2025
... A4794: Ukraine | B4794: September | C4794: 2 | D4794: 2024

Sheet Harms table
A1: Date Range Inputs
A2: 12-Month Start | B2: =IF(Config!C8="","",Config!C8) -> 44743 | C2: 12-Month End | D2: =IF(Config!C9="","",IF(Config!C10="Annual",Config!C9,DATE(YEAR(Config!C8),MONTH(Config!C8)+11,DAY(EOMONTH(Config!C8,11))))) -> 45838
A3: 24-Month Start | B3: =IF(B2="","",DATE(YEAR(B2)+1,MONTH(B2),DAY(B2))) -> 45108 | C3: 24-Month End | D3: =IF(Config!C9="","",Config!C9) -> 45838 | F3: Table 7 Complaint Rate (and Complaint Count) by Harm and Medical Device Problem [Use this table if the PSUR update frequency is 'annually'.]
A4: Surveillance Start | B4: =IF(Config!C8="","",Config!C8) -> 44743 | C4: Surveillance End (Annual) | D4: =$D$2 -> 45838
C5: Surveillance End (Biennial) | D5: =$D$3 -> 45838
A6: Total Sales (Surv-Ann) | B6: =IF(B2="",0,SUMIFS('Complaint Rate'!$C$2:$C$46,'Complaint Rate'!$A$2:$A$46,">="&B2,'Complaint Rate'!$A$2:$A$46,"<="&D2)) -> 60476 | C6: Total Sales (Surv-Biennial) | D6: =IF(B4="",0,SUMIFS('Complaint Rate'!$C$2:$C$46,'Complaint Rate'!$A$2:$A$46,">="&B4,'Complaint Rate'!$A$2:$A$46,"<="&D5)) -> 60476 | F6: Harm | G6: Current 12‑Month Data Collection Period | I6: Max Expected Rate of Occurrence (from the RACT[1]) | J6: Max Expected Rate (Numeric)
H7: Cumulative Surveillance Period
A8: Total Sales (12-Mo) | B8: =B6 -> 60476 | C8: Total Sales (24-Mo) | D8: =IF(B3="",0,SUMIFS('Complaint Rate'!$C$2:$C$46,'Complaint Rate'!$A$2:$A$46,">="&B3,'Complaint Rate'!$A$2:$A$46,"<="&D3)) -> 40873 | F8: Medical Device Problem | G8: =IF($B$2="","-",TEXT($B$2,"mmm-yyyy")&" to "&TEXT($D$2,"mmm-yyyy")) -> Jul-2022 to Jun-2025 | H8: =IF($B$4="","-",TEXT($B$4,"mmm-yyyy")&" to "&TEXT($D$4,"mmm-yyyy")) -> Jul-2022 to Jun-2025
F9: =IF(COUNTA(complaints!$A$2:$A$928)=0,"","No Clinical Signs, Symptoms or Conditions") -> No Clinical Signs, Symptoms or Conditions | G9: {=IF(COUNTA(complaints!$A$2:$A$928)=0,"-",IF($B$8=0,"-",IFERROR(TEXT(SUMPRODUCT((complaints!$F$2:$F$928<>"")*(complaints!$B$2:$B$928>=$B$2)*(complaints!$B$2:$B$928<=$D$2))/$B$8,"0.0000")&" ("&SUMPRODUCT((complaints!$F$2:$F$928<>"")*(complaints!$B$2:$B$928>=$B$2)*(complaints!$B$2:$B$928<=$D$2))&")","-")))} -> 0.0003 (16) | H9: {=IF(COUNTA(complaints!$A$2:$A$928)=0,"-",IF($B$6=0,"-",IFERROR(TEXT(SUMPRODUCT((complaints!$F$2:$F$928<>"")*(complaints!$B$2:$B$928>=$B$4)*(complaints!$B$2:$B$928<=$D$4))/$B$6,"0.0000")&" ("&SUMPRODUCT((complaints!$F$2:$F$928<>"")*(complaints!$B$2:$B$928>=$B$4)*(complaints!$B$2:$B$928<=$D$4))&")","-")))} -> 0.0003 (16) | I9: =IF(COUNTA(complaints!$A$2:$A$928)=0,"",IF(H9="-","-",_xlfn.LET(_xlpm.rate,VALUE(LEFT(H9,FIND(" ",H9)-1)),IF(_xlpm.rate>0.1,"O5",IF(_xlpm.rate>0.01,"O4",IF(_xlpm.rate>0.001,"O3",IF(_xlpm.rate>0.0001,"O2","O1"))))))) -> O2 | J9: =IF(COUNTA(complaints!$A$2:$A$928)=0,"",IF(H9="-","-",_xlfn.LET(_xlpm.rate,VALUE(LEFT(H9,FIND(" ",H9)-1)),IF(_xlpm.rate>0.1,1,IF(_xlpm.rate>0.01,0.1,IF(_xlpm.rate>0.001,0.01,IF(_xlpm.rate>0.0001,0.001,0.0001))))))) -> 0.001
F10: {=IF(COUNTA(complaints!$A$2:$A$928)=0,"",IFERROR(" "&INDEX(_xlfn._xlws.SORT(_xlfn.UNIQUE(_xlfn._xlws.FILTER(complaints!$E$2:$E$928,complaints!$E$2:$E$928<>""))),1),""))} -> Break | G10: {=IF(F10="","",IF($B$8=0,"-",IFERROR(TEXT(SUMPRODUCT((complaints!$E$2:$E$928=TRIM(F10))*(complaints!$F$2:$F$928<>"")*(complaints!$B$2:$B$928>=$B$2)*(complaints!$B$2:$B$928<=$D$2))/$B$8,"0.0000")&" ("&SUMPRODUCT((complaints!$E$2:$E$928=TRIM(F10))*(complaints!$F$2:$F$928<>"")*(complaints!$B$2:$B$928>=$B$2)*(complaints!$B$2:$B$928<=$D$2))&")","-")))} -> 0.0000 (2) | H10: {=IF(F10="","",IF($B$6=0,"-",IFERROR(TEXT(SUMPRODUCT((complaints!$E$2:$E$928=TRIM(F10))*(complaints!$F$2:$F$928<>"")*(complaints!$B$2:$B$928>=$B$4)*(complaints!$B$2:$B$928<=$D$4))/$B$6,"0.0000")&" ("&SUMPRODUCT((complaints!$E$2:$E$928=TRIM(F10))*(complaints!$F$2:$F$928<>"")*(complaints!$B$2:$B$928>=$B$4)*(complaints!$B$2:$B$928<=$D$4))&")","-")))} -> 0.0000 (2) | I10: =IF(F10="","",IF(H10="-","-",_xlfn.LET(_xlpm.rate,VALUE(LEFT(H10,FIND(" ",H10)-1)),IF(_xlpm.rate>0.1,"O5",IF(_xlpm.rate>0.01,"O4",IF(_xlpm.rate>0.001,"O3",IF(_xlpm.rate>0.0001,"O2","O1"))))))) -> O1 | J10: =IF(F10="","",IF(H10="-","-",_xlfn.LET(_xlpm.rate,VALUE(LEFT(H10,FIND(" ",H10)-1)),IF(_xlpm.rate>0.1,1,IF(_xlpm.rate>0.01,0.1,IF(_xlpm.rate>0.001,0.01,IF(_xlpm.rate>0.0001,0.001,0.0001))))))) -> 0.0001
F11: {=IF(COUNTA(complaints!$A$2:$A$928)=0,"",IFERROR(" "&INDEX(_xlfn._xlws.SORT(_xlfn.UNIQUE(_xlfn._xlws.FILTER(complaints!$E$2:$E$928,complaints!$E$2:$E$928<>""))),2),""))} -> Contamination | G11: {=IF(F11="","",IF($B$8=0,"-",IFERROR(TEXT(SUMPRODUCT((complaints!$E$2:$E$928=TRIM(F11))*(complaints!$F$2:$F$928<>"")*(complaints!$B$2:$B$928>=$B$2)*(complaints!$B$2:$B$928<=$D$2))/$B$8,"0.0000")&" ("&SUMPRODUCT((complaints!$E$2:$E$928=TRIM(F11))*(complaints!$F$2:$F$928<>"")*(complaints!$B$2:$B$928>=$B$2)*(complaints!$B$2:$B$928<=$D$2))&")","-")))} -> 0.0000 (1) | H11: {=IF(F11="","",IF($B$6=0,"-",IFERROR(TEXT(SUMPRODUCT((complaints!$E$2:$E$928=TRIM(F11))*(complaints!$F$2:$F$928<>"")*(complaints!$B$2:$B$928>=$B$4)*(complaints!$B$2:$B$928<=$D$4))/$B$6,"0.0000")&" ("&SUMPRODUCT((complaints!$E$2:$E$928=TRIM(F11))*(complaints!$F$2:$F$928<>"")*(complaints!$B$2:$B$928>=$B$4)*(complaints!$B$2:$B$928<=$D$4))&")","-")))} -> 0.0000 (1) | I11: =IF(F11="","",IF(H11="-","-",_xlfn.LET(_xlpm.rate,VALUE(LEFT(H11,FIND(" ",H11)-1)),IF(_xlpm.rate>0.1,"O5",IF(_xlpm.rate>0.01,"O4",IF(_xlpm.rate>0.001,"O3",IF(_xlpm.rate>0.0001,"O2","O1"))))))) -> O1 | J11: =IF(F11="","",IF(H11="-","-",_xlfn.LET(_xlpm.rate,VALUE(LEFT(H11,FIND(" ",H11)-1)),IF(_xlpm.rate>0.1,1,IF(_xlpm.rate>0.01,0.1,IF(_xlpm.rate>0.001,0.01,IF(_xlpm.rate>0.0001,0.001,0.0001))))))) -> 0.0001
F12: {=IF(COUNTA(complaints!$A$2:$A$928)=0,"",IFERROR(" "&INDEX(_xlfn._xlws.SORT(_xlfn.UNIQUE(_xlfn._xlws.FILTER(complaints!$E$2:$E$928,complaints!$E$2:$E$928<>""))),3),""))} -> Defective Device | G12: {=IF(F12="","",IF($B$8=0,"-",IFERROR(TEXT(SUMPRODUCT((complaints!$E$2:$E$928=TRIM(F12))*(complaints!$F$2:$F$928<>"")*(complaints!$B$2:$B$928>=$B$2)*(complaints!$B$2:$B$928<=$D$2))/$B$8,"0.0000")&" ("&SUMPRODUCT((complaints!$E$2:$E$928=TRIM(F12))*(complaints!$F$2:$F$928<>"")*(complaints!$B$2:$B$928>=$B$2)*(complaints!$B$2:$B$928<=$D$2))&")","-")))} -> 0.0000 (2) | H12: {=IF(F12="","",IF($B$6=0,"-",IFERROR(TEXT(SUMPRODUCT((complaints!$E$2:$E$928=TRIM(F12))*(complaints!$F$2:$F$928<>"")*(complaints!$B$2:$B$928>=$B$4)*(complaints!$B$2:$B$928<=$D$4))/$B$6,"0.0000")&" ("&SUMPRODUCT((complaints!$E$2:$E$928=TRIM(F12))*(complaints!$F$2:$F$928<>"")*(complaints!$B$2:$B$928>=$B$4)*(complaints!$B$2:$B$928<=$D$4))&")","-")))} -> 0.0000 (2) | I12: =IF(F12="","",IF(H12="-","-",_xlfn.LET(_xlpm.rate,VALUE(LEFT(H12,FIND(" ",H12)-1)),IF(_xlpm.rate>0.1,"O5",IF(_xlpm.rate>0.01,"O4",IF(_xlpm.rate>0.001,"O3",IF(_xlpm.rate>0.0001,"O2","O1"))))))) -> O1 | J12: =IF(F12="","",IF(H12="-","-",_xlfn.LET(_xlpm.rate,VALUE(LEFT(H12,FIND(" ",H12)-1)),IF(_xlpm.rate>0.1,1,IF(_xlpm.rate>0.01,0.1,IF(_xlpm.rate>0.001,0.01,IF(_xlpm.rate>0.0001,0.001,0.0001))))))) -> 0.0001
F13: {=IF(COUNTA(complaints!$A$2:$A$928)=0,"",IFERROR(" "&INDEX(_xlfn._xlws.SORT(_xlfn.UNIQUE(_xlfn._xlws.FILTER(complaints!$E$2:$E$928,complaints!$E$2:$E$928<>""))),4),""))} -> UNKNOWN - arrivedwarm | G13: {=IF(F13="","",IF($B$8=0,"-",IFERROR(TEXT(SUMPRODUCT((complaints!$E$2:$E$928=TRIM(F13))*(complaints!$F$2:$F$928<>"")*(complaints!$B$2:$B$928>=$B$2)*(complaints!$B$2:$B$928<=$D$2))/$B$8,"0.0000")&" ("&SUMPRODUCT((complaints!$E$2:$E$928=TRIM(F13))*(complaints!$F$2:$F$928<>"")*(complaints!$B$2:$B$928>=$B$2)*(complaints!$B$2:$B$928<=$D$2))&")","-")))} -> 0.0000 (0) | H13: {=IF(F13="","",IF($B$6=0,"-",IFERROR(TEXT(SUMPRODUCT((complaints!$E$2:$E$928=TRIM(F13))*(complaints!$F$2:$F$928<>"")*(complaints!$B$2:$B$928>=$B$4)*(complaints!$B$2:$B$928<=$D$4))/$B$6,"0.0000")&" ("&SUMPRODUCT((complaints!$E$2:$E$928=TRIM(F13))*(complaints!$F$2:$F$928<>"")*(complaints!$B$2:$B$928>=$B$4)*(complaints!$B$2:$B$928<=$D$4))&")","-")))} -> 0.0000 (0) | I13: =IF(F13="","",IF(H13="-","-",_xlfn.LET(_xlpm.rate,VALUE(LEFT(H13,FIND(" ",H13)-1)),IF(_xlpm.rate>0.1,"O5",IF(_xlpm.rate>0.01,"O4",IF(_xlpm.rate>0.001,"O3",IF(_xlpm.rate>0.0001,"O2","O1"))))))) -> O1 | J13: =IF(F13="","",IF(H13="-","-",_xlfn.LET(_xlpm.rate,VALUE(LEFT(H13,FIND(" ",H13)-1)),IF(_xlpm.rate>0.1,1,IF(_xlpm.rate>0.01,0.1,IF(_xlpm.rate>0.001,0.01,IF(_xlpm.rate>0.0001,0.001,0.0001))))))) -> 0.0001
F14: {=IF(COUNTA(complaints!$A$2:$A$928)=0,"",IFERROR(" "&INDEX(_xlfn._xlws.SORT(_xlfn.UNIQUE(_xlfn._xlws.FILTER(complaints!$E$2:$E$928,complaints!$E$2:$E$928<>""))),5),""))} -> UNKNOWN - bottleslids | G14: {=IF(F14="","",IF($B$8=0,"-",IFERROR(TEXT(SUMPRODUCT((complaints!$E$2:$E$928=TRIM(F14))*(complaints!$F$2:$F$928<>"")*(complaints!$B$2:$B$928>=$B$2)*(complaints!$B$2:$B$928<=$D$2))/$B$8,"0.0000")&" ("&SUMPRODUCT((complaints!$E$2:$E$928=TRIM(F14))*(complaints!$F$2:$F$928<>"")*(complaints!$B$2:$B$928>=$B$2)*(complaints!$B$2:$B$928<=$D$2))&")","-")))} -> 0.0000 (1) | H14: {=IF(F14="","",IF($B$6=0,"-",IFERROR(TEXT(SUMPRODUCT((complaints!$E$2:$E$928=TRIM(F14))*(complaints!$F$2:$F$928<>"")*(complaints!$B$2:$B$928>=$B$4)*(complaints!$B$2:$B$928<=$D$4))/$B$6,"0.0000")&" ("&SUMPRODUCT((complaints!$E$2:$E$928=TRIM(F14))*(complaints!$F$2:$F$928<>"")*(complaints!$B$2:$B$928>=$B$4)*(complaints!$B$2:$B$928<=$D$4))&")","-")))} -> 0.0000 (1) | I14: =IF(F14="","",IF(H14="-","-",_xlfn.LET(_xlpm.rate,VALUE(LEFT(H14,FIND(" ",H14)-1)),IF(_xlpm.rate>0.1,"O5",IF(_xlpm.rate>0.01,"O4",IF(_xlpm.rate>0.001,"O3",IF(_xlpm.rate>0.0001,"O2","O1"))))))) -> O1 | J14: =IF(F14="","",IF(H14="-","-",_xlfn.LET(_xlpm.rate,VALUE(LEFT(H14,FIND(" ",H14)-1)),IF(_xlpm.rate>0.1,1,IF(_xlpm.rate>0.01,0.1,IF(_xlpm.rate>0.001,0.01,IF(_xlpm.rate>0.0001,0.001,0.0001))))))) -> 0.0001
F15: {=IF(COUNTA(complaints!$A$2:$A$928)=0,"",IFERROR(" "&INDEX(_xlfn._xlws.SORT(_xlfn.UNIQUE(_xlfn._xlws.FILTER(complaints!$E$2:$E$928,complaints!$E$2:$E$928<>""))),6),""))} -> UNKNOWN - colorph | G15: {=IF(F15="","",IF($B$8=0,"-",IFERROR(TEXT(SUMPRODUCT((complaints!$E$2:$E$928=TRIM(F15))*(complaints!$F$2:$F$928<>"")*(complaints!$B$2:$B$928>=$B$2)*(complaints!$B$2:$B$928<=$D$2))/$B$8,"0.0000")&" ("&SUMPRODUCT((complaints!$E$2:$E$928=TRIM(F15))*(complaints!$F$2:$F$928<>"")*(complaints!$B$2:$B$928>=$B$2)*(complaints!$B$2:$B$928<=$D$2))&")","-")))} -> 0.0001 (9) | H15: {=IF(F15="","",IF($B$6=0,"-",IFERROR(TEXT(SUMPRODUCT((complaints!$E$2:$E$928=TRIM(F15))*(complaints!$F$2:$F$928<>"")*(complaints!$B$2:$B$928>=$B$4)*(complaints!$B$2:$B$928<=$D$4))/$B$6,"0.0000")&" ("&SUMPRODUCT((complaints!$E$2:$E$928=TRIM(F15))*(complaints!$F$2:$F$928<>"")*(complaints!$B$2:$B$928>=$B$4)*(complaints!$B$2:$B$928<=$D$4))&")","-")))} -> 0.0001 (9) | I15: =IF(F15="","",IF(H15="-","-",_xlfn.LET(_xlpm.rate,VALUE(LEFT(H15,FIND(" ",H15)-1)),IF(_xlpm.rate>0.1,"O5",IF(_xlpm.rate>0.01,"O4",IF(_xlpm.rate>0.001,"O3",IF(_xlpm.rate>0.0001,"O2","O1"))))))) -> O1 | J15: =IF(F15="","",IF(H15="-","-",_xlfn.LET(_xlpm.rate,VALUE(LEFT(H15,FIND(" ",H15)-1)),IF(_xlpm.rate>0.1,1,IF(_xlpm.rate>0.01,0.1,IF(_xlpm.rate>0.001,0.01,IF(_xlpm.rate>0.0001,0.001,0.0001))))))) -> 0.0001
F16: {=IF(COUNTA(complaints!$A$2:$A$928)=0,"",IFERROR(" "&INDEX(_xlfn._xlws.SORT(_xlfn.UNIQUE(_xlfn._xlws.FILTER(complaints!$E$2:$E$928,complaints!$E$2:$E$928<>""))),7),""))} -> UNKNOWN - particles | G16: {=IF(F16="","",IF($B$8=0,"-",IFERROR(TEXT(SUMPRODUCT((complaints!$E$2:$E$928=TRIM(F16))*(complaints!$F$2:$F$928<>"")*(complaints!$B$2:$B$928>=$B$2)*(complaints!$B$2:$B$928<=$D$2))/$B$8,"0.0000")&" ("&SUMPRODUCT((complaints!$E$2:$E$928=TRIM(F16))*(complaints!$F$2:$F$928<>"")*(complaints!$B$2:$B$928>=$B$2)*(complaints!$B$2:$B$928<=$D$2))&")","-")))} -> 0.0000 (1) | H16: {=IF(F16="","",IF($B$6=0,"-",IFERROR(TEXT(SUMPRODUCT((complaints!$E$2:$E$928=TRIM(F16))*(complaints!$F$2:$F$928<>"")*(complaints!$B$2:$B$928>=$B$4)*(complaints!$B$2:$B$928<=$D$4))/$B$6,"0.0000")&" ("&SUMPRODUCT((complaints!$E$2:$E$928=TRIM(F16))*(complaints!$F$2:$F$928<>"")*(complaints!$B$2:$B$928>=$B$4)*(complaints!$B$2:$B$928<=$D$4))&")","-")))} -> 0.0000 (1) | I16: =IF(F16="","",IF(H16="-","-",_xlfn.LET(_xlpm.rate,VALUE(LEFT(H16,FIND(" ",H16)-1)),IF(_xlpm.rate>0.1,"O5",IF(_xlpm.rate>0.01,"O4",IF(_xlpm.rate>0.001,"O3",IF(_xlpm.rate>0.0001,"O2","O1"))))))) -> O1 | J16: =IF(F16="","",IF(H16="-","-",_xlfn.LET(_xlpm.rate,VALUE(LEFT(H16,FIND(" ",H16)-1)),IF(_xlpm.rate>0.1,1,IF(_xlpm.rate>0.01,0.1,IF(_xlpm.rate>0.001,0.01,IF(_xlpm.rate>0.0001,0.001,0.0001))))))) -> 0.0001
F17: {=IF(COUNTA(complaints!$A$2:$A$928)=0,"",IFERROR(" "&INDEX(_xlfn._xlws.SORT(_xlfn.UNIQUE(_xlfn._xlws.FILTER(complaints!$E$2:$E$928,complaints!$E$2:$E$928<>""))),8),""))} | G17: {=IF(F17="","",IF($B$8=0,"-",IFERROR(TEXT(SUMPRODUCT((complaints!$E$2:$E$928=TRIM(F17))*(complaints!$F$2:$F$928<>"")*(complaints!$B$2:$B$928>=$B$2)*(complaints!$B$2:$B$928<=$D$2))/$B$8,"0.0000")&" ("&SUMPRODUCT((complaints!$E$2:$E$928=TRIM(F17))*(complaints!$F$2:$F$928<>"")*(complaints!$B$2:$B$928>=$B$2)*(complaints!$B$2:$B$928<=$D$2))&")","-")))} | H17: {=IF(F17="","",IF($B$6=0,"-",IFERROR(TEXT(SUMPRODUCT((complaints!$E$2:$E$928=TRIM(F17))*(complaints!$F$2:$F$928<>"")*(complaints!$B$2:$B$928>=$B$4)*(complaints!$B$2:$B$928<=$D$4))/$B$6,"0.0000")&" ("&SUMPRODUCT((complaints!$E$2:$E$928=TRIM(F17))*(complaints!$F$2:$F$928<>"")*(complaints!$B$2:$B$928>=$B$4)*(complaints!$B$2:$B$928<=$D$4))&")","-")))} | I17: =IF(F17="","",IF(H17="-","-",_xlfn.LET(_xlpm.rate,VALUE(LEFT(H17,FIND(" ",H17)-1)),IF(_xlpm.rate>0.1,"O5",IF(_xlpm.rate>0.01,"O4",IF(_xlpm.rate>0.001,"O3",IF(_xlpm.rate>0.0001,"O2","O1"))))))) | J17: =IF(F17="","",IF(H17="-","-",_xlfn.LET(_xlpm.rate,VALUE(LEFT(H17,FIND(" ",H17)-1)),IF(_xlpm.rate>0.1,1,IF(_xlpm.rate>0.01,0.1,IF(_xlpm.rate>0.001,0.01,IF(_xlpm.rate>0.0001,0.001,0.0001)))))))
F18: {=IF(COUNTA(complaints!$A$2:$A$928)=0,"",IFERROR(" "&INDEX(_xlfn._xlws.SORT(_xlfn.UNIQUE(_xlfn._xlws.FILTER(complaints!$E$2:$E$928,complaints!$E$2:$E$928<>""))),9),""))} | G18: {=IF(F18="","",IF($B$8=0,"-",IFERROR(TEXT(SUMPRODUCT((complaints!$E$2:$E$928=TRIM(F18))*(complaints!$F$2:$F$928<>"")*(complaints!$B$2:$B$928>=$B$2)*(complaints!$B$2:$B$928<=$D$2))/$B$8,"0.0000")&" ("&SUMPRODUCT((complaints!$E$2:$E$928=TRIM(F18))*(complaints!$F$2:$F$928<>"")*(complaints!$B$2:$B$928>=$B$2)*(complaints!$B$2:$B$928<=$D$2))&")","-")))} | H18: {=IF(F18="","",IF($B$6=0,"-",IFERROR(TEXT(SUMPRODUCT((complaints!$E$2:$E$928=TRIM(F18))*(complaints!$F$2:$F$928<>"")*(complaints!$B$2:$B$928>=$B$4)*(complaints!$B$2:$B$928<=$D$4))/$B$6,"0.0000")&" ("&SUMPRODUCT((complaints!$E$2:$E$928=TRIM(F18))*(complaints!$F$2:$F$928<>"")*(complaints!$B$2:$B$928>=$B$4)*(complaints!$B$2:$B$928<=$D$4))&")","-")))} | I18: =IF(F18="","",IF(H18="-","-",_xlfn.LET(_xlpm.rate,VALUE(LEFT(H18,FIND(" ",H18)-1)),IF(_xlpm.rate>0.1,"O5",IF(_xlpm.rate>0.01,"O4",IF(_xlpm.rate>0.001,"O3",IF(_xlpm.rate>0.0001,"O2","O1"))))))) | J18: =IF(F18="","",IF(H18="-","-",_xlfn.LET(_xlpm.rate,VALUE(LEFT(H18,FIND(" ",H18)-1)),IF(_xlpm.rate>0.1,1,IF(_xlpm.rate>0.01,0.1,IF(_xlpm.rate>0.001,0.01,IF(_xlpm.rate>0.0001,0.001,0.0001)))))))
F19: {=IF(COUNTA(complaints!$A$2:$A$928)=0,"",IFERROR(" "&INDEX(_xlfn._xlws.SORT(_xlfn.UNIQUE(_xlfn._xlws.FILTER(complaints!$E$2:$E$928,complaints!$E$2:$E$928<>""))),10),""))} | G19: {=IF(F19="","",IF($B$8=0,"-",IFERROR(TEXT(SUMPRODUCT((complaints!$E$2:$E$928=TRIM(F19))*(complaints!$F$2:$F$928<>"")*(complaints!$B$2:$B$928>=$B$2)*(complaints!$B$2:$B$928<=$D$2))/$B$8,"0.0000")&" ("&SUMPRODUCT((complaints!$E$2:$E$928=TRIM(F19))*(complaints!$F$2:$F$928<>"")*(complaints!$B$2:$B$928>=$B$2)*(complaints!$B$2:$B$928<=$D$2))&")","-")))} | H19: {=IF(F19="","",IF($B$6=0,"-",IFERROR(TEXT(SUMPRODUCT((complaints!$E$2:$E$928=TRIM(F19))*(complaints!$F$2:$F$928<>"")*(complaints!$B$2:$B$928>=$B$4)*(complaints!$B$2:$B$928<=$D$4))/$B$6,"0.0000")&" ("&SUMPRODUCT((complaints!$E$2:$E$928=TRIM(F19))*(complaints!$F$2:$F$928<>"")*(complaints!$B$2:$B$928>=$B$4)*(complaints!$B$2:$B$928<=$D$4))&")","-")))} | I19: =IF(F19="","",IF(H19="-","-",_xlfn.LET(_xlpm.rate,VALUE(LEFT(H19,FIND(" ",H19)-1)),IF(_xlpm.rate>0.1,"O5",IF(_xlpm.rate>0.01,"O4",IF(_xlpm.rate>0.001,"O3",IF(_xlpm.rate>0.0001,"O2","O1"))))))) | J19: =IF(F19="","",IF(H19="-","-",_xlfn.LET(_xlpm.rate,VALUE(LEFT(H19,FIND(" ",H19)-1)),IF(_xlpm.rate>0.1,1,IF(_xlpm.rate>0.01,0.1,IF(_xlpm.rate>0.001,0.01,IF(_xlpm.rate>0.0001,0.001,0.0001)))))))
F20: {=IF(COUNTA(complaints!$A$2:$A$928)=0,"",IFERROR(" "&INDEX(_xlfn._xlws.SORT(_xlfn.UNIQUE(_xlfn._xlws.FILTER(complaints!$E$2:$E$928,complaints!$E$2:$E$928<>""))),11),""))} | G20: {=IF(F20="","",IF($B$8=0,"-",IFERROR(TEXT(SUMPRODUCT((complaints!$E$2:$E$928=TRIM(F20))*(complaints!$F$2:$F$928<>"")*(complaints!$B$2:$B$928>=$B$2)*(complaints!$B$2:$B$928<=$D$2))/$B$8,"0.0000")&" ("&SUMPRODUCT((complaints!$E$2:$E$928=TRIM(F20))*(complaints!$F$2:$F$928<>"")*(complaints!$B$2:$B$928>=$B$2)*(complaints!$B$2:$B$928<=$D$2))&")","-")))} | H20: {=IF(F20="","",IF($B$6=0,"-",IFERROR(TEXT(SUMPRODUCT((complaints!$E$2:$E$928=TRIM(F20))*(complaints!$F$2:$F$928<>"")*(complaints!$B$2:$B$928>=$B$4)*(complaints!$B$2:$B$928<=$D$4))/$B$6,"0.0000")&" ("&SUMPRODUCT((complaints!$E$2:$E$928=TRIM(F20))*(complaints!$F$2:$F$928<>"")*(complaints!$B$2:$B$928>=$B$4)*(complaints!$B$2:$B$928<=$D$4))&")","-")))} | I20: =IF(F20="","",IF(H20="-","-",_xlfn.LET(_xlpm.rate,VALUE(LEFT(H20,FIND(" ",H20)-1)),IF(_xlpm.rate>0.1,"O5",IF(_xlpm.rate>0.01,"O4",IF(_xlpm.rate>0.001,"O3",IF(_xlpm.rate>0.0001,"O2","O1"))))))) | J20: =IF(F20="","",IF(H20="-","-",_xlfn.LET(_xlpm.rate,VALUE(LEFT(H20,FIND(" ",H20)-1)),IF(_xlpm.rate>0.1,1,IF(_xlpm.rate>0.01,0.1,IF(_xlpm.rate>0.001,0.01,IF(_xlpm.rate>0.0001,0.001,0.0001)))))))
F21: {=IF(COUNTA(complaints!$A$2:$A$928)=0,"",IFERROR(" "&INDEX(_xlfn._xlws.SORT(_xlfn.UNIQUE(_xlfn._xlws.FILTER(complaints!$E$2:$E$928,complaints!$E$2:$E$928<>""))),12),""))} | G21: {=IF(F21="","",IF($B$8=0,"-",IFERROR(TEXT(SUMPRODUCT((complaints!$E$2:$E$928=TRIM(F21))*(complaints!$F$2:$F$928<>"")*(complaints!$B$2:$B$928>=$B$2)*(complaints!$B$2:$B$928<=$D$2))/$B$8,"0.0000")&" ("&SUMPRODUCT((complaints!$E$2:$E$928=TRIM(F21))*(complaints!$F$2:$F$928<>"")*(complaints!$B$2:$B$928>=$B$2)*(complaints!$B$2:$B$928<=$D$2))&")","-")))} | H21: {=IF(F21="","",IF($B$6=0,"-",IFERROR(TEXT(SUMPRODUCT((complaints!$E$2:$E$928=TRIM(F21))*(complaints!$F$2:$F$928<>"")*(complaints!$B$2:$B$928>=$B$4)*(complaints!$B$2:$B$928<=$D$4))/$B$6,"0.0000")&" ("&SUMPRODUCT((complaints!$E$2:$E$928=TRIM(F21))*(complaints!$F$2:$F$928<>"")*(complaints!$B$2:$B$928>=$B$4)*(complaints!$B$2:$B$928<=$D$4))&")","-")))} | I21: =IF(F21="","",IF(H21="-","-",_xlfn.LET(_xlpm.rate,VALUE(LEFT(H21,FIND(" ",H21)-1)),IF(_xlpm.rate>0.1,"O5",IF(_xlpm.rate>0.01,"O4",IF(_xlpm.rate>0.001,"O3",IF(_xlpm.rate>0.0001,"O2","O1"))))))) | J21: =IF(F21="","",IF(H21="-","-",_xlfn.LET(_xlpm.rate,VALUE(LEFT(H21,FIND(" ",H21)-1)),IF(_xlpm.rate>0.1,1,IF(_xlpm.rate>0.01,0.1,IF(_xlpm.rate>0.001,0.01,IF(_xlpm.rate>0.0001,0.001,0.0001)))))))
F27: Table 7 Complaint Rate (and Complaint Count) by Harm and Medical Device Problem [Use this table if the PSUR update frequency is 'every two years'.]
F28: Harm | G28: Current 24‑Month | H28: Cumulative Surveillance | I28: Max Expected Rate of Occurrence | J28: Max Expected Rate (Numeric)
F29: Medical Device Problem | G29: Data Collection Period | H29: Period
G30: =IF($B$3="","-",TEXT($B$3,"mmm-yyyy")&" to "&TEXT($D$3,"mmm-yyyy")) -> Jul-2023 to Jun-2025 | H30: =IF($B$4="","-",TEXT($B$4,"mmm-yyyy")&" to "&TEXT($D$5,"mmm-yyyy")) -> Jul-2022 to Jun-2025
F31: =IF(COUNTA(complaints!$A$2:$A$928)=0,"","No Clinical Signs, Symptoms or Conditions") -> No Clinical Signs, Symptoms or Conditions | G31: {=IF(COUNTA(complaints!$A$2:$A$928)=0,"-",IF($D$8=0,"-",IFERROR(TEXT(SUMPRODUCT((complaints!$F$2:$F$928<>"")*(complaints!$B$2:$B$928>=$B$3)*(complaints!$B$2:$B$928<=$D$3))/$D$8,"0.0000")&" ("&SUMPRODUCT((complaints!$F$2:$F$928<>"")*(complaints!$B$2:$B$928>=$B$3)*(complaints!$B$2:$B$928<=$D$3))&")","-")))} -> 0.0001 (5) | H31: {=IF(COUNTA(complaints!$A$2:$A$928)=0,"-",IF($D$6=0,"-",IFERROR(TEXT(SUMPRODUCT((complaints!$F$2:$F$928<>"")*(complaints!$B$2:$B$928>=$B$4)*(complaints!$B$2:$B$928<=$D$5))/$D$6,"0.0000")&" ("&SUMPRODUCT((complaints!$F$2:$F$928<>"")*(complaints!$B$2:$B$928>=$B$4)*(complaints!$B$2:$B$928<=$D$5))&")","-")))} -> 0.0003 (16) | I31: =IF(COUNTA(complaints!$A$2:$A$928)=0,"",IF(H31="-","-",_xlfn.LET(_xlpm.rate,VALUE(LEFT(H31,FIND(" ",H31)-1)),IF(_xlpm.rate>0.1,"O5",IF(_xlpm.rate>0.01,"O4",IF(_xlpm.rate>0.001,"O3",IF(_xlpm.rate>0.0001,"O2","O1"))))))) -> O2 | J31: =IF(COUNTA(complaints!$A$2:$A$928)=0,"",IF(H31="-","-",_xlfn.LET(_xlpm.rate,VALUE(LEFT(H31,FIND(" ",H31)-1)),IF(_xlpm.rate>0.1,1,IF(_xlpm.rate>0.01,0.1,IF(_xlpm.rate>0.001,0.01,IF(_xlpm.rate>0.0001,0.001,0.0001))))))) -> 0.001
F32: {=IF(COUNTA(complaints!$A$2:$A$928)=0,"",IFERROR(" "&INDEX(_xlfn._xlws.SORT(_xlfn.UNIQUE(_xlfn._xlws.FILTER(complaints!$E$2:$E$928,complaints!$E$2:$E$928<>""))),1),""))} -> Break | G32: {=IF(F32="","",IF($D$8=0,"-",IFERROR(TEXT(SUMPRODUCT((complaints!$E$2:$E$928=TRIM(F32))*(complaints!$F$2:$F$928<>"")*(complaints!$B$2:$B$928>=$B$3)*(complaints!$B$2:$B$928<=$D$3))/$D$8,"0.0000")&" ("&SUMPRODUCT((complaints!$E$2:$E$928=TRIM(F32))*(complaints!$F$2:$F$928<>"")*(complaints!$B$2:$B$928>=$B$3)*(complaints!$B$2:$B$928<=$D$3))&")","-")))} -> 0.0000 (2) | H32: {=IF(F32="","",IF($D$6=0,"-",IFERROR(TEXT(SUMPRODUCT((complaints!$E$2:$E$928=TRIM(F32))*(complaints!$F$2:$F$928<>"")*(complaints!$B$2:$B$928>=$B$4)*(complaints!$B$2:$B$928<=$D$5))/$D$6,"0.0000")&" ("&SUMPRODUCT((complaints!$E$2:$E$928=TRIM(F32))*(complaints!$F$2:$F$928<>"")*(complaints!$B$2:$B$928>=$B$4)*(complaints!$B$2:$B$928<=$D$5))&")","-")))} -> 0.0000 (2) | I32: =IF(F32="","",IF(H32="-","-",_xlfn.LET(_xlpm.rate,VALUE(LEFT(H32,FIND(" ",H32)-1)),IF(_xlpm.rate>0.1,"O5",IF(_xlpm.rate>0.01,"O4",IF(_xlpm.rate>0.001,"O3",IF(_xlpm.rate>0.0001,"O2","O1"))))))) -> O1 | J32: =IF(F32="","",IF(H32="-","-",_xlfn.LET(_xlpm.rate,VALUE(LEFT(H32,FIND(" ",H32)-1)),IF(_xlpm.rate>0.1,1,IF(_xlpm.rate>0.01,0.1,IF(_xlpm.rate>0.001,0.01,IF(_xlpm.rate>0.0001,0.001,0.0001))))))) -> 0.0001
F33: {=IF(COUNTA(complaints!$A$2:$A$928)=0,"",IFERROR(" "&INDEX(_xlfn._xlws.SORT(_xlfn.UNIQUE(_xlfn._xlws.FILTER(complaints!$E$2:$E$928,complaints!$E$2:$E$928<>""))),2),""))} -> Contamination | G33: {=IF(F33="","",IF($D$8=0,"-",IFERROR(TEXT(SUMPRODUCT((complaints!$E$2:$E$928=TRIM(F33))*(complaints!$F$2:$F$928<>"")*(complaints!$B$2:$B$928>=$B$3)*(complaints!$B$2:$B$928<=$D$3))/$D$8,"0.0000")&" ("&SUMPRODUCT((complaints!$E$2:$E$928=TRIM(F33))*(complaints!$F$2:$F$928<>"")*(complaints!$B$2:$B$928>=$B$3)*(complaints!$B$2:$B$928<=$D$3))&")","-")))} -> 0.0000 (0) | H33: {=IF(F33="","",IF($D$6=0,"-",IFERROR(TEXT(SUMPRODUCT((complaints!$E$2:$E$928=TRIM(F33))*(complaints!$F$2:$F$928<>"")*(complaints!$B$2:$B$928>=$B$4)*(complaints!$B$2:$B$928<=$D$5))/$D$6,"0.0000")&" ("&SUMPRODUCT((complaints!$E$2:$E$928=TRIM(F33))*(complaints!$F$2:$F$928<>"")*(complaints!$B$2:$B$928>=$B$4)*(complaints!$B$2:$B$928<=$D$5))&")","-")))} -> 0.0000 (1) | I33: =IF(F33="","",IF(H33="-","-",_xlfn.LET(_xlpm.rate,VALUE(LEFT(H33,FIND(" ",H33)-1)),IF(_xlpm.rate>0.1,"O5",IF(_xlpm.rate>0.01,"O4",IF(_xlpm.rate>0.001,"O3",IF(_xlpm.rate>0.0001,"O2","O1"))))))) -> O1 | J33: =IF(F33="","",IF(H33="-","-",_xlfn.LET(_xlpm.rate,VALUE(LEFT(H33,FIND(" ",H33)-1)),IF(_xlpm.rate>0.1,1,IF(_xlpm.rate>0.01,0.1,IF(_xlpm.rate>0.001,0.01,IF(_xlpm.rate>0.0001,0.001,0.0001))))))) -> 0.0001
F34: {=IF(COUNTA(complaints!$A$2:$A$928)=0,"",IFERROR(" "&INDEX(_xlfn._xlws.SORT(_xlfn.UNIQUE(_xlfn._xlws.FILTER(complaints!$E$2:$E$928,complaints!$E$2:$E$928<>""))),3),""))} -> Defective Device | G34: {=IF(F34="","",IF($D$8=0,"-",IFERROR(TEXT(SUMPRODUCT((complaints!$E$2:$E$928=TRIM(F34))*(complaints!$F$2:$F$928<>"")*(complaints!$B$2:$B$928>=$B$3)*(complaints!$B$2:$B$928<=$D$3))/$D$8,"0.0000")&" ("&SUMPRODUCT((complaints!$E$2:$E$928=TRIM(F34))*(complaints!$F$2:$F$928<>"")*(complaints!$B$2:$B$928>=$B$3)*(complaints!$B$2:$B$928<=$D$3))&")","-")))} -> 0.0000 (2) | H34: {=IF(F34="","",IF($D$6=0,"-",IFERROR(TEXT(SUMPRODUCT((complaints!$E$2:$E$928=TRIM(F34))*(complaints!$F$2:$F$928<>"")*(complaints!$B$2:$B$928>=$B$4)*(complaints!$B$2:$B$928<=$D$5))/$D$6,"0.0000")&" ("&SUMPRODUCT((complaints!$E$2:$E$928=TRIM(F34))*(complaints!$F$2:$F$928<>"")*(complaints!$B$2:$B$928>=$B$4)*(complaints!$B$2:$B$928<=$D$5))&")","-")))} -> 0.0000 (2) | I34: =IF(F34="","",IF(H34="-","-",_xlfn.LET(_xlpm.rate,VALUE(LEFT(H34,FIND(" ",H34)-1)),IF(_xlpm.rate>0.1,"O5",IF(_xlpm.rate>0.01,"O4",IF(_xlpm.rate>0.001,"O3",IF(_xlpm.rate>0.0001,"O2","O1"))))))) -> O1 | J34: =IF(F34="","",IF(H34="-","-",_xlfn.LET(_xlpm.rate,VALUE(LEFT(H34,FIND(" ",H34)-1)),IF(_xlpm.rate>0.1,1,IF(_xlpm.rate>0.01,0.1,IF(_xlpm.rate>0.001,0.01,IF(_xlpm.rate>0.0001,0.001,0.0001))))))) -> 0.0001
F35: {=IF(COUNTA(complaints!$A$2:$A$928)=0,"",IFERROR(" "&INDEX(_xlfn._xlws.SORT(_xlfn.UNIQUE(_xlfn._xlws.FILTER(complaints!$E$2:$E$928,complaints!$E$2:$E$928<>""))),4),""))} -> UNKNOWN - arrivedwarm | G35: {=IF(F35="","",IF($D$8=0,"-",IFERROR(TEXT(SUMPRODUCT((complaints!$E$2:$E$928=TRIM(F35))*(complaints!$F$2:$F$928<>"")*(complaints!$B$2:$B$928>=$B$3)*(complaints!$B$2:$B$928<=$D$3))/$D$8,"0.0000")&" ("&SUMPRODUCT((complaints!$E$2:$E$928=TRIM(F35))*(complaints!$F$2:$F$928<>"")*(complaints!$B$2:$B$928>=$B$3)*(complaints!$B$2:$B$928<=$D$3))&")","-")))} -> 0.0000 (0) | H35: {=IF(F35="","",IF($D$6=0,"-",IFERROR(TEXT(SUMPRODUCT((complaints!$E$2:$E$928=TRIM(F35))*(complaints!$F$2:$F$928<>"")*(complaints!$B$2:$B$928>=$B$4)*(complaints!$B$2:$B$928<=$D$5))/$D$6,"0.0000")&" ("&SUMPRODUCT((complaints!$E$2:$E$928=TRIM(F35))*(complaints!$F$2:$F$928<>"")*(complaints!$B$2:$B$928>=$B$4)*(complaints!$B$2:$B$928<=$D$5))&")","-")))} -> 0.0000 (0) | I35: =IF(F35="","",IF(H35="-","-",_xlfn.LET(_xlpm.rate,VALUE(LEFT(H35,FIND(" ",H35)-1)),IF(_xlpm.rate>0.1,"O5",IF(_xlpm.rate>0.01,"O4",IF(_xlpm.rate>0.001,"O3",IF(_xlpm.rate>0.0001,"O2","O1"))))))) -> O1 | J35: =IF(F35="","",IF(H35="-","-",_xlfn.LET(_xlpm.rate,VALUE(LEFT(H35,FIND(" ",H35)-1)),IF(_xlpm.rate>0.1,1,IF(_xlpm.rate>0.01,0.1,IF(_xlpm.rate>0.001,0.01,IF(_xlpm.rate>0.0001,0.001,0.0001))))))) -> 0.0001
F36: {=IF(COUNTA(complaints!$A$2:$A$928)=0,"",IFERROR(" "&INDEX(_xlfn._xlws.SORT(_xlfn.UNIQUE(_xlfn._xlws.FILTER(complaints!$E$2:$E$928,complaints!$E$2:$E$928<>""))),5),""))} -> UNKNOWN - bottleslids | G36: {=IF(F36="","",IF($D$8=0,"-",IFERROR(TEXT(SUMPRODUCT((complaints!$E$2:$E$928=TRIM(F36))*(complaints!$F$2:$F$928<>"")*(complaints!$B$2:$B$928>=$B$3)*(complaints!$B$2:$B$928<=$D$3))/$D$8,"0.0000")&" ("&SUMPRODUCT((complaints!$E$2:$E$928=TRIM(F36))*(complaints!$F$2:$F$928<>"")*(complaints!$B$2:$B$928>=$B$3)*(complaints!$B$2:$B$928<=$D$3))&")","-")))} -> 0.0000 (1) | H36: {=IF(F36="","",IF($D$6=0,"-",IFERROR(TEXT(SUMPRODUCT((complaints!$E$2:$E$928=TRIM(F36))*(complaints!$F$2:$F$928<>"")*(complaints!$B$2:$B$928>=$B$4)*(complaints!$B$2:$B$928<=$D$5))/$D$6,"0.0000")&" ("&SUMPRODUCT((complaints!$E$2:$E$928=TRIM(F36))*(complaints!$F$2:$F$928<>"")*(complaints!$B$2:$B$928>=$B$4)*(complaints!$B$2:$B$928<=$D$5))&")","-")))} -> 0.0000 (1) | I36: =IF(F36="","",IF(H36="-","-",_xlfn.LET(_xlpm.rate,VALUE(LEFT(H36,FIND(" ",H36)-1)),IF(_xlpm.rate>0.1,"O5",IF(_xlpm.rate>0.01,"O4",IF(_xlpm.rate>0.001,"O3",IF(_xlpm.rate>0.0001,"O2","O1"))))))) -> O1 | J36: =IF(F36="","",IF(H36="-","-",_xlfn.LET(_xlpm.rate,VALUE(LEFT(H36,FIND(" ",H36)-1)),IF(_xlpm.rate>0.1,1,IF(_xlpm.rate>0.01,0.1,IF(_xlpm.rate>0.001,0.01,IF(_xlpm.rate>0.0001,0.001,0.0001))))))) -> 0.0001
F37: {=IF(COUNTA(complaints!$A$2:$A$928)=0,"",IFERROR(" "&INDEX(_xlfn._xlws.SORT(_xlfn.UNIQUE(_xlfn._xlws.FILTER(complaints!$E$2:$E$928,complaints!$E$2:$E$928<>""))),6),""))} -> UNKNOWN - colorph | G37: {=IF(F37="","",IF($D$8=0,"-",IFERROR(TEXT(SUMPRODUCT((complaints!$E$2:$E$928=TRIM(F37))*(complaints!$F$2:$F$928<>"")*(complaints!$B$2:$B$928>=$B$3)*(complaints!$B$2:$B$928<=$D$3))/$D$8,"0.0000")&" ("&SUMPRODUCT((complaints!$E$2:$E$928=TRIM(F37))*(complaints!$F$2:$F$928<>"")*(complaints!$B$2:$B$928>=$B$3)*(complaints!$B$2:$B$928<=$D$3))&")","-")))} -> 0.0000 (0) | H37: {=IF(F37="","",IF($D$6=0,"-",IFERROR(TEXT(SUMPRODUCT((complaints!$E$2:$E$928=TRIM(F37))*(complaints!$F$2:$F$928<>"")*(complaints!$B$2:$B$928>=$B$4)*(complaints!$B$2:$B$928<=$D$5))/$D$6,"0.0000")&" ("&SUMPRODUCT((complaints!$E$2:$E$928=TRIM(F37))*(complaints!$F$2:$F$928<>"")*(complaints!$B$2:$B$928>=$B$4)*(complaints!$B$2:$B$928<=$D$5))&")","-")))} -> 0.0001 (9) | I37: =IF(F37="","",IF(H37="-","-",_xlfn.LET(_xlpm.rate,VALUE(LEFT(H37,FIND(" ",H37)-1)),IF(_xlpm.rate>0.1,"O5",IF(_xlpm.rate>0.01,"O4",IF(_xlpm.rate>0.001,"O3",IF(_xlpm.rate>0.0001,"O2","O1"))))))) -> O1 | J37: =IF(F37="","",IF(H37="-","-",_xlfn.LET(_xlpm.rate,VALUE(LEFT(H37,FIND(" ",H37)-1)),IF(_xlpm.rate>0.1,1,IF(_xlpm.rate>0.01,0.1,IF(_xlpm.rate>0.001,0.01,IF(_xlpm.rate>0.0001,0.001,0.0001))))))) -> 0.0001
F38: {=IF(COUNTA(complaints!$A$2:$A$928)=0,"",IFERROR(" "&INDEX(_xlfn._xlws.SORT(_xlfn.UNIQUE(_xlfn._xlws.FILTER(complaints!$E$2:$E$928,complaints!$E$2:$E$928<>""))),7),""))} -> UNKNOWN - particles | G38: {=IF(F38="","",IF($D$8=0,"-",IFERROR(TEXT(SUMPRODUCT((complaints!$E$2:$E$928=TRIM(F38))*(complaints!$F$2:$F$928<>"")*(complaints!$B$2:$B$928>=$B$3)*(complaints!$B$2:$B$928<=$D$3))/$D$8,"0.0000")&" ("&SUMPRODUCT((complaints!$E$2:$E$928=TRIM(F38))*(complaints!$F$2:$F$928<>"")*(complaints!$B$2:$B$928>=$B$3)*(complaints!$B$2:$B$928<=$D$3))&")","-")))} -> 0.0000 (0) | H38: {=IF(F38="","",IF($D$6=0,"-",IFERROR(TEXT(SUMPRODUCT((complaints!$E$2:$E$928=TRIM(F38))*(complaints!$F$2:$F$928<>"")*(complaints!$B$2:$B$928>=$B$4)*(complaints!$B$2:$B$928<=$D$5))/$D$6,"0.0000")&" ("&SUMPRODUCT((complaints!$E$2:$E$928=TRIM(F38))*(complaints!$F$2:$F$928<>"")*(complaints!$B$2:$B$928>=$B$4)*(complaints!$B$2:$B$928<=$D$5))&")","-")))} -> 0.0000 (1) | I38: =IF(F38="","",IF(H38="-","-",_xlfn.LET(_xlpm.rate,VALUE(LEFT(H38,FIND(" ",H38)-1)),IF(_xlpm.rate>0.1,"O5",IF(_xlpm.rate>0.01,"O4",IF(_xlpm.rate>0.001,"O3",IF(_xlpm.rate>0.0001,"O2","O1"))))))) -> O1 | J38: =IF(F38="","",IF(H38="-","-",_xlfn.LET(_xlpm.rate,VALUE(LEFT(H38,FIND(" ",H38)-1)),IF(_xlpm.rate>0.1,1,IF(_xlpm.rate>0.01,0.1,IF(_xlpm.rate>0.001,0.01,IF(_xlpm.rate>0.0001,0.001,0.0001))))))) -> 0.0001
F39: {=IF(COUNTA(complaints!$A$2:$A$928)=0,"",IFERROR(" "&INDEX(_xlfn._xlws.SORT(_xlfn.UNIQUE(_xlfn._xlws.FILTER(complaints!$E$2:$E$928,complaints!$E$2:$E$928<>""))),8),""))} | G39: {=IF(F39="","",IF($D$8=0,"-",IFERROR(TEXT(SUMPRODUCT((complaints!$E$2:$E$928=TRIM(F39))*(complaints!$F$2:$F$928<>"")*(complaints!$B$2:$B$928>=$B$3)*(complaints!$B$2:$B$928<=$D$3))/$D$8,"0.0000")&" ("&SUMPRODUCT((complaints!$E$2:$E$928=TRIM(F39))*(complaints!$F$2:$F$928<>"")*(complaints!$B$2:$B$928>=$B$3)*(complaints!$B$2:$B$928<=$D$3))&")","-")))} | H39: {=IF(F39="","",IF($D$6=0,"-",IFERROR(TEXT(SUMPRODUCT((complaints!$E$2:$E$928=TRIM(F39))*(complaints!$F$2:$F$928<>"")*(complaints!$B$2:$B$928>=$B$4)*(complaints!$B$2:$B$928<=$D$5))/$D$6,"0.0000")&" ("&SUMPRODUCT((complaints!$E$2:$E$928=TRIM(F39))*(complaints!$F$2:$F$928<>"")*(complaints!$B$2:$B$928>=$B$4)*(complaints!$B$2:$B$928<=$D$5))&")","-")))} | I39: =IF(F39="","",IF(H39="-","-",_xlfn.LET(_xlpm.rate,VALUE(LEFT(H39,FIND(" ",H39)-1)),IF(_xlpm.rate>0.1,"O5",IF(_xlpm.rate>0.01,"O4",IF(_xlpm.rate>0.001,"O3",IF(_xlpm.rate>0.0001,"O2","O1"))))))) | J39: =IF(F39="","",IF(H39="-","-",_xlfn.LET(_xlpm.rate,VALUE(LEFT(H39,FIND(" ",H39)-1)),IF(_xlpm.rate>0.1,1,IF(_xlpm.rate>0.01,0.1,IF(_xlpm.rate>0.001,0.01,IF(_xlpm.rate>0.0001,0.001,0.0001)))))))
F40: {=IF(COUNTA(complaints!$A$2:$A$928)=0,"",IFERROR(" "&INDEX(_xlfn._xlws.SORT(_xlfn.UNIQUE(_xlfn._xlws.FILTER(complaints!$E$2:$E$928,complaints!$E$2:$E$928<>""))),9),""))} | G40: {=IF(F40="","",IF($D$8=0,"-",IFERROR(TEXT(SUMPRODUCT((complaints!$E$2:$E$928=TRIM(F40))*(complaints!$F$2:$F$928<>"")*(complaints!$B$2:$B$928>=$B$3)*(complaints!$B$2:$B$928<=$D$3))/$D$8,"0.0000")&" ("&SUMPRODUCT((complaints!$E$2:$E$928=TRIM(F40))*(complaints!$F$2:$F$928<>"")*(complaints!$B$2:$B$928>=$B$3)*(complaints!$B$2:$B$928<=$D$3))&")","-")))} | H40: {=IF(F40="","",IF($D$6=0,"-",IFERROR(TEXT(SUMPRODUCT((complaints!$E$2:$E$928=TRIM(F40))*(complaints!$F$2:$F$928<>"")*(complaints!$B$2:$B$928>=$B$4)*(complaints!$B$2:$B$928<=$D$5))/$D$6,"0.0000")&" ("&SUMPRODUCT((complaints!$E$2:$E$928=TRIM(F40))*(complaints!$F$2:$F$928<>"")*(complaints!$B$2:$B$928>=$B$4)*(complaints!$B$2:$B$928<=$D$5))&")","-")))} | I40: =IF(F40="","",IF(H40="-","-",_xlfn.LET(_xlpm.rate,VALUE(LEFT(H40,FIND(" ",H40)-1)),IF(_xlpm.rate>0.1,"O5",IF(_xlpm.rate>0.01,"O4",IF(_xlpm.rate>0.001,"O3",IF(_xlpm.rate>0.0001,"O2","O1"))))))) | J40: =IF(F40="","",IF(H40="-","-",_xlfn.LET(_xlpm.rate,VALUE(LEFT(H40,FIND(" ",H40)-1)),IF(_xlpm.rate>0.1,1,IF(_xlpm.rate>0.01,0.1,IF(_xlpm.rate>0.001,0.01,IF(_xlpm.rate>0.0001,0.001,0.0001)))))))
F41: {=IF(COUNTA(complaints!$A$2:$A$928)=0,"",IFERROR(" "&INDEX(_xlfn._xlws.SORT(_xlfn.UNIQUE(_xlfn._xlws.FILTER(complaints!$E$2:$E$928,complaints!$E$2:$E$928<>""))),10),""))} | G41: {=IF(F41="","",IF($D$8=0,"-",IFERROR(TEXT(SUMPRODUCT((complaints!$E$2:$E$928=TRIM(F41))*(complaints!$F$2:$F$928<>"")*(complaints!$B$2:$B$928>=$B$3)*(complaints!$B$2:$B$928<=$D$3))/$D$8,"0.0000")&" ("&SUMPRODUCT((complaints!$E$2:$E$928=TRIM(F41))*(complaints!$F$2:$F$928<>"")*(complaints!$B$2:$B$928>=$B$3)*(complaints!$B$2:$B$928<=$D$3))&")","-")))} | H41: {=IF(F41="","",IF($D$6=0,"-",IFERROR(TEXT(SUMPRODUCT((complaints!$E$2:$E$928=TRIM(F41))*(complaints!$F$2:$F$928<>"")*(complaints!$B$2:$B$928>=$B$4)*(complaints!$B$2:$B$928<=$D$5))/$D$6,"0.0000")&" ("&SUMPRODUCT((complaints!$E$2:$E$928=TRIM(F41))*(complaints!$F$2:$F$928<>"")*(complaints!$B$2:$B$928>=$B$4)*(complaints!$B$2:$B$928<=$D$5))&")","-")))} | I41: =IF(F41="","",IF(H41="-","-",_xlfn.LET(_xlpm.rate,VALUE(LEFT(H41,FIND(" ",H41)-1)),IF(_xlpm.rate>0.1,"O5",IF(_xlpm.rate>0.01,"O4",IF(_xlpm.rate>0.001,"O3",IF(_xlpm.rate>0.0001,"O2","O1"))))))) | J41: =IF(F41="","",IF(H41="-","-",_xlfn.LET(_xlpm.rate,VALUE(LEFT(H41,FIND(" ",H41)-1)),IF(_xlpm.rate>0.1,1,IF(_xlpm.rate>0.01,0.1,IF(_xlpm.rate>0.001,0.01,IF(_xlpm.rate>0.0001,0.001,0.0001)))))))
F42: {=IF(COUNTA(complaints!$A$2:$A$928)=0,"",IFERROR(" "&INDEX(_xlfn._xlws.SORT(_xlfn.UNIQUE(_xlfn._xlws.FILTER(complaints!$E$2:$E$928,complaints!$E$2:$E$928<>""))),11),""))} | G42: {=IF(F42="","",IF($D$8=0,"-",IFERROR(TEXT(SUMPRODUCT((complaints!$E$2:$E$928=TRIM(F42))*(complaints!$F$2:$F$928<>"")*(complaints!$B$2:$B$928>=$B$3)*(complaints!$B$2:$B$928<=$D$3))/$D$8,"0.0000")&" ("&SUMPRODUCT((complaints!$E$2:$E$928=TRIM(F42))*(complaints!$F$2:$F$928<>"")*(complaints!$B$2:$B$928>=$B$3)*(complaints!$B$2:$B$928<=$D$3))&")","-")))} | H42: {=IF(F42="","",IF($D$6=0,"-",IFERROR(TEXT(SUMPRODUCT((complaints!$E$2:$E$928=TRIM(F42))*(complaints!$F$2:$F$928<>"")*(complaints!$B$2:$B$928>=$B$4)*(complaints!$B$2:$B$928<=$D$5))/$D$6,"0.0000")&" ("&SUMPRODUCT((complaints!$E$2:$E$928=TRIM(F42))*(complaints!$F$2:$F$928<>"")*(complaints!$B$2:$B$928>=$B$4)*(complaints!$B$2:$B$928<=$D$5))&")","-")))} | I42: =IF(F42="","",IF(H42="-","-",_xlfn.LET(_xlpm.rate,VALUE(LEFT(H42,FIND(" ",H42)-1)),IF(_xlpm.rate>0.1,"O5",IF(_xlpm.rate>0.01,"O4",IF(_xlpm.rate>0.001,"O3",IF(_xlpm.rate>0.0001,"O2","O1"))))))) | J42: =IF(F42="","",IF(H42="-","-",_xlfn.LET(_xlpm.rate,VALUE(LEFT(H42,FIND(" ",H42)-1)),IF(_xlpm.rate>0.1,1,IF(_xlpm.rate>0.01,0.1,IF(_xlpm.rate>0.001,0.01,IF(_xlpm.rate>0.0001,0.001,0.0001)))))))
F43: {=IF(COUNTA(complaints!$A$2:$A$928)=0,"",IFERROR(" "&INDEX(_xlfn._xlws.SORT(_xlfn.UNIQUE(_xlfn._xlws.FILTER(complaints!$E$2:$E$928,complaints!$E$2:$E$928<>""))),12),""))} | G43: {=IF(F43="","",IF($D$8=0,"-",IFERROR(TEXT(SUMPRODUCT((complaints!$E$2:$E$928=TRIM(F43))*(complaints!$F$2:$F$928<>"")*(complaints!$B$2:$B$928>=$B$3)*(complaints!$B$2:$B$928<=$D$3))/$D$8,"0.0000")&" ("&SUMPRODUCT((complaints!$E$2:$E$928=TRIM(F43))*(complaints!$F$2:$F$928<>"")*(complaints!$B$2:$B$928>=$B$3)*(complaints!$B$2:$B$928<=$D$3))&")","-")))} | H43: {=IF(F43="","",IF($D$6=0,"-",IFERROR(TEXT(SUMPRODUCT((complaints!$E$2:$E$928=TRIM(F43))*(complaints!$F$2:$F$928<>"")*(complaints!$B$2:$B$928>=$B$4)*(complaints!$B$2:$B$928<=$D$5))/$D$6,"0.0000")&" ("&SUMPRODUCT((complaints!$E$2:$E$928=TRIM(F43))*(complaints!$F$2:$F$928<>"")*(complaints!$B$2:$B$928>=$B$4)*(complaints!$B$2:$B$928<=$D$5))&")","-")))} | I43: =IF(F43="","",IF(H43="-","-",_xlfn.LET(_xlpm.rate,VALUE(LEFT(H43,FIND(" ",H43)-1)),IF(_xlpm.rate>0.1,"O5",IF(_xlpm.rate>0.01,"O4",IF(_xlpm.rate>0.001,"O3",IF(_xlpm.rate>0.0001,"O2","O1"))))))) | J43: =IF(F43="","",IF(H43="-","-",_xlfn.LET(_xlpm.rate,VALUE(LEFT(H43,FIND(" ",H43)-1)),IF(_xlpm.rate>0.1,1,IF(_xlpm.rate>0.01,0.1,IF(_xlpm.rate>0.001,0.01,IF(_xlpm.rate>0.0001,0.001,0.0001)))))))
F44: =IF(COUNTA(complaints!$A$2:$A$928)=0,"","Grand Total") -> Grand Total | G44: =G31 -> 0.0001 (5) | H44: =H31 -> 0.0003 (16)
F46: [1] RACT, Risk Assessment & Control Table for ALLY UPS.
F47: [2] RACT, Risk Assessment & Control Table for ALLY UPS.

Sheet Section D - Incidents
A1: Section D: Information on Serious Incidents
A3: Table 2 – Serious Incidents by IMDRF Annex A Medical Device Problem Code
A4: Region | B4: IMDRF Problem Code & Term | C4: N (current period) | D4: Rate (%) | E4: Complaint Number(s)
A5: =IF(COUNTA(complaints!$A$2:$A$928)=0,"","Worldwide") -> Worldwide | B5: {=IF(COUNTA(complaints!$A$2:$A$928)=0,"",IFERROR(_xlfn.LET(_xlpm.mdp,INDEX(_xlfn._xlws.SORT(_xlfn.UNIQUE(_xlfn._xlws.FILTER(complaints!$E$2:$E$928,complaints!$E$2:$E$928<>""))),1),_xlpm.code,IFERROR(VLOOKUP(_xlpm.mdp,Codes!$L$2:$N$409,3,FALSE),"—"),_xlpm.code&" – "&_xlpm.mdp),""))} -> A0401 – Break | C5: =IF(B5="","",COUNTIFS(complaints!$E$2:$E$928,MID(B5,FIND(" – ",B5)+3,999),complaints!$B$2:$B$928,">="&'Harms table'!$B$2,complaints!$B$2:$B$928,"<="&'Harms table'!$D$2)) -> 2 | D5: =IF(C5="","",IF('Harms table'!$B$8=0,"–",TEXT(C5/'Harms table'!$B$8*100,"0.00")&"%")) -> 0.00% | E5: {=IF(B5="","",IFERROR(_xlfn.TEXTJOIN(", ",TRUE,_xlfn._xlws.FILTER(complaints!$A$2:$A$928,(complaints!$E$2:$E$928=MID(B5,FIND(" – ",B5)+3,999))*(complaints!$B$2:$B$928>='Harms table'!$B$2)*(complaints!$B$2:$B$928<='Harms table'!$D$2))),""))} -> 2024-07-0000328, 2024-09-0000519
B6: {=IF(COUNTA(complaints!$A$2:$A$928)=0,"",IFERROR(_xlfn.LET(_xlpm.mdp,INDEX(_xlfn._xlws.SORT(_xlfn.UNIQUE(_xlfn._xlws.FILTER(complaints!$E$2:$E$928,complaints!$E$2:$E$928<>""))),2),_xlpm.code,IFERROR(VLOOKUP(_xlpm.mdp,Codes!$L$2:$N$409,3,FALSE),"—"),_xlpm.code&" – "&_xlpm.mdp),""))} -> A1801 – Contamination | C6: =IF(B6="","",COUNTIFS(complaints!$E$2:$E$928,MID(B6,FIND(" – ",B6)+3,999),complaints!$B$2:$B$928,">="&'Harms table'!$B$2,complaints!$B$2:$B$928,"<="&'Harms table'!$D$2)) -> 1 | D6: =IF(C6="","",IF('Harms table'!$B$8=0,"–",TEXT(C6/'Harms table'!$B$8*100,"0.00")&"%")) -> 0.00% | E6: {=IF(B6="","",IFERROR(_xlfn.TEXTJOIN(", ",TRUE,_xlfn._xlws.FILTER(complaints!$A$2:$A$928,(complaints!$E$2:$E$928=MID(B6,FIND(" – ",B6)+3,999))*(complaints!$B$2:$B$928>='Harms table'!$B$2)*(complaints!$B$2:$B$928<='Harms table'!$D$2))),""))} -> 2023-03-0000416
B7: {=IF(COUNTA(complaints!$A$2:$A$928)=0,"",IFERROR(_xlfn.LET(_xlpm.mdp,INDEX(_xlfn._xlws.SORT(_xlfn.UNIQUE(_xlfn._xlws.FILTER(complaints!$E$2:$E$928,complaints!$E$2:$E$928<>""))),3),_xlpm.code,IFERROR(VLOOKUP(_xlpm.mdp,Codes!$L$2:$N$409,3,FALSE),"—"),_xlpm.code&" – "&_xlpm.mdp),""))} -> A0203 – Defective Device | C7: =IF(B7="","",COUNTIFS(complaints!$E$2:$E$928,MID(B7,FIND(" – ",B7)+3,999),complaints!$B$2:$B$928,">="&'Harms table'!$B$2,complaints!$B$2:$B$928,"<="&'Harms table'!$D$2)) -> 2 | D7: =IF(C7="","",IF('Harms table'!$B$8=0,"–",TEXT(C7/'Harms table'!$B$8*100,"0.00")&"%")) -> 0.00% | E7: {=IF(B7="","",IFERROR(_xlfn.TEXTJOIN(", ",TRUE,_xlfn._xlws.FILTER(complaints!$A$2:$A$928,(complaints!$E$2:$E$928=MID(B7,FIND(" – ",B7)+3,999))*(complaints!$B$2:$B$928>='Harms table'!$B$2)*(complaints!$B$2:$B$928<='Harms table'!$D$2))),""))} -> 2023-12-0000241, 2023-12-0000246
B8: {=IF(COUNTA(complaints!$A$2:$A$928)=0,"",IFERROR(_xlfn.LET(_xlpm.mdp,INDEX(_xlfn._xlws.SORT(_xlfn.UNIQUE(_xlfn._xlws.FILTER(complaints!$E$2:$E$928,complaints!$E$2:$E$928<>""))),4),_xlpm.code,IFERROR(VLOOKUP(_xlpm.mdp,Codes!$L$2:$N$409,3,FALSE),"—"),_xlpm.code&" – "&_xlpm.mdp),""))} -> — – UNKNOWN - arrivedwarm | C8: =IF(B8="","",COUNTIFS(complaints!$E$2:$E$928,MID(B8,FIND(" – ",B8)+3,999),complaints!$B$2:$B$928,">="&'Harms table'!$B$2,complaints!$B$2:$B$928,"<="&'Harms table'!$D$2)) -> 0 | D8: =IF(C8="","",IF('Harms table'!$B$8=0,"–",TEXT(C8/'Harms table'!$B$8*100,"0.00")&"%")) -> 0.00% | E8: {=IF(B8="","",IFERROR(_xlfn.TEXTJOIN(", ",TRUE,_xlfn._xlws.FILTER(complaints!$A$2:$A$928,(complaints!$E$2:$E$928=MID(B8,FIND(" – ",B8)+3,999))*(complaints!$B$2:$B$928>='Harms table'!$B$2)*(complaints!$B$2:$B$928<='Harms table'!$D$2))),""))}
B9: {=IF(COUNTA(complaints!$A$2:$A$928)=0,"",IFERROR(_xlfn.LET(_xlpm.mdp,INDEX(_xlfn._xlws.SORT(_xlfn.UNIQUE(_xlfn._xlws.FILTER(complaints!$E$2:$E$928,complaints!$E$2:$E$928<>""))),5),_xlpm.code,IFERROR(VLOOKUP(_xlpm.mdp,Codes!$L$2:$N$409,3,FALSE),"—"),_xlpm.code&" – "&_xlpm.mdp),""))} -> — – UNKNOWN - bottleslids | C9: =IF(B9="","",COUNTIFS(complaints!$E$2:$E$928,MID(B9,FIND(" – ",B9)+3,999),complaints!$B$2:$B$928,">="&'Harms table'!$B$2,complaints!$B$2:$B$928,"<="&'Harms table'!$D$2)) -> 1 | D9: =IF(C9="","",IF('Harms table'!$B$8=0,"–",TEXT(C9/'Harms table'!$B$8*100,"0.00")&"%")) -> 0.00% | E9: {=IF(B9="","",IFERROR(_xlfn.TEXTJOIN(", ",TRUE,_xlfn._xlws.FILTER(complaints!$A$2:$A$928,(complaints!$E$2:$E$928=MID(B9,FIND(" – ",B9)+3,999))*(complaints!$B$2:$B$928>='Harms table'!$B$2)*(complaints!$B$2:$B$928<='Harms table'!$D$2))),""))} -> 2024-02-0000191
B10: {=IF(COUNTA(complaints!$A$2:$A$928)=0,"",IFERROR(_xlfn.LET(_xlpm.mdp,INDEX(_xlfn._xlws.SORT(_xlfn.UNIQUE(_xlfn._xlws.FILTER(complaints!$E$2:$E$928,complaints!$E$2:$E$928<>""))),6),_xlpm.code,IFERROR(VLOOKUP(_xlpm.mdp,Codes!$L$2:$N$409,3,FALSE),"—"),_xlpm.code&" – "&_xlpm.mdp),""))} -> — – UNKNOWN - colorph | C10: =IF(B10="","",COUNTIFS(complaints!$E$2:$E$928,MID(B10,FIND(" – ",B10)+3,999),complaints!$B$2:$B$928,">="&'Harms table'!$B$2,complaints!$B$2:$B$928,"<="&'Harms table'!$D$2)) -> 9 | D10: =IF(C10="","",IF('Harms table'!$B$8=0,"–",TEXT(C10/'Harms table'!$B$8*100,"0.00")&"%")) -> 0.01% | E10: {=IF(B10="","",IFERROR(_xlfn.TEXTJOIN(", ",TRUE,_xlfn._xlws.FILTER(complaints!$A$2:$A$928,(complaints!$E$2:$E$928=MID(B10,FIND(" – ",B10)+3,999))*(complaints!$B$2:$B$928>='Harms table'!$B$2)*(complaints!$B$2:$B$928<='Harms table'!$D$2))),""))} -> 2023-05-0000145, 2023-05-0000540, 2023-05-0000618, 2023-06-0000030, 2023-06-0000116, 2023-06-0000121, 2023-06-0000281, 2023-06-0000348, 2023-06-0000391
B11: {=IF(COUNTA(complaints!$A$2:$A$928)=0,"",IFERROR(_xlfn.LET(_xlpm.mdp,INDEX(_xlfn._xlws.SORT(_xlfn.UNIQUE(_xlfn._xlws.FILTER(complaints!$E$2:$E$928,complaints!$E$2:$E$928<>""))),7),_xlpm.code,IFERROR(VLOOKUP(_xlpm.mdp,Codes!$L$2:$N$409,3,FALSE),"—"),_xlpm.code&" – "&_xlpm.mdp),""))} -> — – UNKNOWN - particles | C11: =IF(B11="","",COUNTIFS(complaints!$E$2:$E$928,MID(B11,FIND(" – ",B11)+3,999),complaints!$B$2:$B$928,">="&'Harms table'!$B$2,complaints!$B$2:$B$928,"<="&'Harms table'!$D$2)) -> 1 | D11: =IF(C11="","",IF('Harms table'!$B$8=0,"–",TEXT(C11/'Harms table'!$B$8*100,"0.00")&"%")) -> 0.00% | E11: {=IF(B11="","",IFERROR(_xlfn.TEXTJOIN(", ",TRUE,_xlfn._xlws.FILTER(complaints!$A$2:$A$928,(complaints!$E$2:$E$928=MID(B11,FIND(" – ",B11)+3,999))*(complaints!$B$2:$B$928>='Harms table'!$B$2)*(complaints!$B$2:$B$928<='Harms table'!$D$2))),""))} -> 2023-04-0000158
B12: {=IF(COUNTA(complaints!$A$2:$A$928)=0,"",IFERROR(_xlfn.LET(_xlpm.mdp,INDEX(_xlfn._xlws.SORT(_xlfn.UNIQUE(_xlfn._xlws.FILTER(complaints!$E$2:$E$928,complaints!$E$2:$E$928<>""))),8),_xlpm.code,IFERROR(VLOOKUP(_xlpm.mdp,Codes!$L$2:$N$409,3,FALSE),"—"),_xlpm.code&" – "&_xlpm.mdp),""))} | C12: =IF(B12="","",COUNTIFS(complaints!$E$2:$E$928,MID(B12,FIND(" – ",B12)+3,999),complaints!$B$2:$B$928,">="&'Harms table'!$B$2,complaints!$B$2:$B$928,"<="&'Harms table'!$D$2)) | D12: =IF(C12="","",IF('Harms table'!$B$8=0,"–",TEXT(C12/'Harms table'!$B$8*100,"0.00")&"%")) | E12: {=IF(B12="","",IFERROR(_xlfn.TEXTJOIN(", ",TRUE,_xlfn._xlws.FILTER(complaints!$A$2:$A$928,(complaints!$E$2:$E$928=MID(B12,FIND(" – ",B12)+3,999))*(complaints!$B$2:$B$928>='Harms table'!$B$2)*(complaints!$B$2:$B$928<='Harms table'!$D$2))),""))}
B13: {=IF(COUNTA(complaints!$A$2:$A$928)=0,"",IFERROR(_xlfn.LET(_xlpm.mdp,INDEX(_xlfn._xlws.SORT(_xlfn.UNIQUE(_xlfn._xlws.FILTER(complaints!$E$2:$E$928,complaints!$E$2:$E$928<>""))),9),_xlpm.code,IFERROR(VLOOKUP(_xlpm.mdp,Codes!$L$2:$N$409,3,FALSE),"—"),_xlpm.code&" – "&_xlpm.mdp),""))} | C13: =IF(B13="","",COUNTIFS(complaints!$E$2:$E$928,MID(B13,FIND(" – ",B13)+3,999),complaints!$B$2:$B$928,">="&'Harms table'!$B$2,complaints!$B$2:$B$928,"<="&'Harms table'!$D$2)) | D13: =IF(C13="","",IF('Harms table'!$B$8=0,"–",TEXT(C13/'Harms table'!$B$8*100,"0.00")&"%")) | E13: {=IF(B13="","",IFERROR(_xlfn.TEXTJOIN(", ",TRUE,_xlfn._xlws.FILTER(complaints!$A$2:$A$928,(complaints!$E$2:$E$928=MID(B13,FIND(" – ",B13)+3,999))*(complaints!$B$2:$B$928>='Harms table'!$B$2)*(complaints!$B$2:$B$928<='Harms table'!$D$2))),""))}
B14: {=IF(COUNTA(complaints!$A$2:$A$928)=0,"",IFERROR(_xlfn.LET(_xlpm.mdp,INDEX(_xlfn._xlws.SORT(_xlfn.UNIQUE(_xlfn._xlws.FILTER(complaints!$E$2:$E$928,complaints!$E$2:$E$928<>""))),10),_xlpm.code,IFERROR(VLOOKUP(_xlpm.mdp,Codes!$L$2:$N$409,3,FALSE),"—"),_xlpm.code&" – "&_xlpm.mdp),""))} | C14: =IF(B14="","",COUNTIFS(complaints!$E$2:$E$928,MID(B14,FIND(" – ",B14)+3,999),complaints!$B$2:$B$928,">="&'Harms table'!$B$2,complaints!$B$2:$B$928,"<="&'Harms table'!$D$2)) | D14: =IF(C14="","",IF('Harms table'!$B$8=0,"–",TEXT(C14/'Harms table'!$B$8*100,"0.00")&"%")) | E14: {=IF(B14="","",IFERROR(_xlfn.TEXTJOIN(", ",TRUE,_xlfn._xlws.FILTER(complaints!$A$2:$A$928,(complaints!$E$2:$E$928=MID(B14,FIND(" – ",B14)+3,999))*(complaints!$B$2:$B$928>='Harms table'!$B$2)*(complaints!$B$2:$B$928<='Harms table'!$D$2))),""))}
B15: {=IF(COUNTA(complaints!$A$2:$A$928)=0,"",IFERROR(_xlfn.LET(_xlpm.mdp,INDEX(_xlfn._xlws.SORT(_xlfn.UNIQUE(_xlfn._xlws.FILTER(complaints!$E$2:$E$928,complaints!$E$2:$E$928<>""))),11),_xlpm.code,IFERROR(VLOOKUP(_xlpm.mdp,Codes!$L$2:$N$409,3,FALSE),"—"),_xlpm.code&" – "&_xlpm.mdp),""))} | C15: =IF(B15="","",COUNTIFS(complaints!$E$2:$E$928,MID(B15,FIND(" – ",B15)+3,999),complaints!$B$2:$B$928,">="&'Harms table'!$B$2,complaints!$B$2:$B$928,"<="&'Harms table'!$D$2)) | D15: =IF(C15="","",IF('Harms table'!$B$8=0,"–",TEXT(C15/'Harms table'!$B$8*100,"0.00")&"%")) | E15: {=IF(B15="","",IFERROR(_xlfn.TEXTJOIN(", ",TRUE,_xlfn._xlws.FILTER(complaints!$A$2:$A$928,(complaints!$E$2:$E$928=MID(B15,FIND(" – ",B15)+3,999))*(complaints!$B$2:$B$928>='Harms table'!$B$2)*(complaints!$B$2:$B$928<='Harms table'!$D$2))),""))}
A16: Worldwide | B16: TOTAL | C16: =SUM(C5:C15) -> 16 | D16: =IF('Harms table'!$B$8=0,"–",TEXT(C16/'Harms table'!$B$8*100,"0.00")&"%") -> 0.03%
A18: Table 3 – Serious Incidents by IMDRF Annex C Cause Investigation Code
A19: Region | B19: IMDRF Cause Code & Term | C19: N (current period) | D19: Rate (%) | E19: Complaint Number(s)
A20: =IF(COUNTA(complaints!$A$2:$A$928)=0,"","Worldwide") -> Worldwide | B20: {=IF(COUNTA(complaints!$A$2:$A$928)=0,"",IFERROR(INDEX(_xlfn._xlws.SORT(_xlfn.UNIQUE(_xlfn._xlws.FILTER(complaints!$H$2:$H$928,complaints!$H$2:$H$928<>""))),1),""))} | C20: =IF(B20="","",COUNTIFS(complaints!$H$2:$H$928,B20,complaints!$B$2:$B$928,">="&'Harms table'!$B$2,complaints!$B$2:$B$928,"<="&'Harms table'!$D$2)) | D20: =IF(C20="","",IF('Harms table'!$B$8=0,"–",TEXT(C20/'Harms table'!$B$8*100,"0.00")&"%")) | E20: {=IF(B20="","",IFERROR(_xlfn.TEXTJOIN(", ",TRUE,_xlfn._xlws.FILTER(complaints!$A$2:$A$928,(complaints!$H$2:$H$928=B20)*(complaints!$B$2:$B$928>='Harms table'!$B$2)*(complaints!$B$2:$B$928<='Harms table'!$D$2))),""))}
B21: {=IF(COUNTA(complaints!$A$2:$A$928)=0,"",IFERROR(INDEX(_xlfn._xlws.SORT(_xlfn.UNIQUE(_xlfn._xlws.FILTER(complaints!$H$2:$H$928,complaints!$H$2:$H$928<>""))),2),""))} | C21: =IF(B21="","",COUNTIFS(complaints!$H$2:$H$928,B21,complaints!$B$2:$B$928,">="&'Harms table'!$B$2,complaints!$B$2:$B$928,"<="&'Harms table'!$D$2)) | D21: =IF(C21="","",IF('Harms table'!$B$8=0,"–",TEXT(C21/'Harms table'!$B$8*100,"0.00")&"%")) | E21: {=IF(B21="","",IFERROR(_xlfn.TEXTJOIN(", ",TRUE,_xlfn._xlws.FILTER(complaints!$A$2:$A$928,(complaints!$H$2:$H$928=B21)*(complaints!$B$2:$B$928>='Harms table'!$B$2)*(complaints!$B$2:$B$928<='Harms table'!$D$2))),""))}
B22: {=IF(COUNTA(complaints!$A$2:$A$928)=0,"",IFERROR(INDEX(_xlfn._xlws.SORT(_xlfn.UNIQUE(_xlfn._xlws.FILTER(complaints!$H$2:$H$928,complaints!$H$2:$H$928<>""))),3),""))} | C22: =IF(B22="","",COUNTIFS(complaints!$H$2:$H$928,B22,complaints!$B$2:$B$928,">="&'Harms table'!$B$2,complaints!$B$2:$B$928,"<="&'Harms table'!$D$2)) | D22: =IF(C22="","",IF('Harms table'!$B$8=0,"–",TEXT(C22/'Harms table'!$B$8*100,"0.00")&"%")) | E22: {=IF(B22="","",IFERROR(_xlfn.TEXTJOIN(", ",TRUE,_xlfn._xlws.FILTER(complaints!$A$2:$A$928,(complaints!$H$2:$H$928=B22)*(complaints!$B$2:$B$928>='Harms table'!$B$2)*(complaints!$B$2:$B$928<='Harms table'!$D$2))),""))}
B23: {=IF(COUNTA(complaints!$A$2:$A$928)=0,"",IFERROR(INDEX(_xlfn._xlws.SORT(_xlfn.UNIQUE(_xlfn._xlws.FILTER(complaints!$H$2:$H$928,complaints!$H$2:$H$928<>""))),4),""))} | C23: =IF(B23="","",COUNTIFS(complaints!$H$2:$H$928,B23,complaints!$B$2:$B$928,">="&'Harms table'!$B$2,complaints!$B$2:$B$928,"<="&'Harms table'!$D$2)) | D23: =IF(C23="","",IF('Harms table'!$B$8=0,"–",TEXT(C23/'Harms table'!$B$8*100,"0.00")&"%")) | E23: {=IF(B23="","",IFERROR(_xlfn.TEXTJOIN(", ",TRUE,_xlfn._xlws.FILTER(complaints!$A$2:$A$928,(complaints!$H$2:$H$928=B23)*(complaints!$B$2:$B$928>='Harms table'!$B$2)*(complaints!$B$2:$B$928<='Harms table'!$D$2))),""))}
B24: {=IF(COUNTA(complaints!$A$2:$A$928)=0,"",IFERROR(INDEX(_xlfn._xlws.SORT(_xlfn.UNIQUE(_xlfn._xlws.FILTER(complaints!$H$2:$H$928,complaints!$H$2:$H$928<>""))),5),""))} | C24: =IF(B24="","",COUNTIFS(complaints!$H$2:$H$928,B24,complaints!$B$2:$B$928,">="&'Harms table'!$B$2,complaints!$B$2:$B$928,"<="&'Harms table'!$D$2)) | D24: =IF(C24="","",IF('Harms table'!$B$8=0,"–",TEXT(C24/'Harms table'!$B$8*100,"0.00")&"%")) | E24: {=IF(B24="","",IFERROR(_xlfn.TEXTJOIN(", ",TRUE,_xlfn._xlws.FILTER(complaints!$A$2:$A$928,(complaints!$H$2:$H$928=B24)*(complaints!$B$2:$B$928>='Harms table'!$B$2)*(complaints!$B$2:$B$928<='Harms table'!$D$2))),""))}
B25: {=IF(COUNTA(complaints!$A$2:$A$928)=0,"",IFERROR(INDEX(_xlfn._xlws.SORT(_xlfn.UNIQUE(_xlfn._xlws.FILTER(complaints!$H$2:$H$928,complaints!$H$2:$H$928<>""))),6),""))} | C25: =IF(B25="","",COUNTIFS(complaints!$H$2:$H$928,B25,complaints!$B$2:$B$928,">="&'Harms table'!$B$2,complaints!$B$2:$B$928,"<="&'Harms table'!$D$2)) | D25: =IF(C25="","",IF('Harms table'!$B$8=0,"–",TEXT(C25/'Harms table'!$B$8*100,"0.00")&"%")) | E25: {=IF(B25="","",IFERROR(_xlfn.TEXTJOIN(", ",TRUE,_xlfn._xlws.FILTER(complaints!$A$2:$A$928,(complaints!$H$2:$H$928=B25)*(complaints!$B$2:$B$928>='Harms table'!$B$2)*(complaints!$B$2:$B$928<='Harms table'!$D$2))),""))}
B26: {=IF(COUNTA(complaints!$A$2:$A$928)=0,"",IFERROR(INDEX(_xlfn._xlws.SORT(_xlfn.UNIQUE(_xlfn._xlws.FILTER(complaints!$H$2:$H$928,complaints!$H$2:$H$928<>""))),7),""))} | C26: =IF(B26="","",COUNTIFS(complaints!$H$2:$H$928,B26,complaints!$B$2:$B$928,">="&'Harms table'!$B$2,complaints!$B$2:$B$928,"<="&'Harms table'!$D$2)) | D26: =IF(C26="","",IF('Harms table'!$B$8=0,"–",TEXT(C26/'Harms table'!$B$8*100,"0.00")&"%")) | E26: {=IF(B26="","",IFERROR(_xlfn.TEXTJOIN(", ",TRUE,_xlfn._xlws.FILTER(complaints!$A$2:$A$928,(complaints!$H$2:$H$928=B26)*(complaints!$B$2:$B$928>='Harms table'!$B$2)*(complaints!$B$2:$B$928<='Harms table'!$D$2))),""))}
B27: {=IF(COUNTA(complaints!$A$2:$A$928)=0,"",IFERROR(INDEX(_xlfn._xlws.SORT(_xlfn.UNIQUE(_xlfn._xlws.FILTER(complaints!$H$2:$H$928,complaints!$H$2:$H$928<>""))),8),""))} | C27: =IF(B27="","",COUNTIFS(complaints!$H$2:$H$928,B27,complaints!$B$2:$B$928,">="&'Harms table'!$B$2,complaints!$B$2:$B$928,"<="&'Harms table'!$D$2)) | D27: =IF(C27="","",IF('Harms table'!$B$8=0,"–",TEXT(C27/'Harms table'!$B$8*100,"0.00")&"%")) | E27: {=IF(B27="","",IFERROR(_xlfn.TEXTJOIN(", ",TRUE,_xlfn._xlws.FILTER(complaints!$A$2:$A$928,(complaints!$H$2:$H$928=B27)*(complaints!$B$2:$B$928>='Harms table'!$B$2)*(complaints!$B$2:$B$928<='Harms table'!$D$2))),""))}
B28: {=IF(COUNTA(complaints!$A$2:$A$928)=0,"",IFERROR(INDEX(_xlfn._xlws.SORT(_xlfn.UNIQUE(_xlfn._xlws.FILTER(complaints!$H$2:$H$928,complaints!$H$2:$H$928<>""))),9),""))} | C28: =IF(B28="","",COUNTIFS(complaints!$H$2:$H$928,B28,complaints!$B$2:$B$928,">="&'Harms table'!$B$2,complaints!$B$2:$B$928,"<="&'Harms table'!$D$2)) | D28: =IF(C28="","",IF('Harms table'!$B$8=0,"–",TEXT(C28/'Harms table'!$B$8*100,"0.00")&"%")) | E28: {=IF(B28="","",IFERROR(_xlfn.TEXTJOIN(", ",TRUE,_xlfn._xlws.FILTER(complaints!$A$2:$A$928,(complaints!$H$2:$H$928=B28)*(complaints!$B$2:$B$928>='Harms table'!$B$2)*(complaints!$B$2:$B$928<='Harms table'!$D$2))),""))}
B29: {=IF(COUNTA(complaints!$A$2:$A$928)=0,"",IFERROR(INDEX(_xlfn._xlws.SORT(_xlfn.UNIQUE(_xlfn._xlws.FILTER(complaints!$H$2:$H$928,complaints!$H$2:$H$928<>""))),10),""))} | C29: =IF(B29="","",COUNTIFS(complaints!$H$2:$H$928,B29,complaints!$B$2:$B$928,">="&'Harms table'!$B$2,complaints!$B$2:$B$928,"<="&'Harms table'!$D$2)) | D29: =IF(C29="","",IF('Harms table'!$B$8=0,"–",TEXT(C29/'Harms table'!$B$8*100,"0.00")&"%")) | E29: {=IF(B29="","",IFERROR(_xlfn.TEXTJOIN(", ",TRUE,_xlfn._xlws.FILTER(complaints!$A$2:$A$928,(complaints!$H$2:$H$928=B29)*(complaints!$B$2:$B$928>='Harms table'!$B$2)*(complaints!$B$2:$B$928<='Harms table'!$D$2))),""))}
B30: {=IF(COUNTA(complaints!$A$2:$A$928)=0,"",IFERROR(INDEX(_xlfn._xlws.SORT(_xlfn.UNIQUE(_xlfn._xlws.FILTER(complaints!$H$2:$H$928,complaints!$H$2:$H$928<>""))),11),""))} | C30: =IF(B30="","",COUNTIFS(complaints!$H$2:$H$928,B30,complaints!$B$2:$B$928,">="&'Harms table'!$B$2,complaints!$B$2:$B$928,"<="&'Harms table'!$D$2)) | D30: =IF(C30="","",IF('Harms table'!$B$8=0,"–",TEXT(C30/'Harms table'!$B$8*100,"0.00")&"%")) | E30: {=IF(B30="","",IFERROR(_xlfn.TEXTJOIN(", ",TRUE,_xlfn._xlws.FILTER(complaints!$A$2:$A$928,(complaints!$H$2:$H$928=B30)*(complaints!$B$2:$B$928>='Harms table'!$B$2)*(complaints!$B$2:$B$928<='Harms table'!$D$2))),""))}
B31: {=IF(COUNTA(complaints!$A$2:$A$928)=0,"",IFERROR(INDEX(_xlfn._xlws.SORT(_xlfn.UNIQUE(_xlfn._xlws.FILTER(complaints!$H$2:$H$928,complaints!$H$2:$H$928<>""))),12),""))} | C31: =IF(B31="","",COUNTIFS(complaints!$H$2:$H$928,B31,complaints!$B$2:$B$928,">="&'Harms table'!$B$2,complaints!$B$2:$B$928,"<="&'Harms table'!$D$2)) | D31: =IF(C31="","",IF('Harms table'!$B$8=0,"–",TEXT(C31/'Harms table'!$B$8*100,"0.00")&"%")) | E31: {=IF(B31="","",IFERROR(_xlfn.TEXTJOIN(", ",TRUE,_xlfn._xlws.FILTER(complaints!$A$2:$A$928,(complaints!$H$2:$H$928=B31)*(complaints!$B$2:$B$928>='Harms table'!$B$2)*(complaints!$B$2:$B$928<='Harms table'!$D$2))),""))}
B32: {=IF(COUNTA(complaints!$A$2:$A$928)=0,"",IFERROR(INDEX(_xlfn._xlws.SORT(_xlfn.UNIQUE(_xlfn._xlws.FILTER(complaints!$H$2:$H$928,complaints!$H$2:$H$928<>""))),13),""))} | C32: =IF(B32="","",COUNTIFS(complaints!$H$2:$H$928,B32,complaints!$B$2:$B$928,">="&'Harms table'!$B$2,complaints!$B$2:$B$928,"<="&'Harms table'!$D$2)) | D32: =IF(C32="","",IF('Harms table'!$B$8=0,"–",TEXT(C32/'Harms table'!$B$8*100,"0.00")&"%")) | E32: {=IF(B32="","",IFERROR(_xlfn.TEXTJOIN(", ",TRUE,_xlfn._xlws.FILTER(complaints!$A$2:$A$928,(complaints!$H$2:$H$928=B32)*(complaints!$B$2:$B$928>='Harms table'!$B$2)*(complaints!$B$2:$B$928<='Harms table'!$D$2))),""))}
A33: Worldwide | B33: TOTAL | C33: =SUM(C20:C32) -> 0 | D33: =IF('Harms table'!$B$8=0,"–",TEXT(C33/'Harms table'!$B$8*100,"0.00")&"%") -> 0.00%
A35: Table 4 – IMDRF Annex F Health Impact by Investigation Conclusion
A36: IMDRF Health Impact (Annex F) | B36: Region | C36: No. Serious Incidents | D36: D01 - Device Issue % | E36: D02 - Non-Device Issue % | F36: D03 - Inconclusive % | G36: D04 - Under Investigation %
A37: =IF(COUNTA(complaints!$A$2:$A$928)=0,"","No Clinical Signs, Symptoms or Conditions") -> No Clinical Signs, Symptoms or Conditions | B37: =IF(COUNTA(complaints!$A$2:$A$928)=0,"","Worldwide") -> Worldwide | C37: =IF(COUNTA(complaints!$A$2:$A$928)=0,"",COUNTIFS(complaints!$F$2:$F$928,"No Clinical Signs*",complaints!$B$2:$B$928,">="&'Harms table'!$B$2,complaints!$B$2:$B$928,"<="&'Harms table'!$D$2)) -> 16 | D37: =IF(OR(C37=0,C37=""),"–",TEXT(COUNTIFS(complaints!$F$2:$F$928,"No Clinical Signs*",complaints!$I$2:$I$928,"D01*",complaints!$B$2:$B$928,">="&'Harms table'!$B$2,complaints!$B$2:$B$928,"<="&'Harms table'!$D$2)/C37*100,"0.0")&"%") -> 0.0% | E37: =IF(OR(C37=0,C37=""),"–",TEXT(COUNTIFS(complaints!$F$2:$F$928,"No Clinical Signs*",complaints!$I$2:$I$928,"D02*",complaints!$B$2:$B$928,">="&'Harms table'!$B$2,complaints!$B$2:$B$928,"<="&'Harms table'!$D$2)/C37*100,"0.0")&"%") -> 0.0% | F37: =IF(OR(C37=0,C37=""),"–",TEXT(COUNTIFS(complaints!$F$2:$F$928,"No Clinical Signs*",complaints!$I$2:$I$928,"D03*",complaints!$B$2:$B$928,">="&'Harms table'!$B$2,complaints!$B$2:$B$928,"<="&'Harms table'!$D$2)/C37*100,"0.0")&"%") -> 0.0% | G37: =IF(OR(C37=0,C37=""),"–",TEXT(COUNTIFS(complaints!$F$2:$F$928,"No Clinical Signs*",complaints!$I$2:$I$928,"D04*",complaints!$B$2:$B$928,">="&'Harms table'!$B$2,complaints!$B$2:$B$928,"<="&'Harms table'!$D$2)/C37*100,"0.0")&"%") -> 0.0%
A38: TOTAL | B38: Worldwide | C38: =C37 -> 16 | D38: =D37 -> 0.0% | E38: =E37 -> 0.0% | F38: =F37 -> 0.0% | G38: =G37 -> 0.0%

Sheet Section H - FSCA
A1: Section H: Field Safety Corrective Actions (FSCA)
A3: Table 8 – FSCA Initiated in Current Reporting Period and Open FSCAs
A4: Type of Action | B4: Manufacturer Ref. Number | C4: Issuing Date / Date of Final FSN | D4: Scope / Device Models | E4: Status of FSCA | F4: Rationale & Description | G4: Impacted Regions | H4: Date Reported to MHRA
A16: Summary
A17: Total FSCAs | B17: =COUNTA(A5:A14) -> 0
A18: Open FSCAs | B18: =COUNTIF(E5:E14,"Open")+COUNTIF(E5:E14,"In Progress") -> 0
A19: Closed FSCAs | B19: =COUNTIF(E5:E14,"Closed") -> 0

Sheet Section I - CAPA
A1: Section I: Corrective and Preventive Actions (CAPA)
A3: Table 9 – CAPA Initiated in Current Reporting Period
A4: CAPA ID | B4: Date Initiated | C4: Source / Trigger | D4: Description of Issue | E4: Corrective / Preventive Action Taken | F4: Status | G4: Target Close Date
A16: Summary
A17: Total CAPAs | B17: =COUNTA(A5:A14) -> 0
A18: Open CAPAs | B18: =COUNTIF(F5:F14,"Open")+COUNTIF(F5:F14,"In Progress") -> 0
A19: Closed CAPAs | B19: =COUNTIF(F5:F14,"Closed") -> 0
A20: Overdue CAPAs | B20: =COUNTIF(F5:F14,"Overdue") -> 0

Sheet Codes
A1: IMDRF Code | B1: Medical Device Problem Term | C1: Level | D1: Parent Category | F1: IMDRF Code | G1: Harm Term | H1: Level | I1: Parent Category | K1: Symptom Code | L1: Default MDP | M1: Confidence | N1: IMDRF Code
A2: A01 | B2: Patient Device Interaction Problem | C2: 1 | F2: E01 | G2: Nervous System | H2: 1 | K2: alignmentissues | L2: Defective Device | M2: LOW | N2: A0203
A3: A0101 | B3: Patient-Device Incompatibility | C3: 2 | D3: Patient Device Interaction Problem | F3: E0101 | G3: Balance Problems | H3: 2 | I3: Nervous System | K3: bent | L3: Material Twisted/Bent | M3: HIGH | N3: A0406
A4: A0102 | B4: Osseointegration Problem | C4: 2 | D4: Patient Device Interaction Problem | F4: E0102 | G4: Brain Injury | H4: 2 | I4: Nervous System | K4: brokenbutton | L4: Break | M4: HIGH | N4: A0401
A5: A0103 | B5: Loosening of Implant Not Related to Bone-Ingrowth | C5: 2 | D5: Patient Device Interaction Problem | F5: E0103 | G5: Cerebral Edema | H5: 2 | I5: Nervous System | K5: brokenhandle | L5: Break | M5: HIGH | N5: A0401
A6: A0104 | B6: Migration or Expulsion of Device | C6: 2 | D6: Patient Device Interaction Problem | F6: E0104 | G6: Cerebral Hyperperfusion Syndrome | H6: 2 | I6: Nervous System | K6: brokenordamagedcomponent | L6: Break | M6: LOW | N6: A0401
A7: A0105 | B7: Lack of Effect | C7: 2 | D7: Patient Device Interaction Problem | F7: E0105 | G7: Cerebral Ventriculomegaly | H7: 2 | I7: Nervous System | K7: cannotbeadjusted | L7: Defective Device | M7: LOW | N7: A0203
A8: A0106 | B8: Device Stenosis | C8: 2 | D8: Patient Device Interaction Problem | F8: E0106 | G8: Cerebrospinal Fluid Leakage | H8: 2 | I8: Nervous System | K8: componentseparation | L8: Material Separation | M8: HIGH | N8: A0413
A9: A0107 | B9: Implant Subsidence | C9: 2 | D9: Patient Device Interaction Problem | F9: E0107 | G9: Cognitive Changes | H9: 2 | I9: Nervous System | K9: connectionissues | L9: Loose or Intermittent Connection | M9: HIGH | N9: A1205
A10: A02 | B10: Manufacturing, Packaging or Shipping Problem | C10: 1 | F10: E0108 | G10: Concussion | H10: 2 | I10: Nervous System | K10: damagedpackaging | L10: Packaging Problem | M10: HIGH | N10: A0205
A11: A0201 | B11: Product Quality Problem | C11: 2 | D11: Manufacturing, Packaging or Shipping Problem | F11: E0109 | G11: Convulsion/Seizure | H11: 2 | I11: Nervous System | K11: discolorationortarnish | L11: Contamination | M11: MED | N11: A1801
A12: A0202 | B12: Defective Component | C12: 2 | D12: Manufacturing, Packaging or Shipping Problem | F12: E0110 | G12: Hyporesponsive to Stimuli | H12: 2 | I12: Nervous System | K12: doesnotperformproperly | L12: Defective Device | M12: MED | N12: A0203
A13: A0203 | B13: Defective Device | C13: 2 | D13: Manufacturing, Packaging or Shipping Problem | F13: E0111 | G13: Hyperresponsive to Stimuli | H13: 2 | I13: Nervous System | K13: electrical | L13: Electrical Power Problem | M13: MED | N13: A1910
A14: A0204 | B14: Device Damaged Prior to Use | C14: 2 | D14: Manufacturing, Packaging or Shipping Problem | F14: E0112 | G14: Dizziness | H14: 2 | I14: Nervous System | K14: equipment | L14: Defective Device | M14: LOW | N14: A0203
A15: A0205 | B15: Packaging Problem | C15: 2 | D15: Manufacturing, Packaging or Shipping Problem | F15: E0113 | G15: Dysphasia | H15: 2 | I15: Nervous System | K15: excessiveheat | L15: Overheating of Device | M15: HIGH | N15: A1005
A16: A0206 | B16: Device Misassembled During Manufacturing / Shipping | C16: 2 | D16: Manufacturing, Packaging or Shipping Problem | F16: E0114 | G16: Encephalitis | H16: 2 | I16: Nervous System | K16: excessivesoundornoise | L16: Noise, Audible | M16: HIGH | N16: A0508
A17: A0207 | B17: Shipping Damage or Problem Device Damaged Prior to Receipt by User | C17: 2 | D17: Manufacturing, Packaging or Shipping Problem | F17: E0115 | G17: Encephalopathy | H17: 2 | I17: Nervous System | K17: footpedalissues | L17: Material Frayed | M17: LOW | N17: A0414
A18: A03 | B18: Chemical Problem | C18: 1 | F18: E0116 | G18: Headache | H18: 2 | I18: Nervous System | K18: foreignmaterial | L18: Contamination | M18: HIGH | N18: A1801
A19: A0301 | B19: Device Emits Odor | C19: 2 | D19: Chemical Problem | F19: E0117 | G19: Hydrocephalus | H19: 2 | I19: Nervous System | K19: holeortear | L19: Material Frayed | M19: MED | N19: A0414
A20: A0302 | B20: Device Ingredient or Reagent Problem | C20: 2 | D20: Chemical Problem | F20: E0118 | G20: Intracranial Hemorrhage | H20: 2 | I20: Nervous System | K20: intermittentfunctionality | L20: Difficult or Delayed Activation | M20: HIGH | N20: A1501
A21: A0303 | B21: Improper Chemical Reaction | C21: 2 | D21: Chemical Problem | F21: E0119 | G21: Intracranial Hypertension | H21: 2 | I21: Nervous System | K21: labeling | L21: Device Markings/Labelling Problem | M21: HIGH | N21: A2101
A22: A04 | B22: Material Integrity Problem | C22: 1 | F22: E0120 | G22: Loss of Consciousness | H22: 2 | I22: Nervous System | K22: laceration | L22: Defective Device | M22: LOW | N22: A0203
A23: A0401 | B23: Break | C23: 2 | D23: Material Integrity Problem | F23: E0121 | G23: Meningitis | H23: 2 | I23: Nervous System | K23: leak | L23: Fluid/Blood Leak | M23: HIGH | N23: A0504
A24: A0402 | B24: Burst Container or Vessel | C24: 2 | D24: Material Integrity Problem | F24: E0122 | G24: Migraine | H24: 2 | I24: Nervous System | K24: lowpressure | L24: Detachment of Device or Device Component | M24: MED | N24: A0501
A25: A0403 | B25: Explosion | C25: 2 | D25: Material Integrity Problem | F25: E0123 | G25: Movement Disorder | H25: 2 | I25: Nervous System | K25: missingcomponent | L25: Component Missing | M25: HIGH | N25: A0202
A26: A0404 | B26: Crack | C26: 2 | D26: Material Integrity Problem | F26: E0124 | G26: Nerve Damage | H26: 2 | I26: Nervous System | K26: other | L26: Appropriate Device Problem Term/Code Not Available | M26: LOW | N26: A27
A27: A0405 | B27: Degraded | C27: 2 | D27: Material Integrity Problem | F27: E0125 | G27: Neuralgia | H27: 2 | I27: Nervous System | K27: performance | L27: Defective Device | M27: LOW | N27: A0203
A28: A0406 | B28: Material Deformation | C28: 2 | D28: Material Integrity Problem | F28: E0126 | G28: Numbness | H28: 2 | I28: Nervous System | K28: powerissues | L28: Complete Loss of Power | M28: HIGH | N28: A0708
A29: A0407 | B29: Material Discolored | C29: 2 | D29: Material Integrity Problem | F29: E0127 | G29: Paresis/Paralysis | H29: 2 | I29: Nervous System | K29: pressureissues | L29: Detachment of Device or Device Component | M29: MED | N29: A0501
A30: A0408 | B30: Material Disintegration | C30: 2 | D30: Material Integrity Problem | F30: E0128 | G30: Peripheral Neuropathy | H30: 2 | I30: Nervous System | K30: productslipping | L30: Detachment of Device or Device Component | M30: LOW | N30: A0501
A31: A0409 | B31: Material Opacification | C31: 2 | D31: Material Integrity Problem | F31: E0129 | G31: Spinal Cord Injury | H31: 2 | I31: Nervous System | K31: productsticking | L31: Mechanical Jam | M31: HIGH | N31: A0506
A32: A0410 | B32: Material Perforation | C32: 2 | D32: Material Integrity Problem | F32: E0130 | G32: Stroke | H32: 2 | I32: Nervous System | K32: rigidjoints | L32: Mechanical Jam | M32: LOW | N32: A0506
A33: A0411 | B33: Material Protrusion/Extrusion | C33: 2 | D33: Material Integrity Problem | F33: E0131 | G33: Syncope | H33: 2 | I33: Nervous System | K33: rust | L33: Corroded | M33: HIGH | N33: A0405
A34: A0412 | B34: Material Rupture | C34: 2 | D34: Material Integrity Problem | F34: E0132 | G34: Tingling/Paresthesias | H34: 2 | I34: Nervous System | K34: shippingdamage | L34: Break | M34: MED | N34: A0401
... A38: A0416 | B38: Failure to Degrade | C38: 2 | D38: Material Integrity Problem | F38: E0136 | G38: Vertigo | H38: 2 | I38: Nervous System | K38: burn | L38: Overheating of Device | M38: MED | N38: A1005
A39: A05 | B39: Mechanical Problem | C39: 1 | F39: E02 | G39: Mental, Emotional and Behavioural Disorders | H39: 1
A40: A0501 | B40: Detachment of Device or Device Component | C40: 2 | D40: Mechanical Problem | F40: E0201 | G40: Addictive Disorder | H40: 2 | I40: Mental, Emotional and Behavioural Disorders
A41: A0502 | B41: Device Damaged by Another Device | C41: 2 | D41: Mechanical Problem | F41: E0202 | G41: Anxiety or Fear | H41: 2 | I41: Mental, Emotional and Behavioural Disorders
A42: A0503 | B42: Ejection Problem | C42: 2 | D42: Mechanical Problem | F42: E0203 | G42: Delirium | H42: 2 | I42: Mental, Emotional and Behavioural Disorders
A43: A0504 | B43: Leak/Splash | C43: 2 | D43: Mechanical Problem | F43: E0204 | G43: Depression | H43: 2 | I43: Mental, Emotional and Behavioural Disorders
A44: A0505 | B44: Firing Problem | C44: 2 | D44: Mechanical Problem | F44: E0205 | G44: Eating Disorder | H44: 2 | I44: Mental, Emotional and Behavioural Disorders
A45: A0506 | B45: Mechanical Jam | C45: 2 | D45: Mechanical Problem | F45: E0206 | G45: Mood Disorder or Disturbance | H45: 2 | I45: Mental, Emotional and Behavioural Disorders
A46: A0507 | B46: Mechanics Altered | C46: 2 | D46: Mechanical Problem | F46: E0207 | G46: Post-Traumatic Stress Disorder | H46: 2 | I46: Mental, Emotional and Behavioural Disorders
A47: A0508 | B47: Noise, Audible | C47: 2 | D47: Mechanical Problem | F47: E0208 | G47: Psychotic Disorder | H47: 2 | I47: Mental, Emotional and Behavioural Disorders
A48: A0509 | B48: Physical Resistance/Sticking | C48: 2 | D48: Mechanical Problem | F48: E0209 | G48: Sexual Disorder | H48: 2 | I48: Mental, Emotional and Behavioural Disorders
A49: A0510 | B49: Retraction Problem | C49: 2 | D49: Mechanical Problem | F49: E0210 | G49: Sleep Disorder | H49: 2 | I49: Mental, Emotional and Behavioural Disorders
A50: A0511 | B50: Structural Problem | C50: 2 | D50: Mechanical Problem | F50: E0211 | G50: Stress | H50: 2 | I50: Mental, Emotional and Behavioural Disorders
A51: A0512 | B51: Unintended Movement | C51: 2 | D51: Mechanical Problem | F51: E0212 | G51: Suicidal Ideation or Attempted Suicide | H51: 2 | I51: Mental, Emotional and Behavioural Disorders
A52: A0513 | B52: Inadequate Lubrication | C52: 2 | D52: Mechanical Problem | F52: E03 | G52: Blood and Lymphatic System | H52: 1
A53: A0514 | B53: Damaged Thread | C53: 2 | D53: Mechanical Problem | F53: E0301 | G53: Anemia | H53: 2 | I53: Blood and Lymphatic System
A54: A06 | B54: Optical Problem | C54: 1 | F54: E0302 | G54: Bone Marrow Failure | H54: 2 | I54: Blood and Lymphatic System
A55: A0601 | B55: Misfocusing | C55: 2 | D55: Optical Problem | F55: E0303 | G55: Coagulation Disorder | H55: 2 | I55: Blood and Lymphatic System
A56: A0602 | B56: Optical Decentration | C56: 2 | D56: Optical Problem | F56: E0304 | G56: Hematoma | H56: 2 | I56: Blood and Lymphatic System
A57: A0603 | B57: Optical Discoloration | C57: 2 | D57: Optical Problem | F57: E0305 | G57: Hemorrhage | H57: 2 | I57: Blood and Lymphatic System
A58: A0604 | B58: Optical Distortion | C58: 2 | D58: Optical Problem | F58: E0306 | G58: Lymphadenopathy | H58: 2 | I58: Blood and Lymphatic System
A59: A0605 | B59: Optical Obstruction | C59: 2 | D59: Optical Problem | F59: E0307 | G59: Lymphedema | H59: 2 | I59: Blood and Lymphatic System
A60: A07 | B60: Electrical/Electronic Property Problem | C60: 1 | F60: E0308 | G60: Seroma | H60: 2 | I60: Blood and Lymphatic System
A61: A0701 | B61: Capturing Problem | C61: 2 | D61: Electrical/Electronic Property Problem | F61: E0309 | G61: Thrombocytopenia | H61: 2 | I61: Blood and Lymphatic System
A62: A0702 | B62: Continuous Firing | C62: 2 | D62: Electrical/Electronic Property Problem | F62: E0310 | G62: Thrombosis | H62: 2 | I62: Blood and Lymphatic System
A63: A0703 | B63: Arcing | C63: 2 | D63: Electrical/Electronic Property Problem | F63: E0311 | G63: White Blood Cell Disorder | H63: 2 | I63: Blood and Lymphatic System
A64: A0704 | B64: Sparking | C64: 2 | D64: Electrical/Electronic Property Problem | F64: E04 | G64: Immune System | H64: 1
A65: A0705 | B65: Battery Problem | C65: 2 | D65: Electrical/Electronic Property Problem | F65: E0401 | G65: Allergic Reaction | H65: 2 | I65: Immune System
A66: A0706 | B66: Charging Problem | C66: 2 | D66: Electrical/Electronic Property Problem | F66: E0402 | G66: Anaphylactic Reaction | H66: 2 | I66: Immune System
A67: A0707 | B67: Failure to Discharge | C67: 2 | D67: Electrical/Electronic Property Problem | F67: E0403 | G67: Autoimmune Disorder | H67: 2 | I67: Immune System
A68: A0708 | B68: Power Problem | C68: 2 | D68: Electrical/Electronic Property Problem | F68: E0404 | G68: Graft Rejection | H68: 2 | I68: Immune System
A69: A0709 | B69: Device Sensing Problem | C69: 2 | D69: Electrical/Electronic Property Problem | F69: E0405 | G69: Graft-versus-Host Disease | H69: 2 | I69: Immune System
A70: A0710 | B70: Failure to Conduct | C70: 2 | D70: Electrical/Electronic Property Problem | F70: E0406 | G70: Hypersensitivity | H70: 2 | I70: Immune System
A71: A0711 | B71: Interrogation Problem | C71: 2 | D71: Electrical/Electronic Property Problem | F71: E0407 | G71: Immunodeficiency | H71: 2 | I71: Immune System
A72: A0712 | B72: Pacing Problem | C72: 2 | D72: Electrical/Electronic Property Problem | F72: E0408 | G72: Immunological Reaction | H72: 2 | I72: Immune System
A73: A0713 | B73: Defibrillation/Stimulation Problem | C73: 2 | D73: Electrical/Electronic Property Problem | F73: E0409 | G73: Metal Sensitivity | H73: 2 | I73: Immune System
A74: A0714 | B74: Unintended Electrical Shock | C74: 2 | D74: Electrical/Electronic Property Problem | F74: E05 | G74: Vascular System | H74: 1
A75: A0715 | B75: Grounding Malfunction | C75: 2 | D75: Electrical/Electronic Property Problem | F75: E0501 | G75: Aneurysm | H75: 2 | I75: Vascular System
A76: A0716 | B76: Electrical Overstress | C76: 2 | D76: Electrical/Electronic Property Problem | F76: E0502 | G76: Angina Pectoris | H76: 2 | I76: Vascular System
A77: A0717 | B77: Electrostatic Discharge | C77: 2 | D77: Electrical/Electronic Property Problem | F77: E0503 | G77: Arteriovenous Fistula Complication | H77: 2 | I77: Vascular System
A78: A0718 | B78: Failure to Shut Off | C78: 2 | D78: Electrical/Electronic Property Problem | F78: E0504 | G78: Arteriovenous Fistula Malfunction | H78: 2 | I78: Vascular System
A79: A0719 | B79: Unexpected Shutdown | C79: 2 | D79: Electrical/Electronic Property Problem | F79: E0505 | G79: Aortic Dissection | H79: 2 | I79: Vascular System
A80: A0720 | B80: Electromagnetic Compatibility Problem | C80: 2 | D80: Electrical/Electronic Property Problem | F80: E0506 | G80: Blood Pressure Changes | H80: 2 | I80: Vascular System
A81: A0721 | B81: Circuit Failure | C81: 2 | D81: Electrical/Electronic Property Problem | F81: E0507 | G81: Circulatory Problem | H81: 2 | I81: Vascular System
A82: A0722 | B82: Impedance Problem | C82: 2 | D82: Electrical/Electronic Property Problem | F82: E0508 | G82: Deep Vein Thrombosis | H82: 2 | I82: Vascular System
A83: A0723 | B83: Unexpected Mode Switch | C83: 2 | D83: Electrical/Electronic Property Problem | F83: E0509 | G83: Embolism | H83: 2 | I83: Vascular System
A84: A08 | B84: Calibration Problem | C84: 1 | F84: E0510 | G84: Hematological Signs and Symptoms | H84: 2 | I84: Vascular System
A85: A0801 | B85: Failure to Calibrate | C85: 2 | D85: Calibration Problem | F85: E0511 | G85: Hemodynamic Instability | H85: 2 | I85: Vascular System
A86: A0802 | B86: Failure to Recalibrate | C86: 2 | D86: Calibration Problem | F86: E0512 | G86: Ischemia | H86: 2 | I86: Vascular System
A87: A0803 | B87: Imprecision | C87: 2 | D87: Calibration Problem | F87: E0513 | G87: Phlebitis | H87: 2 | I87: Vascular System
A88: A0804 | B88: Overcorrection | C88: 2 | D88: Calibration Problem | F88: E0514 | G88: Vascular Damage or Injury | H88: 2 | I88: Vascular System
A89: A0805 | B89: Undercorrection | C89: 2 | D89: Calibration Problem | F89: E0515 | G89: Vascular Dissection | H89: 2 | I89: Vascular System
A90: A09 | B90: Output Problem | C90: 1 | F90: E0516 | G90: Vascular Fistula | H90: 2 | I90: Vascular System
A91: A0901 | B91: Audible Prompt/Feedback Problem | C91: 2 | D91: Output Problem | F91: E0517 | G91: Vascular Occlusion | H91: 2 | I91: Vascular System
A92: A0902 | B92: Display or Visual Feedback Problem | C92: 2 | D92: Output Problem | F92: E0518 | G92: Vascular Perforation | H92: 2 | I92: Vascular System
A93: A0903 | B93: Tactile Prompts/Feedback | C93: 2 | D93: Output Problem | F93: E0519 | G93: Vascular Pseudoaneurysm | H93: 2 | I93: Vascular System
A94: A0904 | B94: Energy Output Problem | C94: 2 | D94: Output Problem | F94: E0520 | G94: Vascular Spasm | H94: 2 | I94: Vascular System
A95: A0905 | B95: Radiation Output Problem | C95: 2 | D95: Output Problem | F95: E0521 | G95: Vascular Stenosis or Restenosis | H95: 2 | I95: Vascular System
A96: A0906 | B96: Gas Output Problem | C96: 2 | D96: Output Problem | F96: E0522 | G96: Vasovagal Response | H96: 2 | I96: Vascular System
A97: A0907 | B97: No Device Output | C97: 2 | D97: Output Problem | F97: E06 | G97: Heart | H97: 1
A98: A0908 | B98: Incorrect, Inadequate or Imprecise Result or Readings | C98: 2 | D98: Output Problem | F98: E0601 | G98: Cardiac Arrest | H98: 2 | I98: Heart
A99: A0909 | B99: Unexpected Therapeutic Results | C99: 2 | D99: Output Problem | F99: E0602 | G99: Cardiac Conduction Disorder | H99: 2 | I99: Heart
A100: A10 | B100: Temperature Problem | C100: 1 | F100: E0603 | G100: Cardiac Failure | H100: 2 | I100: Heart
A101: A1001 | B101: Excessive Cooling | C101: 2 | D101: Temperature Problem | F101: E0604 | G101: Cardiac Tamponade | H101: 2 | I101: Heart
A102: A1002 | B102: Excessive Heating | C102: 2 | D102: Temperature Problem | F102: E0605 | G102: Cardiomyopathy | H102: 2 | I102: Heart
A103: A1003 | B103: Insufficient Cooling | C103: 2 | D103: Temperature Problem | F103: E0606 | G103: Endocarditis | H103: 2 | I103: Heart
...

Sheet Complaint Rate
A1: Month | B1: Complaints | C1: Cumulative Sales | D1: Complaint Rate (per unit) | E1: Mean Rate | F1: UCL (Mean + 3σ) | G1: Breach? | I1: Month | J1: Complaint Rate | K1: Mean Rate | L1: UCL
A2: =IF(Config!C8="","",DATE(YEAR(Config!C8),MONTH(Config!C8),1)) -> 44743 | B2: =IF(A2="","",COUNTIFS(complaints!$B$2:$B$928,">="&A2,complaints!$B$2:$B$928,"<="&EOMONTH(A2,0),complaints!$B$2:$B$928,"<>"&"")) -> 0 | C2: =IF(A2="","",SUMIFS(Sales!$C$2:$C$78141,Sales!$D$2:$D$78141,YEAR(A2),Sales!$B$2:$B$78141,TEXT(A2,"MMMM"))) -> 1569 | D2: =IF(A2="","",IF(C2=0,IF(B2=0,0,B2),B2/C2)) -> 0 | E2: =IF(A2="","",AVERAGEIF($D$2:$D$46,"<>")) -> 0.0002761998 | F2: {=IF(A2="","",AVERAGEIF($D$2:$D$46,"<>")+3*IFERROR(STDEV(IF($D$2:$D$46<>"", $D$2:$D$46)),0))} -> 0.0023740003 | G2: =IF(A2="","",IF(D2>F2,"⚠ BREACH","")) | I2: =IF(A2="","",TEXT(A2,"MMM YYYY")) -> Jul 2022 | J2: =IF(A2="","",D2) -> 0 | K2: =IF(A2="","",E2) -> 0.0002761998 | L2: =IF(A2="","",F2) -> 0.0023740003
A3: =IF(A2="","",IF(EDATE(A2,1)>EOMONTH(Config!$C$9,0),"",EDATE(A2,1))) -> 44774 | B3: =IF(A3="","",COUNTIFS(complaints!$B$2:$B$928,">="&A3,complaints!$B$2:$B$928,"<="&EOMONTH(A3,0),complaints!$B$2:$B$928,"<>"&"")) -> 0 | C3: =IF(A3="","",SUMIFS(Sales!$C$2:$C$78141,Sales!$D$2:$D$78141,YEAR(A3),Sales!$B$2:$B$78141,TEXT(A3,"MMMM"))) -> 1518 | D3: =IF(A3="","",IF(C3=0,IF(B3=0,0,B3),B3/C3)) -> 0 | E3: =IF(A3="","",AVERAGEIF($D$2:$D$46,"<>")) -> 0.0002761998 | F3: {=IF(A3="","",AVERAGEIF($D$2:$D$46,"<>")+3*IFERROR(STDEV(IF($D$2:$D$46<>"", $D$2:$D$46)),0))} -> 0.0023740003 | G3: =IF(A3="","",IF(D3>F3,"⚠ BREACH","")) | I3: =IF(A3="","",TEXT(A3,"MMM YYYY")) -> Aug 2022 | J3: =IF(A3="","",D3) -> 0 | K3: =IF(A3="","",E3) -> 0.0002761998 | L3: =IF(A3="","",F3) -> 0.0023740003
A4: =IF(A3="","",IF(EDATE(A3,1)>EOMONTH(Config!$C$9,0),"",EDATE(A3,1))) -> 44805 | B4: =IF(A4="","",COUNTIFS(complaints!$B$2:$B$928,">="&A4,complaints!$B$2:$B$928,"<="&EOMONTH(A4,0),complaints!$B$2:$B$928,"<>"&"")) -> 0 | C4: =IF(A4="","",SUMIFS(Sales!$C$2:$C$78141,Sales!$D$2:$D$78141,YEAR(A4),Sales!$B$2:$B$78141,TEXT(A4,"MMMM"))) -> 1521 | D4: =IF(A4="","",IF(C4=0,IF(B4=0,0,B4),B4/C4)) -> 0 | E4: =IF(A4="","",AVERAGEIF($D$2:$D$46,"<>")) -> 0.0002761998 | F4: {=IF(A4="","",AVERAGEIF($D$2:$D$46,"<>")+3*IFERROR(STDEV(IF($D$2:$D$46<>"", $D$2:$D$46)),0))} -> 0.0023740003 | G4: =IF(A4="","",IF(D4>F4,"⚠ BREACH","")) | I4: =IF(A4="","",TEXT(A4,"MMM YYYY")) -> Sep 2022 | J4: =IF(A4="","",D4) -> 0 | K4: =IF(A4="","",E4) -> 0.0002761998 | L4: =IF(A4="","",F4) -> 0.0023740003
A5: =IF(A4="","",IF(EDATE(A4,1)>EOMONTH(Config!$C$9,0),"",EDATE(A4,1))) -> 44835 | B5: =IF(A5="","",COUNTIFS(complaints!$B$2:$B$928,">="&A5,complaints!$B$2:$B$928,"<="&EOMONTH(A5,0),complaints!$B$2:$B$928,"<>"&"")) -> 0 | C5: =IF(A5="","",SUMIFS(Sales!$C$2:$C$78141,Sales!$D$2:$D$78141,YEAR(A5),Sales!$B$2:$B$78141,TEXT(A5,"MMMM"))) -> 1548 | D5: =IF(A5="","",IF(C5=0,IF(B5=0,0,B5),B5/C5)) -> 0 | E5: =IF(A5="","",AVERAGEIF($D$2:$D$46,"<>")) -> 0.0002761998 | F5: {=IF(A5="","",AVERAGEIF($D$2:$D$46,"<>")+3*IFERROR(STDEV(IF($D$2:$D$46<>"", $D$2:$D$46)),0))} -> 0.0023740003 | G5: =IF(A5="","",IF(D5>F5,"⚠ BREACH","")) | I5: =IF(A5="","",TEXT(A5,"MMM YYYY")) -> Oct 2022 | J5: =IF(A5="","",D5) -> 0 | K5: =IF(A5="","",E5) -> 0.0002761998 | L5: =IF(A5="","",F5) -> 0.0023740003
A6: =IF(A5="","",IF(EDATE(A5,1)>EOMONTH(Config!$C$9,0),"",EDATE(A5,1))) -> 44866 | B6: =IF(A6="","",COUNTIFS(complaints!$B$2:$B$928,">="&A6,complaints!$B$2:$B$928,"<="&EOMONTH(A6,0),complaints!$B$2:$B$928,"<>"&"")) -> 0 | C6: =IF(A6="","",SUMIFS(Sales!$C$2:$C$78141,Sales!$D$2:$D$78141,YEAR(A6),Sales!$B$2:$B$78141,TEXT(A6,"MMMM"))) -> 1528 | D6: =IF(A6="","",IF(C6=0,IF(B6=0,0,B6),B6/C6)) -> 0 | E6: =IF(A6="","",AVERAGEIF($D$2:$D$46,"<>")) -> 0.0002761998 | F6: {=IF(A6="","",AVERAGEIF($D$2:$D$46,"<>")+3*IFERROR(STDEV(IF($D$2:$D$46<>"", $D$2:$D$46)),0))} -> 0.0023740003 | G6: =IF(A6="","",IF(D6>F6,"⚠ BREACH","")) | I6: =IF(A6="","",TEXT(A6,"MMM YYYY")) -> Nov 2022 | J6: =IF(A6="","",D6) -> 0 | K6: =IF(A6="","",E6) -> 0.0002761998 | L6: =IF(A6="","",F6) -> 0.0023740003
A7: =IF(A6="","",IF(EDATE(A6,1)>EOMONTH(Config!$C$9,0),"",EDATE(A6,1))) -> 44896 | B7: =IF(A7="","",COUNTIFS(complaints!$B$2:$B$928,">="&A7,complaints!$B$2:$B$928,"<="&EOMONTH(A7,0),complaints!$B$2:$B$928,"<>"&"")) -> 0 | C7: =IF(A7="","",SUMIFS(Sales!$C$2:$C$78141,Sales!$D$2:$D$78141,YEAR(A7),Sales!$B$2:$B$78141,TEXT(A7,"MMMM"))) -> 1201 | D7: =IF(A7="","",IF(C7=0,IF(B7=0,0,B7),B7/C7)) -> 0 | E7: =IF(A7="","",AVERAGEIF($D$2:$D$46,"<>")) -> 0.0002761998 | F7: {=IF(A7="","",AVERAGEIF($D$2:$D$46,"<>")+3*IFERROR(STDEV(IF($D$2:$D$46<>"", $D$2:$D$46)),0))} -> 0.0023740003 | G7: =IF(A7="","",IF(D7>F7,"⚠ BREACH","")) | I7: =IF(A7="","",TEXT(A7,"MMM YYYY")) -> Dec 2022 | J7: =IF(A7="","",D7) -> 0 | K7: =IF(A7="","",E7) -> 0.0002761998 | L7: =IF(A7="","",F7) -> 0.0023740003
A8: =IF(A7="","",IF(EDATE(A7,1)>EOMONTH(Config!$C$9,0),"",EDATE(A7,1))) -> 44927 | B8: =IF(A8="","",COUNTIFS(complaints!$B$2:$B$928,">="&A8,complaints!$B$2:$B$928,"<="&EOMONTH(A8,0),complaints!$B$2:$B$928,"<>"&"")) -> 0 | C8: =IF(A8="","",SUMIFS(Sales!$C$2:$C$78141,Sales!$D$2:$D$78141,YEAR(A8),Sales!$B$2:$B$78141,TEXT(A8,"MMMM"))) -> 2007 | D8: =IF(A8="","",IF(C8=0,IF(B8=0,0,B8),B8/C8)) -> 0 | E8: =IF(A8="","",AVERAGEIF($D$2:$D$46,"<>")) -> 0.0002761998 | F8: {=IF(A8="","",AVERAGEIF($D$2:$D$46,"<>")+3*IFERROR(STDEV(IF($D$2:$D$46<>"", $D$2:$D$46)),0))} -> 0.0023740003 | G8: =IF(A8="","",IF(D8>F8,"⚠ BREACH","")) | I8: =IF(A8="","",TEXT(A8,"MMM YYYY")) -> Jan 2023 | J8: =IF(A8="","",D8) -> 0 | K8: =IF(A8="","",E8) -> 0.0002761998 | L8: =IF(A8="","",F8) -> 0.0023740003
A9: =IF(A8="","",IF(EDATE(A8,1)>EOMONTH(Config!$C$9,0),"",EDATE(A8,1))) -> 44958 | B9: =IF(A9="","",COUNTIFS(complaints!$B$2:$B$928,">="&A9,complaints!$B$2:$B$928,"<="&EOMONTH(A9,0),complaints!$B$2:$B$928,"<>"&"")) -> 0 | C9: =IF(A9="","",SUMIFS(Sales!$C$2:$C$78141,Sales!$D$2:$D$78141,YEAR(A9),Sales!$B$2:$B$78141,TEXT(A9,"MMMM"))) -> 1670 | D9: =IF(A9="","",IF(C9=0,IF(B9=0,0,B9),B9/C9)) -> 0 | E9: =IF(A9="","",AVERAGEIF($D$2:$D$46,"<>")) -> 0.0002761998 | F9: {=IF(A9="","",AVERAGEIF($D$2:$D$46,"<>")+3*IFERROR(STDEV(IF($D$2:$D$46<>"", $D$2:$D$46)),0))} -> 0.0023740003 | G9: =IF(A9="","",IF(D9>F9,"⚠ BREACH","")) | I9: =IF(A9="","",TEXT(A9,"MMM YYYY")) -> Feb 2023 | J9: =IF(A9="","",D9) -> 0 | K9: =IF(A9="","",E9) -> 0.0002761998 | L9: =IF(A9="","",F9) -> 0.0023740003
A10: =IF(A9="","",IF(EDATE(A9,1)>EOMONTH(Config!$C$9,0),"",EDATE(A9,1))) -> 44986 | B10: =IF(A10="","",COUNTIFS(complaints!$B$2:$B$928,">="&A10,complaints!$B$2:$B$928,"<="&EOMONTH(A10,0),complaints!$B$2:$B$928,"<>"&"")) -> 1 | C10: =IF(A10="","",SUMIFS(Sales!$C$2:$C$78141,Sales!$D$2:$D$78141,YEAR(A10),Sales!$B$2:$B$78141,TEXT(A10,"MMMM"))) -> 1972 | D10: =IF(A10="","",IF(C10=0,IF(B10=0,0,B10),B10/C10)) -> 0.00050709939 | E10: =IF(A10="","",AVERAGEIF($D$2:$D$46,"<>")) -> 0.0002761998 | F10: {=IF(A10="","",AVERAGEIF($D$2:$D$46,"<>")+3*IFERROR(STDEV(IF($D$2:$D$46<>"", $D$2:$D$46)),0))} -> 0.0023740003 | G10: =IF(A10="","",IF(D10>F10,"⚠ BREACH","")) | I10: =IF(A10="","",TEXT(A10,"MMM YYYY")) -> Mar 2023 | J10: =IF(A10="","",D10) -> 0.00050709939 | K10: =IF(A10="","",E10) -> 0.0002761998 | L10: =IF(A10="","",F10) -> 0.0023740003
A11: =IF(A10="","",IF(EDATE(A10,1)>EOMONTH(Config!$C$9,0),"",EDATE(A10,1))) -> 45017 | B11: =IF(A11="","",COUNTIFS(complaints!$B$2:$B$928,">="&A11,complaints!$B$2:$B$928,"<="&EOMONTH(A11,0),complaints!$B$2:$B$928,"<>"&"")) -> 1 | C11: =IF(A11="","",SUMIFS(Sales!$C$2:$C$78141,Sales!$D$2:$D$78141,YEAR(A11),Sales!$B$2:$B$78141,TEXT(A11,"MMMM"))) -> 1610 | D11: =IF(A11="","",IF(C11=0,IF(B11=0,0,B11),B11/C11)) -> 0.00062111801 | E11: =IF(A11="","",AVERAGEIF($D$2:$D$46,"<>")) -> 0.0002761998 | F11: {=IF(A11="","",AVERAGEIF($D$2:$D$46,"<>")+3*IFERROR(STDEV(IF($D$2:$D$46<>"", $D$2:$D$46)),0))} -> 0.0023740003 | G11: =IF(A11="","",IF(D11>F11,"⚠ BREACH","")) | I11: =IF(A11="","",TEXT(A11,"MMM YYYY")) -> Apr 2023 | J11: =IF(A11="","",D11) -> 0.00062111801 | K11: =IF(A11="","",E11) -> 0.0002761998 | L11: =IF(A11="","",F11) -> 0.0023740003
A12: =IF(A11="","",IF(EDATE(A11,1)>EOMONTH(Config!$C$9,0),"",EDATE(A11,1))) -> 45047 | B12: =IF(A12="","",COUNTIFS(complaints!$B$2:$B$928,">="&A12,complaints!$B$2:$B$928,"<="&EOMONTH(A12,0),complaints!$B$2:$B$928,"<>"&"")) -> 3 | C12: =IF(A12="","",SUMIFS(Sales!$C$2:$C$78141,Sales!$D$2:$D$78141,YEAR(A12),Sales!$B$2:$B$78141,TEXT(A12,"MMMM"))) -> 1777 | D12: =IF(A12="","",IF(C12=0,IF(B12=0,0,B12),B12/C12)) -> 0.0016882386 | E12: =IF(A12="","",AVERAGEIF($D$2:$D$46,"<>")) -> 0.0002761998 | F12: {=IF(A12="","",AVERAGEIF($D$2:$D$46,"<>")+3*IFERROR(STDEV(IF($D$2:$D$46<>"", $D$2:$D$46)),0))} -> 0.0023740003 | G12: =IF(A12="","",IF(D12>F12,"⚠ BREACH","")) | I12: =IF(A12="","",TEXT(A12,"MMM YYYY")) -> May 2023 | J12: =IF(A12="","",D12) -> 0.0016882386 | K12: =IF(A12="","",E12) -> 0.0002761998 | L12: =IF(A12="","",F12) -> 0.0023740003
A13: =IF(A12="","",IF(EDATE(A12,1)>EOMONTH(Config!$C$9,0),"",EDATE(A12,1))) -> 45078 | B13: =IF(A13="","",COUNTIFS(complaints!$B$2:$B$928,">="&A13,complaints!$B$2:$B$928,"<="&EOMONTH(A13,0),complaints!$B$2:$B$928,"<>"&"")) -> 6 | C13: =IF(A13="","",SUMIFS(Sales!$C$2:$C$78141,Sales!$D$2:$D$78141,YEAR(A13),Sales!$B$2:$B$78141,TEXT(A13,"MMMM"))) -> 1682 | D13: =IF(A13="","",IF(C13=0,IF(B13=0,0,B13),B13/C13)) -> 0.0035671819 | E13: =IF(A13="","",AVERAGEIF($D$2:$D$46,"<>")) -> 0.0002761998 | F13: {=IF(A13="","",AVERAGEIF($D$2:$D$46,"<>")+3*IFERROR(STDEV(IF($D$2:$D$46<>"", $D$2:$D$46)),0))} -> 0.0023740003 | G13: =IF(A13="","",IF(D13>F13,"⚠ BREACH","")) -> ⚠ BREACH | I13: =IF(A13="","",TEXT(A13,"MMM YYYY")) -> Jun 2023 | J13: =IF(A13="","",D13) -> 0.0035671819 | K13: =IF(A13="","",E13) -> 0.0002761998 | L13: =IF(A13="","",F13) -> 0.0023740003
A14: =IF(A13="","",IF(EDATE(A13,1)>EOMONTH(Config!$C$9,0),"",EDATE(A13,1))) -> 45108 | B14: =IF(A14="","",COUNTIFS(complaints!$B$2:$B$928,">="&A14,complaints!$B$2:$B$928,"<="&EOMONTH(A14,0),complaints!$B$2:$B$928,"<>"&"")) -> 0 | C14: =IF(A14="","",SUMIFS(Sales!$C$2:$C$78141,Sales!$D$2:$D$78141,YEAR(A14),Sales!$B$2:$B$78141,TEXT(A14,"MMMM"))) -> 1689 | D14: =IF(A14="","",IF(C14=0,IF(B14=0,0,B14),B14/C14)) -> 0 | E14: =IF(A14="","",AVERAGEIF($D$2:$D$46,"<>")) -> 0.0002761998 | F14: {=IF(A14="","",AVERAGEIF($D$2:$D$46,"<>")+3*IFERROR(STDEV(IF($D$2:$D$46<>"", $D$2:$D$46)),0))} -> 0.0023740003 | G14: =IF(A14="","",IF(D14>F14,"⚠ BREACH","")) | I14: =IF(A14="","",TEXT(A14,"MMM YYYY")) -> Jul 2023 | J14: =IF(A14="","",D14) -> 0 | K14: =IF(A14="","",E14) -> 0.0002761998 | L14: =IF(A14="","",F14) -> 0.0023740003
... A46: =IF(A45="","",IF(EDATE(A45,1)>EOMONTH(Config!$C$9,0),"",EDATE(A45,1))) | B46: =IF(A46="","",COUNTIFS(complaints!$B$2:$B$928,">="&A46,complaints!$B$2:$B$928,"<="&EOMONTH(A46,0),complaints!$B$2:$B$928,"<>"&"")) | C46: =IF(A46="","",SUMIFS(Sales!$C$2:$C$78141,Sales!$D$2:$D$78141,YEAR(A46),Sales!$B$2:$B$78141,TEXT(A46,"MMMM"))) | D46: =IF(A46="","",IF(C46=0,IF(B46=0,0,B46),B46/C46)) | E46: =IF(A46="","",AVERAGEIF($D$2:$D$46,"<>")) | F46: {=IF(A46="","",AVERAGEIF($D$2:$D$46,"<>")+3*IFERROR(STDEV(IF($D$2:$D$46<>"", $D$2:$D$46)),0))} | G46: =IF(A46="","",IF(D46>F46,"⚠ BREACH","")) | I46: =IF(A46="","",TEXT(A46,"MMM YYYY")) | J46: =IF(A46="","",D46) | K46: =IF(A46="","",E46) | L46: =IF(A46="","",F46)

Sheet sales tables
B1: slot | C1: =IF(OR(Config!$C$11="",Config!$C$12=""),"",TEXT(Config!$C$11,"MMM YYYY")&" – "&TEXT(Config!$C$12,"MMM YYYY")) | D1: =IF(Config!$C$8="","",TEXT(DATE(YEAR(Config!$C$8),MONTH(Config!$C$8),1),"MMM YYYY")&" – "&TEXT(EOMONTH(DATE(YEAR(Config!$C$8),12,1),0),"MMM YYYY")) -> Jul 2022 – Dec 2022 | E1: =IF(Config!$C$8="","",IF(YEAR(Config!$C$9)>YEAR(Config!$C$8),TEXT(DATE(YEAR(Config!$C$8)+1,1,1),"MMM YYYY")&" – "&IF(YEAR(Config!$C$8)+1=YEAR(Config!$C$9),TEXT(Config!$C$9,"MMM YYYY"),TEXT(EOMONTH(DATE(YEAR(Config!$C$8)+1,12,1),0),"MMM YYYY")),"")) -> Jan 2023 – Dec 2023 | F1: =IF(Config!$C$8="","",IF(YEAR(Config!$C$9)>YEAR(Config!$C$8)+1,TEXT(DATE(YEAR(Config!$C$8)+2,1,1),"MMM YYYY")&" – "&IF(YEAR(Config!$C$8)+2=YEAR(Config!$C$9),TEXT(Config!$C$9,"MMM YYYY"),TEXT(EOMONTH(DATE(YEAR(Config!$C$8)+2,12,1),0),"MMM YYYY")),"")) -> Jan 2024 – Dec 2024 | G1: =IF(Config!$C$8="","",IF(YEAR(Config!$C$9)>YEAR(Config!$C$8)+2,TEXT(DATE(YEAR(Config!$C$8)+3,1,1),"MMM YYYY")&" – "&IF(YEAR(Config!$C$8)+3=YEAR(Config!$C$9),TEXT(Config!$C$9,"MMM YYYY"),TEXT(EOMONTH(DATE(YEAR(Config!$C$8)+3,12,1),0),"MMM YYYY")),"")) -> Jan 2025 – Jun 2025 | H1: {=SUMPRODUCT((C1:G1<>"")*1)} -> 4
B2: Annual Number of Devices Sold by Region
B3: Region | C3: {=IF(COLUMN()-2>$H$1+1,"",IF(COLUMN()-2=$H$1+1,"% of Total",IFERROR(INDEX(_xlfn._xlws.FILTER($C$1:$G$1,$C$1:$G$1<>""),1,COLUMN()-2),"")))} -> Jul 2022 – Dec 2022 | D3: {=IF(COLUMN()-2>$H$1+1,"",IF(COLUMN()-2=$H$1+1,"% of Total",IFERROR(INDEX(_xlfn._xlws.FILTER($C$1:$G$1,$C$1:$G$1<>""),1,COLUMN()-2),"")))} -> Jan 2023 – Dec 2023 | E3: {=IF(COLUMN()-2>$H$1+1,"",IF(COLUMN()-2=$H$1+1,"% of Total",IFERROR(INDEX(_xlfn._xlws.FILTER($C$1:$G$1,$C$1:$G$1<>""),1,COLUMN()-2),"")))} -> Jan 2024 – Dec 2024 | F3: {=IF(COLUMN()-2>$H$1+1,"",IF(COLUMN()-2=$H$1+1,"% of Total",IFERROR(INDEX(_xlfn._xlws.FILTER($C$1:$G$1,$C$1:$G$1<>""),1,COLUMN()-2),"")))} -> Jan 2025 – Jun 2025 | G3: {=IF(COLUMN()-2>$H$1+1,"",IF(COLUMN()-2=$H$1+1,"% of Total",IFERROR(INDEX(_xlfn._xlws.FILTER($C$1:$G$1,$C$1:$G$1<>""),1,COLUMN()-2),"")))} -> % of Total | H3: {=IF(COLUMN()-2>$H$1+1,"",IF(COLUMN()-2=$H$1+1,"% of Total",IFERROR(INDEX(_xlfn._xlws.FILTER($C$1:$G$1,$C$1:$G$1<>""),1,COLUMN()-2),"")))}
B6: EEA ¹ + TR ² + XI ³ | C6: {=IF(COLUMN()-2>$H$1+1,"",IF(COLUMN()-2=$H$1+1,IF(SUM($D$92:$G$92)=0,"-",(IF(ISNUMBER(D82),D82,0)+IF(ISNUMBER(E82),E82,0)+IF(ISNUMBER(F82),F82,0)+IF(ISNUMBER(G82),G82,0))/SUM($D$92:$G$92)),IFERROR(INDEX(_xlfn._xlws.FILTER($C82:$G82,$C$1:$G$1<>""),1,COLUMN()-2),"")))} -> 0 | D6: {=IF(COLUMN()-2>$H$1+1,"",IF(COLUMN()-2=$H$1+1,IF(SUM($D$92:$G$92)=0,"-",(IF(ISNUMBER(D82),D82,0)+IF(ISNUMBER(E82),E82,0)+IF(ISNUMBER(F82),F82,0)+IF(ISNUMBER(G82),G82,0))/SUM($D$92:$G$92)),IFERROR(INDEX(_xlfn._xlws.FILTER($C82:$G82,$C$1:$G$1<>""),1,COLUMN()-2),"")))} -> 0 | E6: {=IF(COLUMN()-2>$H$1+1,"",IF(COLUMN()-2=$H$1+1,IF(SUM($D$92:$G$92)=0,"-",(IF(ISNUMBER(D82),D82,0)+IF(ISNUMBER(E82),E82,0)+IF(ISNUMBER(F82),F82,0)+IF(ISNUMBER(G82),G82,0))/SUM($D$92:$G$92)),IFERROR(INDEX(_xlfn._xlws.FILTER($C82:$G82,$C$1:$G$1<>""),1,COLUMN()-2),"")))} -> 0 | F6: {=IF(COLUMN()-2>$H$1+1,"",IF(COLUMN()-2=$H$1+1,IF(SUM($D$92:$G$92)=0,"-",(IF(ISNUMBER(D82),D82,0)+IF(ISNUMBER(E82),E82,0)+IF(ISNUMBER(F82),F82,0)+IF(ISNUMBER(G82),G82,0))/SUM($D$92:$G$92)),IFERROR(INDEX(_xlfn._xlws.FILTER($C82:$G82,$C$1:$G$1<>""),1,COLUMN()-2),"")))} -> 0 | G6: {=IF(COLUMN()-2>$H$1+1,"",IF(COLUMN()-2=$H$1+1,IF(SUM($D$92:$G$92)=0,"-",(IF(ISNUMBER(D82),D82,0)+IF(ISNUMBER(E82),E82,0)+IF(ISNUMBER(F82),F82,0)+IF(ISNUMBER(G82),G82,0))/SUM($D$92:$G$92)),IFERROR(INDEX(_xlfn._xlws.FILTER($C82:$G82,$C$1:$G$1<>""),1,COLUMN()-2),"")))} -> 0 | H6: {=IF(COLUMN()-2>$H$1+1,"",IF(COLUMN()-2=$H$1+1,IF(SUM($D$92:$G$92)=0,"-",(IF(ISNUMBER(D82),D82,0)+IF(ISNUMBER(E82),E82,0)+IF(ISNUMBER(F82),F82,0)+IF(ISNUMBER(G82),G82,0))/SUM($D$92:$G$92)),IFERROR(INDEX(_xlfn._xlws.FILTER($C82:$G82,$C$1:$G$1<>""),1,COLUMN()-2),"")))}
B7: Australia | C7: {=IF(COLUMN()-2>$H$1+1,"",IF(COLUMN()-2=$H$1+1,IF(SUM($D$92:$G$92)=0,"-",(IF(ISNUMBER(D83),D83,0)+IF(ISNUMBER(E83),E83,0)+IF(ISNUMBER(F83),F83,0)+IF(ISNUMBER(G83),G83,0))/SUM($D$92:$G$92)),IFERROR(INDEX(_xlfn._xlws.FILTER($C83:$G83,$C$1:$G$1<>""),1,COLUMN()-2),"")))} -> 0 | D7: {=IF(COLUMN()-2>$H$1+1,"",IF(COLUMN()-2=$H$1+1,IF(SUM($D$92:$G$92)=0,"-",(IF(ISNUMBER(D83),D83,0)+IF(ISNUMBER(E83),E83,0)+IF(ISNUMBER(F83),F83,0)+IF(ISNUMBER(G83),G83,0))/SUM($D$92:$G$92)),IFERROR(INDEX(_xlfn._xlws.FILTER($C83:$G83,$C$1:$G$1<>""),1,COLUMN()-2),"")))} -> 0 | E7: {=IF(COLUMN()-2>$H$1+1,"",IF(COLUMN()-2=$H$1+1,IF(SUM($D$92:$G$92)=0,"-",(IF(ISNUMBER(D83),D83,0)+IF(ISNUMBER(E83),E83,0)+IF(ISNUMBER(F83),F83,0)+IF(ISNUMBER(G83),G83,0))/SUM($D$92:$G$92)),IFERROR(INDEX(_xlfn._xlws.FILTER($C83:$G83,$C$1:$G$1<>""),1,COLUMN()-2),"")))} -> 0 | F7: {=IF(COLUMN()-2>$H$1+1,"",IF(COLUMN()-2=$H$1+1,IF(SUM($D$92:$G$92)=0,"-",(IF(ISNUMBER(D83),D83,0)+IF(ISNUMBER(E83),E83,0)+IF(ISNUMBER(F83),F83,0)+IF(ISNUMBER(G83),G83,0))/SUM($D$92:$G$92)),IFERROR(INDEX(_xlfn._xlws.FILTER($C83:$G83,$C$1:$G$1<>""),1,COLUMN()-2),"")))} -> 0 | G7: {=IF(COLUMN()-2>$H$1+1,"",IF(COLUMN()-2=$H$1+1,IF(SUM($D$92:$G$92)=0,"-",(IF(ISNUMBER(D83),D83,0)+IF(ISNUMBER(E83),E83,0)+IF(ISNUMBER(F83),F83,0)+IF(ISNUMBER(G83),G83,0))/SUM($D$92:$G$92)),IFERROR(INDEX(_xlfn._xlws.FILTER($C83:$G83,$C$1:$G$1<>""),1,COLUMN()-2),"")))} -> 0 | H7: {=IF(COLUMN()-2>$H$1+1,"",IF(COLUMN()-2=$H$1+1,IF(SUM($D$92:$G$92)=0,"-",(IF(ISNUMBER(D83),D83,0)+IF(ISNUMBER(E83),E83,0)+IF(ISNUMBER(F83),F83,0)+IF(ISNUMBER(G83),G83,0))/SUM($D$92:$G$92)),IFERROR(INDEX(_xlfn._xlws.FILTER($C83:$G83,$C$1:$G$1<>""),1,COLUMN()-2),"")))}
